Workbook

Sheet Coverage
A1: Coverage summary (formulas read the Opportunities sheet)
A2: As-of date | B2: 46307
A4: Active rows (action create or update_existing) | B4: =COUNTIFS(Opportunities!$C$2:$C$161,"<>exclude")
A5: Excluded rows | B5: =COUNTIFS(Opportunities!$C$2:$C$161,"exclude")
A6: Total rows | B6: =B4+B5
A7: Active rows with a known deadline | B7: =COUNTIFS(Opportunities!$C$2:$C$161,"<>exclude",Opportunities!$U$2:$U$161,">0")
A8: Closing within 3 days | B8: =COUNTIFS(Opportunities!$C$2:$C$161,"<>exclude",Opportunities!$U$2:$U$161,">="&$B$2,Opportunities!$U$2:$U$161,"<="&$B$2+3)
A9: Closing within 7 days | B9: =COUNTIFS(Opportunities!$C$2:$C$161,"<>exclude",Opportunities!$U$2:$U$161,">="&$B$2,Opportunities!$U$2:$U$161,"<="&$B$2+7)
A10: Closing within 30 days | B10: =COUNTIFS(Opportunities!$C$2:$C$161,"<>exclude",Opportunities!$U$2:$U$161,">="&$B$2,Opportunities!$U$2:$U$161,"<="&$B$2+30)
A11: Leads with no deadline seen | B11: =COUNTIFS(Opportunities!$AT$2:$AT$161,"lead_no_deadline")
A13: Active rows by category and region tier
A14: category | B14: uganda | C14: east_africa | D14: africa | E14: global | F14: total
A15: job | B15: =COUNTIFS(Opportunities!$H$2:$H$161,$A15,Opportunities!$AR$2:$AR$161,B$14,Opportunities!$C$2:$C$161,"<>exclude") | C15: =COUNTIFS(Opportunities!$H$2:$H$161,$A15,Opportunities!$AR$2:$AR$161,C$14,Opportunities!$C$2:$C$161,"<>exclude") | D15: =COUNTIFS(Opportunities!$H$2:$H$161,$A15,Opportunities!$AR$2:$AR$161,D$14,Opportunities!$C$2:$C$161,"<>exclude") | E15: =COUNTIFS(Opportunities!$H$2:$H$161,$A15,Opportunities!$AR$2:$AR$161,E$14,Opportunities!$C$2:$C$161,"<>exclude") | F15: =SUM(B15:E15)
A16: internship | B16: =COUNTIFS(Opportunities!$H$2:$H$161,$A16,Opportunities!$AR$2:$AR$161,B$14,Opportunities!$C$2:$C$161,"<>exclude") | C16: =COUNTIFS(Opportunities!$H$2:$H$161,$A16,Opportunities!$AR$2:$AR$161,C$14,Opportunities!$C$2:$C$161,"<>exclude") | D16: =COUNTIFS(Opportunities!$H$2:$H$161,$A16,Opportunities!$AR$2:$AR$161,D$14,Opportunities!$C$2:$C$161,"<>exclude") | E16: =COUNTIFS(Opportunities!$H$2:$H$161,$A16,Opportunities!$AR$2:$AR$161,E$14,Opportunities!$C$2:$C$161,"<>exclude") | F16: =SUM(B16:E16)
A17: scholarship | B17: =COUNTIFS(Opportunities!$H$2:$H$161,$A17,Opportunities!$AR$2:$AR$161,B$14,Opportunities!$C$2:$C$161,"<>exclude") | C17: =COUNTIFS(Opportunities!$H$2:$H$161,$A17,Opportunities!$AR$2:$AR$161,C$14,Opportunities!$C$2:$C$161,"<>exclude") | D17: =COUNTIFS(Opportunities!$H$2:$H$161,$A17,Opportunities!$AR$2:$AR$161,D$14,Opportunities!$C$2:$C$161,"<>exclude") | E17: =COUNTIFS(Opportunities!$H$2:$H$161,$A17,Opportunities!$AR$2:$AR$161,E$14,Opportunities!$C$2:$C$161,"<>exclude") | F17: =SUM(B17:E17)
A18: fellowship | B18: =COUNTIFS(Opportunities!$H$2:$H$161,$A18,Opportunities!$AR$2:$AR$161,B$14,Opportunities!$C$2:$C$161,"<>exclude") | C18: =COUNTIFS(Opportunities!$H$2:$H$161,$A18,Opportunities!$AR$2:$AR$161,C$14,Opportunities!$C$2:$C$161,"<>exclude") | D18: =COUNTIFS(Opportunities!$H$2:$H$161,$A18,Opportunities!$AR$2:$AR$161,D$14,Opportunities!$C$2:$C$161,"<>exclude") | E18: =COUNTIFS(Opportunities!$H$2:$H$161,$A18,Opportunities!$AR$2:$AR$161,E$14,Opportunities!$C$2:$C$161,"<>exclude") | F18: =SUM(B18:E18)
A19: grant | B19: =COUNTIFS(Opportunities!$H$2:$H$161,$A19,Opportunities!$AR$2:$AR$161,B$14,Opportunities!$C$2:$C$161,"<>exclude") | C19: =COUNTIFS(Opportunities!$H$2:$H$161,$A19,Opportunities!$AR$2:$AR$161,C$14,Opportunities!$C$2:$C$161,"<>exclude") | D19: =COUNTIFS(Opportunities!$H$2:$H$161,$A19,Opportunities!$AR$2:$AR$161,D$14,Opportunities!$C$2:$C$161,"<>exclude") | E19: =COUNTIFS(Opportunities!$H$2:$H$161,$A19,Opportunities!$AR$2:$AR$161,E$14,Opportunities!$C$2:$C$161,"<>exclude") | F19: =SUM(B19:E19)
A20: training | B20: =COUNTIFS(Opportunities!$H$2:$H$161,$A20,Opportunities!$AR$2:$AR$161,B$14,Opportunities!$C$2:$C$161,"<>exclude") | C20: =COUNTIFS(Opportunities!$H$2:$H$161,$A20,Opportunities!$AR$2:$AR$161,C$14,Opportunities!$C$2:$C$161,"<>exclude") | D20: =COUNTIFS(Opportunities!$H$2:$H$161,$A20,Opportunities!$AR$2:$AR$161,D$14,Opportunities!$C$2:$C$161,"<>exclude") | E20: =COUNTIFS(Opportunities!$H$2:$H$161,$A20,Opportunities!$AR$2:$AR$161,E$14,Opportunities!$C$2:$C$161,"<>exclude") | F20: =SUM(B20:E20)
A21: consultancy | B21: =COUNTIFS(Opportunities!$H$2:$H$161,$A21,Opportunities!$AR$2:$AR$161,B$14,Opportunities!$C$2:$C$161,"<>exclude") | C21: =COUNTIFS(Opportunities!$H$2:$H$161,$A21,Opportunities!$AR$2:$AR$161,C$14,Opportunities!$C$2:$C$161,"<>exclude") | D21: =COUNTIFS(Opportunities!$H$2:$H$161,$A21,Opportunities!$AR$2:$AR$161,D$14,Opportunities!$C$2:$C$161,"<>exclude") | E21: =COUNTIFS(Opportunities!$H$2:$H$161,$A21,Opportunities!$AR$2:$AR$161,E$14,Opportunities!$C$2:$C$161,"<>exclude") | F21: =SUM(B21:E21)
A22: total | B22: =SUM(B15:B21) | C22: =SUM(C15:C21) | D22: =SUM(D15:D21) | E22: =SUM(E15:E21) | F22: =SUM(F15:F21)
A24: Cohort notes
A25: Strong this run: Uganda entry-level and graduate-trainee jobs, and Africa-eligible fellowships and grants from a live feed.
A26: Thin: vocational, trades, hospitality and agriculture jobs outside Kampala; Kenya, Tanzania and Rwanda jobs (index pages only); paid apprenticeships; first-hand scholarship pages from official funders.
A27: No row is marked verified. Every active row needs the provider-owned listing found and checked (see Agent_Check_Plan and README.md).

Sheet Opportunities
A1: record_key | B1: existing_opportunity_id | C1: action | D1: title | E1: organization_name | F1: organization_official_url | G1: organization_reference | H1: category | I1: applicant_type | J1: description | K1: eligibility_json | L1: required_skills_json | M1: preferred_skills_json | N1: location | O1: eligible_countries_json | P1: work_mode | Q1: work_mode_evidence | R1: compensation_status | S1: compensation_details | T1: deadline_utc | U1: deadline_date | V1: deadline_original_text | W1: deadline_timezone | X1: deadline_precision | Y1: deadline_type | Z1: application_method | AA1: application_url | AB1: source_url | AC1: additional_source_urls_json | AD1: source_publication_date | AE1: checked_at_utc | AF1: source | AG1: verification_status | AH1: source_authentic | AI1: no_inappropriate_fees | AJ1: no_sensitive_data_ask | AK1: deadline_plausible | AL1: duplicate_checked | AM1: evidence_json | AN1: additional_costs | AO1: unresolved_requirements_json | AP1: review_notes | AQ1: import_ready | AR1: region_tier | AS1: source_family | AT1: lead_status | AU1: agent_verdict | AV1: agent_checked_at_utc | AW1: official_listing_url | AX1: value_score_0_100 | AY1: effort_score_0_100 | AZ1: risk_score_0_100 | BA1: evidence_files
A2: jentroy-software-dev-intern-2026-10 | C2: create | D2: Software Development Intern (Graduate Program) | E2: Jentroy Uganda | H2: internship | I2: individual | J2: Graduate software development internship in Kampala. Applicants email a CV with a GitHub or portfolio link if available, using the subject line Graduate Intern. | K2: {"educationLevels":["bachelors"]} | N2: Kampala, Uganda | R2: unknown | T2: 2026-10-15T14:00:00Z | U2: 46310 | V2: Deadline: 15th October 2026 at 5:00 PM (EAT) | W2: EAT (UTC+3) | X2: datetime | Y2: fixed | Z2: Email CV (plus GitHub or portfolio link) with subject line Graduate Intern; exact address not captured. | AB2: https://theugandanjobline.com/2026/10/software-development-intern-graduate-program-jobs-jentroy-uganda.html | AC2: [] | AD2: 2026-10-05 | AE2: 2026-10-10T12:00:00Z | AF2: scraped | AG2: pending | AH2: =FALSE() | AI2: =FALSE() | AJ2: =FALSE() | AK2: =TRUE() | AL2: =TRUE() | AM2: {"sourceAuthentic":{"urls":["https://theugandanjobline.com/2026/10/software-development-intern-graduate-program-jobs-jentroy-uganda.html"],"rationale":"Seen on The Ugandan Jobline, a third-party or index page. Provider-owned listing not yet located, so authenticity is unconfirmed.","checkedAtUtc":"2026-10-10T12:00:00Z"},"noInappropriateFees":{"urls":["https://theugandanjobline.com/2026/10/software-development-intern-graduate-program-jobs-jentroy-uganda.html"],"rationale":"The summary text retrieved mentions no fee, but the provider page was not reviewed, so this is unconfirmed.","checkedAtUtc":"2026-10-10T12:00:00Z"},"noSensitiveDataAsk":{"urls":["https://theugandanjobline.com/2026/10/software-development-intern-graduate-program-jobs-jentroy-uganda.html"],"rationale":"The retrieved summary asks for no passwords, codes or payments, but full application instructions were not reviewed.","checkedAtUtc":"2026-10-10T12:00:00Z"},"deadlinePlausible":{"urls":["https://theugandanjobline.com/2026/10/software-development-intern-graduate-program-jobs-jentroy-uganda.html"],"rationale":"Source states 'Deadline: 15th October 2026 at 5:00 PM (EAT)', which falls on or after the delivery date 2026-10-12. Not cross-checked against the provider page.","checkedAtUtc":"2026-10-10T12:00:00Z"},"duplicateChecked":{"urls":[],"rationale":"Title compared with all 115 catalog records and every row in this file using the app's bigram rule (threshold 0.85, 3-day window). Closest catalog title: 'Programme Development Manager' at 0.606.","checkedAtUtc":"2026-10-10T12:00:00Z"}} | AO2: ["Locate the provider-owned listing and the official application link","Confirm no application, processing or placement fee on the official page","Confirm no inappropriate sensitive-data request on the official page","Confirm closing date and timezone on the official page","Compensation not stated","Employer official site and email address not captured"] | AP2: Source page structured data lists a bachelor degree requirement. Only shortlisted candidates are contacted. | AQ2: =FALSE() | AR2: uganda | AS2: theugandanjobline.com | AT2: open_with_deadline | AU2: unresolved | AV2: 2026-10-12T09:15:53Z
A3: natgas-graduate-trainee-software-engineer-2026-10 | C3: create | D3: Graduate Trainee, Software Engineer (2 positions) | E3: NATGAS Uganda | H3: job | I3: individual | J3: Two fresh-graduate trainee software engineer positions advertised by NATGAS Uganda. | N3: Uganda (town not confirmed) | R3: unknown | U3: 46325 | V3: Closes 30 Oct | W3: unknown | X3: date | Y3: fixed | Z3: Apply as described on the source listing; the official application route is not yet confirmed. | AB3: https://theugandanjobline.com/2026/10/graduate-trainee-software-engineer-2-fresh-graduate-positions-jobs-natgas-uganda.html | AC3: [] | AE3: 2026-10-10T12:00:00Z | AF3: scraped | AG3: pending | AH3: =FALSE() | AI3: =FALSE() | AJ3: =FALSE() | AK3: =TRUE() | AL3: =TRUE() | AM3: {"sourceAuthentic":{"urls":["https://theugandanjobline.com/2026/10/graduate-trainee-software-engineer-2-fresh-graduate-positions-jobs-natgas-uganda.html"],"rationale":"Seen on The Ugandan Jobline, a third-party or index page. Provider-owned listing not yet located, so authenticity is unconfirmed.","checkedAtUtc":"2026-10-10T12:00:00Z"},"noInappropriateFees":{"urls":["https://theugandanjobline.com/2026/10/graduate-trainee-software-engineer-2-fresh-graduate-positions-jobs-natgas-uganda.html"],"rationale":"The summary text retrieved mentions no fee, but the provider page was not reviewed, so this is unconfirmed.","checkedAtUtc":"2026-10-10T12:00:00Z"},"noSensitiveDataAsk":{"urls":["https://theugandanjobline.com/2026/10/graduate-trainee-software-engineer-2-fresh-graduate-positions-jobs-natgas-uganda.html"],"rationale":"The retrieved summary asks for no passwords, codes or payments, but full application instructions were not reviewed.","checkedAtUtc":"2026-10-10T12:00:00Z"},"deadlinePlausible":{"urls":["https://theugandanjobline.com/2026/10/graduate-trainee-software-engineer-2-fresh-graduate-positions-jobs-natgas-uganda.html"],"rationale":"Source states 'Closes 30 Oct', which falls on or after the delivery date 2026-10-12. Not cross-checked against the provider page.","checkedAtUtc":"2026-10-10T12:00:00Z"},"duplicateChecked":{"urls":[],"rationale":"Title compared with all 115 catalog records and every row in this file using the app's bigram rule (threshold 0.85, 3-day window). Closest catalog title: 'Senior Business Support Associate (Fleet & Training), G7, Kampala' at 0.413.","checkedAtUtc":"2026-10-10T12:00:00Z"}} | AO3: ["Locate the provider-owned listing and the official application link","Confirm no application, processing or placement fee on the official page","Confirm no inappropriate sensitive-data request on the official page","Confirm closing date and timezone on the official page","Duty station, qualifications and pay not captured"] | AP3: Listing page snapshot seen 2026-10-10; some Ugandan Jobline index pages were 1 to 2 weeks old, so reconfirm the deadline on the employer page. | AQ3: =FALSE() | AR3: uganda | AS3: theugandanjobline.com | AT3: open_with_deadline | AU3: unresolved | AV3: 2026-10-12T09:15:53Z
A4: eacop-gis-graduate-trainee-2026-10 | C4: create | D4: GIS Graduate Trainee | E4: East African Crude Oil Pipeline (EACOP) | H4: job | I4: individual | J4: Graduate trainee role in GIS with the East African Crude Oil Pipeline company, tagged no experience required. | N4: Uganda (town not confirmed) | R4: unknown | U4: 46313 | V4: Closes 18 Oct | W4: unknown | X4: date | Y4: fixed | Z4: Apply as described on the source listing; the official application route is not yet confirmed. | AB4: https://theugandanjobline.com/2026/10/gis-graduate-trainee-no-experience-jobs-jobs-east-african-crude-oil-pipeline.html | AC4: [] | AE4: 2026-10-10T12:00:00Z | AF4: scraped | AG4: pending | AH4: =FALSE() | AI4: =FALSE() | AJ4: =FALSE() | AK4: =TRUE() | AL4: =TRUE() | AM4: {"sourceAuthentic":{"urls":["https://theugandanjobline.com/2026/10/gis-graduate-trainee-no-experience-jobs-jobs-east-african-crude-oil-pipeline.html"],"rationale":"Seen on The Ugandan Jobline, a third-party or index page. Provider-owned listing not yet located, so authenticity is unconfirmed.","checkedAtUtc":"2026-10-10T12:00:00Z"},"noInappropriateFees":{"urls":["https://theugandanjobline.com/2026/10/gis-graduate-trainee-no-experience-jobs-jobs-east-african-crude-oil-pipeline.html"],"rationale":"The summary text retrieved mentions no fee, but the provider page was not reviewed, so this is unconfirmed.","checkedAtUtc":"2026-10-10T12:00:00Z"},"noSensitiveDataAsk":{"urls":["https://theugandanjobline.com/2026/10/gis-graduate-trainee-no-experience-jobs-jobs-east-african-crude-oil-pipeline.html"],"rationale":"The retrieved summary asks for no passwords, codes or payments, but full application instructions were not reviewed.","checkedAtUtc":"2026-10-10T12:00:00Z"},"deadlinePlausible":{"urls":["https://theugandanjobline.com/2026/10/gis-graduate-trainee-no-experience-jobs-jobs-east-african-crude-oil-pipeline.html"],"rationale":"Source states 'Closes 18 Oct', which falls on or after the delivery date 2026-10-12. Not cross-checked against the provider page.","checkedAtUtc":"2026-10-10T12:00:00Z"},"duplicateChecked":{"urls":[],"rationale":"Title compared with all 115 catalog records and every row in this file using the app's bigram rule (threshold 0.85, 3-day window). Closest catalog title: 'Brain Awareness Week Grants' at 0.372.","checkedAtUtc":"2026-10-10T12:00:00Z"}} | AO4: ["Locate the provider-owned listing and the official application link","Confirm no application, processing or placement fee on the official page","Confirm no inappropriate sensitive-data request on the official page","Confirm closing date and timezone on the official page","Qualifications, pay and duty station not captured"] | AP4: EACOP is a politically and environmentally contested project; agent should still verify the posting on the official EACOP careers site. Listing page snapshot seen 2026-10-10; some Ugandan Jobline index pages were 1 to 2 weeks old, so reconfirm the deadline on the employer page. | AQ4: =FALSE() | AR4: uganda | AS4: theugandanjobline.com | AT4: open_with_deadline | AU4: unresolved | AV4: 2026-10-12T09:15:53Z
A5: eacop-hr-graduate-trainee-2026-10 | C5: create | D5: Human Resource Graduate Trainee | E5: East African Crude Oil Pipeline (EACOP) | H5: job | I5: individual | J5: Graduate trainee role in human resources with the East African Crude Oil Pipeline company, tagged no experience required and contract. | N5: Uganda (town not confirmed) | R5: unknown | U5: 46313 | V5: Closes 18 Oct | W5: unknown | X5: date | Y5: fixed | Z5: Apply as described on the source listing; the official application route is not yet confirmed. | AB5: https://theugandanjobline.com/2026/10/human-resource-graduate-trainee-no-experience-jobs-jobs-east-african-crude-oil-pipeline.html | AC5: [] | AE5: 2026-10-10T12:00:00Z | AF5: scraped | AG5: pending | AH5: =FALSE() | AI5: =FALSE() | AJ5: =FALSE() | AK5: =TRUE() | AL5: =TRUE() | AM5: {"sourceAuthentic":{"urls":["https://theugandanjobline.com/2026/10/human-resource-graduate-trainee-no-experience-jobs-jobs-east-african-crude-oil-pipeline.html"],"rationale":"Seen on The Ugandan Jobline, a third-party or index page. Provider-owned listing not yet located, so authenticity is unconfirmed.","checkedAtUtc":"2026-10-10T12:00:00Z"},"noInappropriateFees":{"urls":["https://theugandanjobline.com/2026/10/human-resource-graduate-trainee-no-experience-jobs-jobs-east-african-crude-oil-pipeline.html"],"rationale":"The summary text retrieved mentions no fee, but the provider page was not reviewed, so this is unconfirmed.","checkedAtUtc":"2026-10-10T12:00:00Z"},"noSensitiveDataAsk":{"urls":["https://theugandanjobline.com/2026/10/human-resource-graduate-trainee-no-experience-jobs-jobs-east-african-crude-oil-pipeline.html"],"rationale":"The retrieved summary asks for no passwords, codes or payments, but full application instructions were not reviewed.","checkedAtUtc":"2026-10-10T12:00:00Z"},"deadlinePlausible":{"urls":["https://theugandanjobline.com/2026/10/human-resource-graduate-trainee-no-experience-jobs-jobs-east-african-crude-oil-pipeline.html"],"rationale":"Source states 'Closes 18 Oct', which falls on or after the delivery date 2026-10-12. Not cross-checked against the provider page.","checkedAtUtc":"2026-10-10T12:00:00Z"},"duplicateChecked":{"urls":[],"rationale":"Title compared with all 115 catalog records and every row in this file using the app's bigram rule (threshold 0.85, 3-day window). Closest catalog title: 'Hinrich Foundation Trade Research Grants' at 0.5.","checkedAtUtc":"2026-10-10T12:00:00Z"}} | AO5: ["Locate the provider-owned listing and the official application link","Confirm no application, processing or placement fee on the official page","Confirm no inappropriate sensitive-data request on the official page","Confirm closing date and timezone on the official page","Qualifications, pay and duty station not captured"] | AP5: Listing page snapshot seen 2026-10-10; some Ugandan Jobline index pages were 1 to 2 weeks old, so reconfirm the deadline on the employer page. | AQ5: =FALSE() | AR5: uganda | AS5: theugandanjobline.com | AT5: open_with_deadline | AU5: unresolved | AV5: 2026-10-12T09:15:53Z
A6: mayfair-insurance-ict-graduate-trainee-2026-10 | C6: create | D6: Graduate Trainee, ICT | E6: Mayfair Insurance | H6: job | I6: individual | J6: ICT graduate trainee position at Mayfair Insurance. | N6: Uganda (town not confirmed) | R6: unknown | U6: 46307 | V6: Closes 12 Oct | W6: unknown | X6: date | Y6: fixed | Z6: Apply as described on the source listing; the official application route is not yet confirmed. | AB6: https://theugandanjobline.com/2026/10/graduate-trainee-ict-jobs-mayfair-insurance.html | AC6: [] | AE6: 2026-10-10T12:00:00Z | AF6: scraped | AG6: pending | AH6: =FALSE() | AI6: =FALSE() | AJ6: =FALSE() | AK6: =TRUE() | AL6: =TRUE() | AM6: {"sourceAuthentic":{"urls":["https://theugandanjobline.com/2026/10/graduate-trainee-ict-jobs-mayfair-insurance.html"],"rationale":"Seen on The Ugandan Jobline, a third-party or index page. Provider-owned listing not yet located, so authenticity is unconfirmed.","checkedAtUtc":"2026-10-10T12:00:00Z"},"noInappropriateFees":{"urls":["https://theugandanjobline.com/2026/10/graduate-trainee-ict-jobs-mayfair-insurance.html"],"rationale":"The summary text retrieved mentions no fee, but the provider page was not reviewed, so this is unconfirmed.","checkedAtUtc":"2026-10-10T12:00:00Z"},"noSensitiveDataAsk":{"urls":["https://theugandanjobline.com/2026/10/graduate-trainee-ict-jobs-mayfair-insurance.html"],"rationale":"The retrieved summary asks for no passwords, codes or payments, but full application instructions were not reviewed.","checkedAtUtc":"2026-10-10T12:00:00Z"},"deadlinePlausible":{"urls":["https://theugandanjobline.com/2026/10/graduate-trainee-ict-jobs-mayfair-insurance.html"],"rationale":"Source states 'Closes 12 Oct', which falls on or after the delivery date 2026-10-12. Not cross-checked against the provider page.","checkedAtUtc":"2026-10-10T12:00:00Z"},"duplicateChecked":{"urls":[],"rationale":"Title compared with all 115 catalog records and every row in this file using the app's bigram rule (threshold 0.85, 3-day window). Closest catalog title: 'Hinrich Foundation Trade Research Grants' at 0.34.","checkedAtUtc":"2026-10-10T12:00:00Z"}} | AO6: ["Locate the provider-owned listing and the official application link","Confirm no application, processing or placement fee on the official page","Confirm no inappropriate sensitive-data request on the official page","Confirm closing date and timezone on the official page","Qualifications and pay not captured"] | AP6: Closes today (2026-10-12), re-check immediately. Short window at retrieval. Listing page snapshot seen 2026-10-10; some Ugandan Jobline index pages were 1 to 2 weeks old, so reconfirm the deadline on the employer page. | AQ6: =FALSE() | AR6: uganda | AS6: theugandanjobline.com | AT6: open_with_deadline | AU6: unresolved | AV6: 2026-10-12T09:15:53Z
A7: uetcl-esi-graduate-skills-programme-2026-10 | C7: create | D7: UETCL ESI Graduate Skills Development Programme | E7: Uganda Electricity Transmission Company Limited (UETCL) | H7: training | I7: individual | J7: Graduate skills development programme advertised by UETCL, tagged no experience required. | N7: Uganda (town not confirmed) | R7: unknown | U7: 46308 | V7: Closes 13 Oct | W7: unknown | X7: date | Y7: fixed | Z7: Apply as described on the source listing; the official application route is not yet confirmed. | AB7: https://theugandanjobline.com/2026/10/uetcl-esi-graduate-skills-development-programme-no-experience-jobs-jobs-uganda-electricity-transmission-company-limited-uetcl.html | AC7: [] | AE7: 2026-10-10T12:00:00Z | AF7: scraped | AG7: pending | AH7: =FALSE() | AI7: =FALSE() | AJ7: =FALSE() | AK7: =TRUE() | AL7: =TRUE() | AM7: {"sourceAuthentic":{"urls":["https://theugandanjobline.com/2026/10/uetcl-esi-graduate-skills-development-programme-no-experience-jobs-jobs-uganda-electricity-transmission-company-limited-uetcl.html"],"rationale":"Seen on The Ugandan Jobline, a third-party or index page. Provider-owned listing not yet located, so authenticity is unconfirmed.","checkedAtUtc":"2026-10-10T12:00:00Z"},"noInappropriateFees":{"urls":["https://theugandanjobline.com/2026/10/uetcl-esi-graduate-skills-development-programme-no-experience-jobs-jobs-uganda-electricity-transmission-company-limited-uetcl.html"],"rationale":"The summary text retrieved mentions no fee, but the provider page was not reviewed, so this is unconfirmed.","checkedAtUtc":"2026-10-10T12:00:00Z"},"noSensitiveDataAsk":{"urls":["https://theugandanjobline.com/2026/10/uetcl-esi-graduate-skills-development-programme-no-experience-jobs-jobs-uganda-electricity-transmission-company-limited-uetcl.html"],"rationale":"The retrieved summary asks for no passwords, codes or payments, but full application instructions were not reviewed.","checkedAtUtc":"2026-10-10T12:00:00Z"},"deadlinePlausible":{"urls":["https://theugandanjobline.com/2026/10/uetcl-esi-graduate-skills-development-programme-no-experience-jobs-jobs-uganda-electricity-transmission-company-limited-uetcl.html"],"rationale":"Source states 'Closes 13 Oct', which falls on or after the delivery date 2026-10-12. Not cross-checked against the provider page.","checkedAtUtc":"2026-10-10T12:00:00Z"},"duplicateChecked":{"urls":[],"rationale":"Title compared with all 115 catalog records and every row in this file using the app's bigram rule (threshold 0.85, 3-day window). Closest catalog title: 'Programme Development Manager' at 0.571.","checkedAtUtc":"2026-10-10T12:00:00Z"}} | AO7: ["Locate the provider-owned listing and the official application link","Confirm no application, processing or placement fee on the official page","Confirm no inappropriate sensitive-data request on the official page","Confirm closing date and timezone on the official page","Paid or unpaid not stated","Eligibility not captured"] | AP7: Category set to training because it is a skills programme; confirm whether paid. Listing page snapshot seen 2026-10-10; some Ugandan Jobline index pages were 1 to 2 weeks old, so reconfirm the deadline on the employer page. | AQ7: =FALSE() | AR7: uganda | AS7: theugandanjobline.com | AT7: open_with_deadline | AU7: unresolved | AV7: 2026-10-12T09:15:53Z
A8: uetcl-communication-engineer-2026-10 | C8: create | D8: Communication Engineer (Transmission and Access System) | E8: Uganda Electricity Transmission Company Limited (UETCL) | H8: job | I8: individual | J8: Engineering role in transmission and access communications at UETCL. | N8: Uganda (town not confirmed) | R8: unknown | U8: 46316 | V8: Closes 21 Oct | W8: unknown | X8: date | Y8: fixed | Z8: Apply as described on the source listing; the official application route is not yet confirmed. | AB8: https://theugandanjobline.com/2026/10/communication-engineer-transmission-access-system-jobs-uganda-electricity-transmission-company-limited-uetcl.html | AC8: [] | AE8: 2026-10-10T12:00:00Z | AF8: scraped | AG8: pending | AH8: =FALSE() | AI8: =FALSE() | AJ8: =FALSE() | AK8: =TRUE() | AL8: =TRUE() | AM8: {"sourceAuthentic":{"urls":["https://theugandanjobline.com/2026/10/communication-engineer-transmission-access-system-jobs-uganda-electricity-transmission-company-limited-uetcl.html"],"rationale":"Seen on The Ugandan Jobline, a third-party or index page. Provider-owned listing not yet located, so authenticity is unconfirmed.","checkedAtUtc":"2026-10-10T12:00:00Z"},"noInappropriateFees":{"urls":["https://theugandanjobline.com/2026/10/communication-engineer-transmission-access-system-jobs-uganda-electricity-transmission-company-limited-uetcl.html"],"rationale":"The summary text retrieved mentions no fee, but the provider page was not reviewed, so this is unconfirmed.","checkedAtUtc":"2026-10-10T12:00:00Z"},"noSensitiveDataAsk":{"urls":["https://theugandanjobline.com/2026/10/communication-engineer-transmission-access-system-jobs-uganda-electricity-transmission-company-limited-uetcl.html"],"rationale":"The retrieved summary asks for no passwords, codes or payments, but full application instructions were not reviewed.","checkedAtUtc":"2026-10-10T12:00:00Z"},"deadlinePlausible":{"urls":["https://theugandanjobline.com/2026/10/communication-engineer-transmission-access-system-jobs-uganda-electricity-transmission-company-limited-uetcl.html"],"rationale":"Source states 'Closes 21 Oct', which falls on or after the delivery date 2026-10-12. Not cross-checked against the provider page.","checkedAtUtc":"2026-10-10T12:00:00Z"},"duplicateChecked":{"urls":[],"rationale":"Title compared with all 115 catalog records and every row in this file using the app's bigram rule (threshold 0.85, 3-day window). Closest catalog title: 'UNESCO Communication and Information Sector Internship' at 0.556.","checkedAtUtc":"2026-10-10T12:00:00Z"}} | AO8: ["Locate the provider-owned listing and the official application link","Confirm no application, processing or placement fee on the official page","Confirm no inappropriate sensitive-data request on the official page","Confirm closing date and timezone on the official page","Qualifications and pay not captured"] | AP8: Listing page snapshot seen 2026-10-10; some Ugandan Jobline index pages were 1 to 2 weeks old, so reconfirm the deadline on the employer page. | AQ8: =FALSE() | AR8: uganda | AS8: theugandanjobline.com | AT8: open_with_deadline | AU8: unresolved | AV8: 2026-10-12T09:15:53Z
A9: drc-meal-trainee-uganda-2026-10 | C9: create | D9: MEAL Trainee | E9: Danish Refugee Council (DRC) | F9: https://www.drc.ngo/ | H9: job | I9: individual | J9: Monitoring, evaluation, accountability and learning trainee role listed as a fresh-graduate, no-experience job. | N9: Uganda (town not confirmed) | R9: unknown | U9: 46309 | V9: Closes 14 Oct | W9: unknown | X9: date | Y9: fixed | Z9: Apply as described on the source listing; the official application route is not yet confirmed. | AB9: https://theugandanjobline.com/2026/10/meal-trainee-no-experience-jobs-jobs-danish-refugee-council.html | AC9: [] | AE9: 2026-10-10T12:00:00Z | AF9: scraped | AG9: pending | AH9: =FALSE() | AI9: =FALSE() | AJ9: =FALSE() | AK9: =TRUE() | AL9: =TRUE() | AM9: {"sourceAuthentic":{"urls":["https://theugandanjobline.com/2026/10/meal-trainee-no-experience-jobs-jobs-danish-refugee-council.html"],"rationale":"Seen on The Ugandan Jobline, a third-party or index page. Provider-owned listing not yet located, so authenticity is unconfirmed.","checkedAtUtc":"2026-10-10T12:00:00Z"},"noInappropriateFees":{"urls":["https://theugandanjobline.com/2026/10/meal-trainee-no-experience-jobs-jobs-danish-refugee-council.html"],"rationale":"The summary text retrieved mentions no fee, but the provider page was not reviewed, so this is unconfirmed.","checkedAtUtc":"2026-10-10T12:00:00Z"},"noSensitiveDataAsk":{"urls":["https://theugandanjobline.com/2026/10/meal-trainee-no-experience-jobs-jobs-danish-refugee-council.html"],"rationale":"The retrieved summary asks for no passwords, codes or payments, but full application instructions were not reviewed.","checkedAtUtc":"2026-10-10T12:00:00Z"},"deadlinePlausible":{"urls":["https://theugandanjobline.com/2026/10/meal-trainee-no-experience-jobs-jobs-danish-refugee-council.html"],"rationale":"Source states 'Closes 14 Oct', which falls on or after the delivery date 2026-10-12. Not cross-checked against the provider page.","checkedAtUtc":"2026-10-10T12:00:00Z"},"duplicateChecked":{"urls":[],"rationale":"Title compared with all 115 catalog records and every row in this file using the app's bigram rule (threshold 0.85, 3-day window). Closest catalog title: 'MEAL Officer' at 0.364.","checkedAtUtc":"2026-10-10T12:00:00Z"}} | AO9: ["Locate the provider-owned listing and the official application link","Confirm no application, processing or placement fee on the official page","Confirm no inappropriate sensitive-data request on the official page","Confirm closing date and timezone on the official page","Duty station and contract terms not captured"] | AP9: Check DRC careers portal for the same reference. Listing page snapshot seen 2026-10-10; some Ugandan Jobline index pages were 1 to 2 weeks old, so reconfirm the deadline on the employer page. | AQ9: =FALSE() | AR9: uganda | AS9: theugandanjobline.com | AT9: open_with_deadline | AU9: unresolved | AV9: 2026-10-12T09:15:53Z
A10: naseco-seed-quality-controller-2026-10 | C10: create | D10: Seed Quality Controller (2 positions) | E10: NASECO Seeds | H10: job | I10: individual | J10: Two seed quality controller positions at NASECO Seeds. | N10: Uganda (town not confirmed) | R10: unknown | U10: 46315 | V10: Closes 20 Oct | W10: unknown | X10: date | Y10: fixed | Z10: Apply as described on the source listing; the official application route is not yet confirmed. | AB10: https://theugandanjobline.com/2026/10/seed-quality-controller-2-positions-jobs-naseco-seeds.html | AC10: [] | AE10: 2026-10-10T12:00:00Z | AF10: scraped | AG10: pending | AH10: =FALSE() | AI10: =FALSE() | AJ10: =FALSE() | AK10: =TRUE() | AL10: =TRUE() | AM10: {"sourceAuthentic":{"urls":["https://theugandanjobline.com/2026/10/seed-quality-controller-2-positions-jobs-naseco-seeds.html"],"rationale":"Seen on The Ugandan Jobline, a third-party or index page. Provider-owned listing not yet located, so authenticity is unconfirmed.","checkedAtUtc":"2026-10-10T12:00:00Z"},"noInappropriateFees":{"urls":["https://theugandanjobline.com/2026/10/seed-quality-controller-2-positions-jobs-naseco-seeds.html"],"rationale":"The summary text retrieved mentions no fee, but the provider page was not reviewed, so this is unconfirmed.","checkedAtUtc":"2026-10-10T12:00:00Z"},"noSensitiveDataAsk":{"urls":["https://theugandanjobline.com/2026/10/seed-quality-controller-2-positions-jobs-naseco-seeds.html"],"rationale":"The retrieved summary asks for no passwords, codes or payments, but full application instructions were not reviewed.","checkedAtUtc":"2026-10-10T12:00:00Z"},"deadlinePlausible":{"urls":["https://theugandanjobline.com/2026/10/seed-quality-controller-2-positions-jobs-naseco-seeds.html"],"rationale":"Source states 'Closes 20 Oct', which falls on or after the delivery date 2026-10-12. Not cross-checked against the provider page.","checkedAtUtc":"2026-10-10T12:00:00Z"},"duplicateChecked":{"urls":[],"rationale":"Title compared with all 115 catalog records and every row in this file using the app's bigram rule (threshold 0.85, 3-day window). Closest catalog title: 'Global Poverty and Inequality Innovation Grant' at 0.423.","checkedAtUtc":"2026-10-10T12:00:00Z"}} | AO10: ["Locate the provider-owned listing and the official application link","Confirm no application, processing or placement fee on the official page","Confirm no inappropriate sensitive-data request on the official page","Confirm closing date and timezone on the official page","Qualifications and pay not captured"] | AP10: Listing page snapshot seen 2026-10-10; some Ugandan Jobline index pages were 1 to 2 weeks old, so reconfirm the deadline on the employer page. | AQ10: =FALSE() | AR10: uganda | AS10: theugandanjobline.com | AT10: open_with_deadline | AU10: unresolved | AV10: 2026-10-12T09:15:53Z
A11: naseco-seed-production-lead-2026-10 | C11: create | D11: Production Systems, Early Generation Seed and Variety Advancement Lead | E11: NASECO Seeds | H11: job | I11: individual | J11: Lead role covering production systems, early generation seed and variety advancement at NASECO Seeds. | N11: Uganda (town not confirmed) | R11: unknown | U11: 46315 | V11: Closes 20 Oct | W11: unknown | X11: date | Y11: fixed | Z11: Apply as described on the source listing; the official application route is not yet confirmed. | AB11: https://theugandanjobline.com/2026/10/production-systems-early-generation-seed-and-variety-advancement-lead-jobs-naseco-seeds.html | AC11: [] | AE11: 2026-10-10T12:00:00Z | AF11: scraped | AG11: pending | AH11: =FALSE() | AI11: =FALSE() | AJ11: =FALSE() | AK11: =TRUE() | AL11: =TRUE() | AM11: {"sourceAuthentic":{"urls":["https://theugandanjobline.com/2026/10/production-systems-early-generation-seed-and-variety-advancement-lead-jobs-naseco-seeds.html"],"rationale":"Seen on The Ugandan Jobline, a third-party or index page. Provider-owned listing not yet located, so authenticity is unconfirmed.","checkedAtUtc":"2026-10-10T12:00:00Z"},"noInappropriateFees":{"urls":["https://theugandanjobline.com/2026/10/production-systems-early-generation-seed-and-variety-advancement-lead-jobs-naseco-seeds.html"],"rationale":"The summary text retrieved mentions no fee, but the provider page was not reviewed, so this is unconfirmed.","checkedAtUtc":"2026-10-10T12:00:00Z"},"noSensitiveDataAsk":{"urls":["https://theugandanjobline.com/2026/10/production-systems-early-generation-seed-and-variety-advancement-lead-jobs-naseco-seeds.html"],"rationale":"The retrieved summary asks for no passwords, codes or payments, but full application instructions were not reviewed.","checkedAtUtc":"2026-10-10T12:00:00Z"},"deadlinePlausible":{"urls":["https://theugandanjobline.com/2026/10/production-systems-early-generation-seed-and-variety-advancement-lead-jobs-naseco-seeds.html"],"rationale":"Source states 'Closes 20 Oct', which falls on or after the delivery date 2026-10-12. Not cross-checked against the provider page.","checkedAtUtc":"2026-10-10T12:00:00Z"},"duplicateChecked":{"urls":[],"rationale":"Title compared with all 115 catalog records and every row in this file using the app's bigram rule (threshold 0.85, 3-day window). Closest catalog title: 'Early-Stage Social Enterprises Grant' at 0.465.","checkedAtUtc":"2026-10-10T12:00:00Z"}} | AO11: ["Locate the provider-owned listing and the official application link","Confirm no application, processing or placement fee on the official page","Confirm no inappropriate sensitive-data request on the official page","Confirm closing date and timezone on the official page","Qualifications and pay not captured"] | AP11: Listing page snapshot seen 2026-10-10; some Ugandan Jobline index pages were 1 to 2 weeks old, so reconfirm the deadline on the employer page. | AQ11: =FALSE() | AR11: uganda | AS11: theugandanjobline.com | AT11: open_with_deadline | AU11: unresolved | AV11: 2026-10-12T09:15:53Z
A12: naseco-quality-assurance-supervisor-2026-10 | C12: create | D12: Quality Assurance Supervisor | E12: NASECO Seeds | H12: job | I12: individual | J12: Quality assurance supervisor role at NASECO Seeds. | N12: Uganda (town not confirmed) | R12: unknown | U12: 46315 | V12: Closes 20 Oct | W12: unknown | X12: date | Y12: fixed | Z12: Apply as described on the source listing; the official application route is not yet confirmed. | AB12: https://theugandanjobline.com/2026/10/quality-assurance-supervisor-jobs-naseco-seeds-2.html | AC12: [] | AE12: 2026-10-10T12:00:00Z | AF12: scraped | AG12: pending | AH12: =FALSE() | AI12: =FALSE() | AJ12: =FALSE() | AK12: =TRUE() | AL12: =TRUE() | AM12: {"sourceAuthentic":{"urls":["https://theugandanjobline.com/2026/10/quality-assurance-supervisor-jobs-naseco-seeds-2.html"],"rationale":"Seen on The Ugandan Jobline, a third-party or index page. Provider-owned listing not yet located, so authenticity is unconfirmed.","checkedAtUtc":"2026-10-10T12:00:00Z"},"noInappropriateFees":{"urls":["https://theugandanjobline.com/2026/10/quality-assurance-supervisor-jobs-naseco-seeds-2.html"],"rationale":"The summary text retrieved mentions no fee, but the provider page was not reviewed, so this is unconfirmed.","checkedAtUtc":"2026-10-10T12:00:00Z"},"noSensitiveDataAsk":{"urls":["https://theugandanjobline.com/2026/10/quality-assurance-supervisor-jobs-naseco-seeds-2.html"],"rationale":"The retrieved summary asks for no passwords, codes or payments, but full application instructions were not reviewed.","checkedAtUtc":"2026-10-10T12:00:00Z"},"deadlinePlausible":{"urls":["https://theugandanjobline.com/2026/10/quality-assurance-supervisor-jobs-naseco-seeds-2.html"],"rationale":"Source states 'Closes 20 Oct', which falls on or after the delivery date 2026-10-12. Not cross-checked against the provider page.","checkedAtUtc":"2026-10-10T12:00:00Z"},"duplicateChecked":{"urls":[],"rationale":"Title compared with all 115 catalog records and every row in this file using the app's bigram rule (threshold 0.85, 3-day window). Closest catalog title: 'Grants Finance Senior Associate/Manager' at 0.4.","checkedAtUtc":"2026-10-10T12:00:00Z"}} | AO12: ["Locate the provider-owned listing and the official application link","Confirm no application, processing or placement fee on the official page","Confirm no inappropriate sensitive-data request on the official page","Confirm closing date and timezone on the official page","Qualifications and pay not captured"] | AP12: Listing page snapshot seen 2026-10-10; some Ugandan Jobline index pages were 1 to 2 weeks old, so reconfirm the deadline on the employer page. | AQ12: =FALSE() | AR12: uganda | AS12: theugandanjobline.com | AT12: open_with_deadline | AU12: unresolved | AV12: 2026-10-12T09:15:53Z
A13: giz-uganda-advisor-crrf-maternity-cover-2026-10 | C13: create | D13: Advisor, Comprehensive Refugee Response Framework (maternity cover) | E13: GIZ Uganda | F13: https://www.giz.de/ | H13: job | I13: individual | J13: Advisory role on the Comprehensive Refugee Response Framework with GIZ Uganda, covering a maternity leave. | N13: Uganda (town not confirmed) | R13: unknown | U13: 46318 | V13: Closes 23 Oct | W13: unknown | X13: date | Y13: fixed | Z13: Apply as described on the source listing; the official application route is not yet confirmed. | AB13: https://theugandanjobline.com/2026/10/advisor-maternity-cover-comprehensive-refugee-response-framework-crrf-jobs-giz-uganda.html | AC13: [] | AE13: 2026-10-10T12:00:00Z | AF13: scraped | AG13: pending | AH13: =FALSE() | AI13: =FALSE() | AJ13: =FALSE() | AK13: =TRUE() | AL13: =TRUE() | AM13: {"sourceAuthentic":{"urls":["https://theugandanjobline.com/2026/10/advisor-maternity-cover-comprehensive-refugee-response-framework-crrf-jobs-giz-uganda.html"],"rationale":"Seen on The Ugandan Jobline, a third-party or index page. Provider-owned listing not yet located, so authenticity is unconfirmed.","checkedAtUtc":"2026-10-10T12:00:00Z"},"noInappropriateFees":{"urls":["https://theugandanjobline.com/2026/10/advisor-maternity-cover-comprehensive-refugee-response-framework-crrf-jobs-giz-uganda.html"],"rationale":"The summary text retrieved mentions no fee, but the provider page was not reviewed, so this is unconfirmed.","checkedAtUtc":"2026-10-10T12:00:00Z"},"noSensitiveDataAsk":{"urls":["https://theugandanjobline.com/2026/10/advisor-maternity-cover-comprehensive-refugee-response-framework-crrf-jobs-giz-uganda.html"],"rationale":"The retrieved summary asks for no passwords, codes or payments, but full application instructions were not reviewed.","checkedAtUtc":"2026-10-10T12:00:00Z"},"deadlinePlausible":{"urls":["https://theugandanjobline.com/2026/10/advisor-maternity-cover-comprehensive-refugee-response-framework-crrf-jobs-giz-uganda.html"],"rationale":"Source states 'Closes 23 Oct', which falls on or after the delivery date 2026-10-12. Not cross-checked against the provider page.","checkedAtUtc":"2026-10-10T12:00:00Z"},"duplicateChecked":{"urls":[],"rationale":"Title compared with all 115 catalog records and every row in this file using the app's bigram rule (threshold 0.85, 3-day window). Closest catalog title: 'Territory Field Sales Representative, Mukono' at 0.391.","checkedAtUtc":"2026-10-10T12:00:00Z"}} | AO13: ["Locate the provider-owned listing and the official application link","Confirm no application, processing or placement fee on the official page","Confirm no inappropriate sensitive-data request on the official page","Confirm closing date and timezone on the official page","Contract length and qualifications not captured"] | AP13: Fixed-term cover role. Verify on the GIZ careers portal. Listing page snapshot seen 2026-10-10; some Ugandan Jobline index pages were 1 to 2 weeks old, so reconfirm the deadline on the employer page. | AQ13: =FALSE() | AR13: uganda | AS13: theugandanjobline.com | AT13: open_with_deadline | AU13: unresolved | AV13: 2026-10-12T09:15:53Z
A14: unwomen-uganda-sasa-together-evaluation-2026-10 | C14: create | D14: National Consultant to Evaluate the SASA Together Strategy | E14: UN Women Uganda | F14: https://www.unwomen.org/ | H14: consultancy | I14: individual | J14: National consultancy to evaluate the SASA Together strategy for UN Women in Uganda. | N14: Uganda (town not confirmed) | R14: unknown | U14: 46310 | V14: Closes 15 Oct | W14: unknown | X14: date | Y14: fixed | Z14: Apply as described on the source listing; the official application route is not yet confirmed. | AB14: https://theugandanjobline.com/2026/10/national-consultant-to-evaluate-the-sasa-together-strategy-jobs-unwomen-uganda.html | AC14: [] | AE14: 2026-10-10T12:00:00Z | AF14: scraped | AG14: pending | AH14: =FALSE() | AI14: =FALSE() | AJ14: =FALSE() | AK14: =TRUE() | AL14: =TRUE() | AM14: {"sourceAuthentic":{"urls":["https://theugandanjobline.com/2026/10/national-consultant-to-evaluate-the-sasa-together-strategy-jobs-unwomen-uganda.html"],"rationale":"Seen on The Ugandan Jobline, a third-party or index page. Provider-owned listing not yet located, so authenticity is unconfirmed.","checkedAtUtc":"2026-10-10T12:00:00Z"},"noInappropriateFees":{"urls":["https://theugandanjobline.com/2026/10/national-consultant-to-evaluate-the-sasa-together-strategy-jobs-unwomen-uganda.html"],"rationale":"The summary text retrieved mentions no fee, but the provider page was not reviewed, so this is unconfirmed.","checkedAtUtc":"2026-10-10T12:00:00Z"},"noSensitiveDataAsk":{"urls":["https://theugandanjobline.com/2026/10/national-consultant-to-evaluate-the-sasa-together-strategy-jobs-unwomen-uganda.html"],"rationale":"The retrieved summary asks for no passwords, codes or payments, but full application instructions were not reviewed.","checkedAtUtc":"2026-10-10T12:00:00Z"},"deadlinePlausible":{"urls":["https://theugandanjobline.com/2026/10/national-consultant-to-evaluate-the-sasa-together-strategy-jobs-unwomen-uganda.html"],"rationale":"Source states 'Closes 15 Oct', which falls on or after the delivery date 2026-10-12. Not cross-checked against the provider page.","checkedAtUtc":"2026-10-10T12:00:00Z"},"duplicateChecked":{"urls":[],"rationale":"Title compared with all 115 catalog records and every row in this file using the app's bigram rule (threshold 0.85, 3-day window). Closest catalog title: 'Sensory & Taste Evaluation Specialist' at 0.48.","checkedAtUtc":"2026-10-10T12:00:00Z"}} | AO14: ["Locate the provider-owned listing and the official application link","Confirm no application, processing or placement fee on the official page","Confirm no inappropriate sensitive-data request on the official page","Confirm closing date and timezone on the official page","Nationality restriction, fee and terms of reference not captured"] | AP14: Short window at retrieval. Probably limited to Ugandan nationals (national consultant); confirm. | AQ14: =FALSE() | AR14: uganda | AS14: theugandanjobline.com | AT14: open_with_deadline | AU14: unresolved | AV14: 2026-10-12T09:15:53Z
A15: unicef-uganda-chwp-oversight-consultant-2026-10 | C15: create | D15: National Consultant, Oversight, Coordination, Monitoring and Quality Assurance of the Community Health Workforce Programme | E15: UNICEF Uganda | F15: https://www.unicef.org/uganda/ | H15: consultancy | I15: individual | J15: National consultancy for oversight, coordination, monitoring and quality assurance of the Community Health Workforce Programme. | N15: Uganda (town not confirmed) | R15: unknown | U15: 46310 | V15: Closes 15 Oct | W15: unknown | X15: date | Y15: fixed | Z15: Apply as described on the source listing; the official application route is not yet confirmed. | AB15: https://theugandanjobline.com/2026/10/national-consultant-for-oversight-coordination-monitoring-and-quality-assurance-of-the-community-health-workforce-programme-chwp-jobs-united-nations-childrens-fund.html | AC15: [] | AE15: 2026-10-10T12:00:00Z | AF15: scraped | AG15: pending | AH15: =FALSE() | AI15: =FALSE() | AJ15: =FALSE() | AK15: =TRUE() | AL15: =TRUE() | AM15: {"sourceAuthentic":{"urls":["https://theugandanjobline.com/2026/10/national-consultant-for-oversight-coordination-monitoring-and-quality-assurance-of-the-community-health-workforce-programme-chwp-jobs-united-nations-childrens-fund.html"],"rationale":"Seen on The Ugandan Jobline, a third-party or index page. Provider-owned listing not yet located, so authenticity is unconfirmed.","checkedAtUtc":"2026-10-10T12:00:00Z"},"noInappropriateFees":{"urls":["https://theugandanjobline.com/2026/10/national-consultant-for-oversight-coordination-monitoring-and-quality-assurance-of-the-community-health-workforce-programme-chwp-jobs-united-nations-childrens-fund.html"],"rationale":"The summary text retrieved mentions no fee, but the provider page was not reviewed, so this is unconfirmed.","checkedAtUtc":"2026-10-10T12:00:00Z"},"noSensitiveDataAsk":{"urls":["https://theugandanjobline.com/2026/10/national-consultant-for-oversight-coordination-monitoring-and-quality-assurance-of-the-community-health-workforce-programme-chwp-jobs-united-nations-childrens-fund.html"],"rationale":"The retrieved summary asks for no passwords, codes or payments, but full application instructions were not reviewed.","checkedAtUtc":"2026-10-10T12:00:00Z"},"deadlinePlausible":{"urls":["https://theugandanjobline.com/2026/10/national-consultant-for-oversight-coordination-monitoring-and-quality-assurance-of-the-community-health-workforce-programme-chwp-jobs-united-nations-childrens-fund.html"],"rationale":"Source states 'Closes 15 Oct', which falls on or after the delivery date 2026-10-12. Not cross-checked against the provider page.","checkedAtUtc":"2026-10-10T12:00:00Z"},"duplicateChecked":{"urls":[],"rationale":"Title compared with all 115 catalog records and every row in this file using the app's bigram rule (threshold 0.85, 3-day window). Closest catalog title: 'University of Edinburgh Mastercard Foundation Online Learning Scholars Program' at 0.554.","checkedAtUtc":"2026-10-10T12:00:00Z"}} | AO15: ["Locate the provider-owned listing and the official application link","Confirm no application, processing or placement fee on the official page","Confirm no inappropriate sensitive-data request on the official page","Confirm closing date and timezone on the official page","Nationality restriction and terms of reference not captured"] | AP15: Short window at retrieval. Likely limited to national candidates; confirm on UNICEF careers. | AQ15: =FALSE() | AR15: uganda | AS15: theugandanjobline.com | AT15: open_with_deadline | AU15: unresolved | AV15: 2026-10-12T09:15:53Z
A16: true-north-planning-engineer-offsites-epc-2026-10 | C16: create | D16: Planning Engineer (Offsites and EPC) | E16: True North Consult | H16: job | I16: individual | J16: Planning engineer role for offsites and EPC work at True North Consult. | N16: Uganda (town not confirmed) | R16: unknown | U16: 46307 | V16: Closes 12 Oct | W16: unknown | X16: date | Y16: fixed | Z16: Apply as described on the source listing; the official application route is not yet confirmed. | AB16: https://theugandanjobline.com/2026/10/planning-engineer-offsites-epc-jobs-true-north-consult.html | AC16: [] | AE16: 2026-10-10T12:00:00Z | AF16: scraped | AG16: pending | AH16: =FALSE() | AI16: =FALSE() | AJ16: =FALSE() | AK16: =TRUE() | AL16: =TRUE() | AM16: {"sourceAuthentic":{"urls":["https://theugandanjobline.com/2026/10/planning-engineer-offsites-epc-jobs-true-north-consult.html"],"rationale":"Seen on The Ugandan Jobline, a third-party or index page. Provider-owned listing not yet located, so authenticity is unconfirmed.","checkedAtUtc":"2026-10-10T12:00:00Z"},"noInappropriateFees":{"urls":["https://theugandanjobline.com/2026/10/planning-engineer-offsites-epc-jobs-true-north-consult.html"],"rationale":"The summary text retrieved mentions no fee, but the provider page was not reviewed, so this is unconfirmed.","checkedAtUtc":"2026-10-10T12:00:00Z"},"noSensitiveDataAsk":{"urls":["https://theugandanjobline.com/2026/10/planning-engineer-offsites-epc-jobs-true-north-consult.html"],"rationale":"The retrieved summary asks for no passwords, codes or payments, but full application instructions were not reviewed.","checkedAtUtc":"2026-10-10T12:00:00Z"},"deadlinePlausible":{"urls":["https://theugandanjobline.com/2026/10/planning-engineer-offsites-epc-jobs-true-north-consult.html"],"rationale":"Source states 'Closes 12 Oct', which falls on or after the delivery date 2026-10-12. Not cross-checked against the provider page.","checkedAtUtc":"2026-10-10T12:00:00Z"},"duplicateChecked":{"urls":[],"rationale":"Title compared with all 115 catalog records and every row in this file using the app's bigram rule (threshold 0.85, 3-day window). Closest catalog title: 'Regional Research and Learning Coordinator, PlayMatters' at 0.395.","checkedAtUtc":"2026-10-10T12:00:00Z"}} | AO16: ["Locate the provider-owned listing and the official application link","Confirm no application, processing or placement fee on the official page","Confirm no inappropriate sensitive-data request on the official page","Confirm closing date and timezone on the official page","Qualifications and pay not captured"] | AP16: Closes today (2026-10-12), re-check immediately. Short window at retrieval. Listing page snapshot seen 2026-10-10; some Ugandan Jobline index pages were 1 to 2 weeks old, so reconfirm the deadline on the employer page. | AQ16: =FALSE() | AR16: uganda | AS16: theugandanjobline.com | AT16: open_with_deadline | AU16: unresolved | AV16: 2026-10-12T09:15:53Z
A17: simplepay-internal-debt-collectors-2026-10 | C17: create | D17: Internal Debt Collector (50 positions) | E17: SimplePay Capital | H17: job | I17: individual | J17: Fifty internal debt collector positions at SimplePay Capital. | N17: Uganda (town not confirmed) | R17: unknown | U17: 46335 | V17: Closes 9 Nov | W17: unknown | X17: date | Y17: fixed | Z17: Apply as described on the source listing; the official application route is not yet confirmed. | AB17: https://theugandanjobline.com/2026/10/50-internal-debt-collector-jobs-simplepay-capital.html | AC17: [] | AE17: 2026-10-10T12:00:00Z | AF17: scraped | AG17: pending | AH17: =FALSE() | AI17: =FALSE() | AJ17: =FALSE() | AK17: =TRUE() | AL17: =TRUE() | AM17: {"sourceAuthentic":{"urls":["https://theugandanjobline.com/2026/10/50-internal-debt-collector-jobs-simplepay-capital.html"],"rationale":"Seen on The Ugandan Jobline, a third-party or index page. Provider-owned listing not yet located, so authenticity is unconfirmed.","checkedAtUtc":"2026-10-10T12:00:00Z"},"noInappropriateFees":{"urls":["https://theugandanjobline.com/2026/10/50-internal-debt-collector-jobs-simplepay-capital.html"],"rationale":"The summary text retrieved mentions no fee, but the provider page was not reviewed, so this is unconfirmed.","checkedAtUtc":"2026-10-10T12:00:00Z"},"noSensitiveDataAsk":{"urls":["https://theugandanjobline.com/2026/10/50-internal-debt-collector-jobs-simplepay-capital.html"],"rationale":"The retrieved summary asks for no passwords, codes or payments, but full application instructions were not reviewed.","checkedAtUtc":"2026-10-10T12:00:00Z"},"deadlinePlausible":{"urls":["https://theugandanjobline.com/2026/10/50-internal-debt-collector-jobs-simplepay-capital.html"],"rationale":"Source states 'Closes 9 Nov', which falls on or after the delivery date 2026-10-12. Not cross-checked against the provider page.","checkedAtUtc":"2026-10-10T12:00:00Z"},"duplicateChecked":{"urls":[],"rationale":"Title compared with all 115 catalog records and every row in this file using the app's bigram rule (threshold 0.85, 3-day window). Closest catalog title: 'CSO Call for Expressions of Project Intentions' at 0.5.","checkedAtUtc":"2026-10-10T12:00:00Z"}} | AO17: ["Locate the provider-owned listing and the official application link","Confirm no application, processing or placement fee on the official page","Confirm no inappropriate sensitive-data request on the official page","Confirm closing date and timezone on the official page","Pay structure (salary versus commission) not captured","Lender licence not checked"] | AP17: Mass hiring in lending and collections: agent should check the lender is licensed (Uganda Microfinance Regulatory Authority or Bank of Uganda) and whether pay is commission-only. | AQ17: =FALSE() | AR17: uganda | AS17: theugandanjobline.com | AT17: open_with_deadline | AU17: unresolved | AV17: 2026-10-12T09:15:53Z
A18: tugende-customer-relations-admin-officer-2026-10 | C18: create | D18: Customer Relations and Administration Officer | E18: Tugende | H18: job | I18: individual | J18: Contract customer relations and administration role at Tugende. | N18: Uganda (town not confirmed) | R18: unknown | U18: 46332 | V18: Closes 6 Nov | W18: unknown | X18: date | Y18: fixed | Z18: Apply as described on the source listing; the official application route is not yet confirmed. | AB18: https://theugandanjobline.com/2026/10/customer-relations-and-administration-officer-jobs-tugende.html | AC18: [] | AE18: 2026-10-10T12:00:00Z | AF18: scraped | AG18: pending | AH18: =FALSE() | AI18: =FALSE() | AJ18: =FALSE() | AK18: =TRUE() | AL18: =TRUE() | AM18: {"sourceAuthentic":{"urls":["https://theugandanjobline.com/2026/10/customer-relations-and-administration-officer-jobs-tugende.html"],"rationale":"Seen on The Ugandan Jobline, a third-party or index page. Provider-owned listing not yet located, so authenticity is unconfirmed.","checkedAtUtc":"2026-10-10T12:00:00Z"},"noInappropriateFees":{"urls":["https://theugandanjobline.com/2026/10/customer-relations-and-administration-officer-jobs-tugende.html"],"rationale":"The summary text retrieved mentions no fee, but the provider page was not reviewed, so this is unconfirmed.","checkedAtUtc":"2026-10-10T12:00:00Z"},"noSensitiveDataAsk":{"urls":["https://theugandanjobline.com/2026/10/customer-relations-and-administration-officer-jobs-tugende.html"],"rationale":"The retrieved summary asks for no passwords, codes or payments, but full application instructions were not reviewed.","checkedAtUtc":"2026-10-10T12:00:00Z"},"deadlinePlausible":{"urls":["https://theugandanjobline.com/2026/10/customer-relations-and-administration-officer-jobs-tugende.html"],"rationale":"Source states 'Closes 6 Nov', which falls on or after the delivery date 2026-10-12. Not cross-checked against the provider page.","checkedAtUtc":"2026-10-10T12:00:00Z"},"duplicateChecked":{"urls":[],"rationale":"Title compared with all 115 catalog records and every row in this file using the app's bigram rule (threshold 0.85, 3-day window). Closest catalog title: 'Chief Operations Officer' at 0.483.","checkedAtUtc":"2026-10-10T12:00:00Z"}} | AO18: ["Locate the provider-owned listing and the official application link","Confirm no application, processing or placement fee on the official page","Confirm no inappropriate sensitive-data request on the official page","Confirm closing date and timezone on the official page","Duty station and pay not captured"] | AQ18: =FALSE() | AR18: uganda | AS18: theugandanjobline.com | AT18: open_with_deadline | AU18: unresolved | AV18: 2026-10-12T09:15:53Z
A19: tugende-branch-executive-2026-10 | C19: create | D19: Branch Executive | E19: Tugende | H19: job | I19: individual | J19: Full-time branch executive role at Tugende. A separate posting for 2 Branch Executive positions shows a 28 Oct closing date. | N19: Uganda (town not confirmed) | R19: unknown | U19: 46332 | V19: Closes 6 Nov | W19: unknown | X19: date | Y19: fixed | Z19: Apply as described on the source listing; the official application route is not yet confirmed. | AB19: https://theugandanjobline.com/2026/10/branch-executive-jobs-tugende-6.html | AC19: ["https://theugandanjobline.com/2026/09/branch-executive-jobs-tugende-5.html"] | AE19: 2026-10-10T12:00:00Z | AF19: scraped | AG19: pending | AH19: =FALSE() | AI19: =FALSE() | AJ19: =FALSE() | AK19: =TRUE() | AL19: =TRUE() | AM19: {"sourceAuthentic":{"urls":["https://theugandanjobline.com/2026/10/branch-executive-jobs-tugende-6.html","https://theugandanjobline.com/2026/09/branch-executive-jobs-tugende-5.html"],"rationale":"Seen on The Ugandan Jobline, a third-party or index page. Provider-owned listing not yet located, so authenticity is unconfirmed.","checkedAtUtc":"2026-10-10T12:00:00Z"},"noInappropriateFees":{"urls":["https://theugandanjobline.com/2026/10/branch-executive-jobs-tugende-6.html"],"rationale":"The summary text retrieved mentions no fee, but the provider page was not reviewed, so this is unconfirmed.","checkedAtUtc":"2026-10-10T12:00:00Z"},"noSensitiveDataAsk":{"urls":["https://theugandanjobline.com/2026/10/branch-executive-jobs-tugende-6.html"],"rationale":"The retrieved summary asks for no passwords, codes or payments, but full application instructions were not reviewed.","checkedAtUtc":"2026-10-10T12:00:00Z"},"deadlinePlausible":{"urls":["https://theugandanjobline.com/2026/10/branch-executive-jobs-tugende-6.html"],"rationale":"Source states 'Closes 6 Nov', which falls on or after the delivery date 2026-10-12. Not cross-checked against the provider page.","checkedAtUtc":"2026-10-10T12:00:00Z"},"duplicateChecked":{"urls":[],"rationale":"Title compared with all 115 catalog records and every row in this file using the app's bigram rule (threshold 0.85, 3-day window). Closest catalog title: 'Health Impact Research Initiative' at 0.233.","checkedAtUtc":"2026-10-10T12:00:00Z"}} | AO19: ["Locate the provider-owned listing and the official application link","Confirm no application, processing or placement fee on the official page","Confirm no inappropriate sensitive-data request on the official page","Confirm closing date and timezone on the official page","Which posting is current","Branch locations and pay not captured"] | AP19: Two Tugende branch executive postings with different closing dates (6 Nov and 28 Oct). Agent should decide whether they are the same call. | AQ19: =FALSE() | AR19: uganda | AS19: theugandanjobline.com | AT19: open_with_deadline | AU19: unresolved | AV19: 2026-10-12T09:15:53Z
A20: unifi-call-centre-agent-2026-10 | C20: create | D20: Call Centre Agent (several positions) | E20: Unifi Uganda | H20: job | I20: individual | J20: Several call centre agent positions, tagged no experience required, at Unifi Uganda. | N20: Uganda (town not confirmed) | R20: unknown | U20: 46333 | V20: Closes 7 Nov | W20: unknown | X20: date | Y20: fixed | Z20: Apply as described on the source listing; the official application route is not yet confirmed. | AB20: https://theugandanjobline.com/2026/10/call-centre-agent-several-no-experience-jobs-jobs-unifi-uganda.html | AC20: [] | AE20: 2026-10-10T12:00:00Z | AF20: scraped | AG20: pending | AH20: =FALSE() | AI20: =FALSE() | AJ20: =FALSE() | AK20: =TRUE() | AL20: =TRUE() | AM20: {"sourceAuthentic":{"urls":["https://theugandanjobline.com/2026/10/call-centre-agent-several-no-experience-jobs-jobs-unifi-uganda.html"],"rationale":"Seen on The Ugandan Jobline, a third-party or index page. Provider-owned listing not yet located, so authenticity is unconfirmed.","checkedAtUtc":"2026-10-10T12:00:00Z"},"noInappropriateFees":{"urls":["https://theugandanjobline.com/2026/10/call-centre-agent-several-no-experience-jobs-jobs-unifi-uganda.html"],"rationale":"The summary text retrieved mentions no fee, but the provider page was not reviewed, so this is unconfirmed.","checkedAtUtc":"2026-10-10T12:00:00Z"},"noSensitiveDataAsk":{"urls":["https://theugandanjobline.com/2026/10/call-centre-agent-several-no-experience-jobs-jobs-unifi-uganda.html"],"rationale":"The retrieved summary asks for no passwords, codes or payments, but full application instructions were not reviewed.","checkedAtUtc":"2026-10-10T12:00:00Z"},"deadlinePlausible":{"urls":["https://theugandanjobline.com/2026/10/call-centre-agent-several-no-experience-jobs-jobs-unifi-uganda.html"],"rationale":"Source states 'Closes 7 Nov', which falls on or after the delivery date 2026-10-12. Not cross-checked against the provider page.","checkedAtUtc":"2026-10-10T12:00:00Z"},"duplicateChecked":{"urls":[],"rationale":"Title compared with all 115 catalog records and every row in this file using the app's bigram rule (threshold 0.85, 3-day window). Closest catalog title: 'Digital Services Specialist / Client Operations Manager' at 0.507.","checkedAtUtc":"2026-10-10T12:00:00Z"}} | AO20: ["Locate the provider-owned listing and the official application link","Confirm no application, processing or placement fee on the official page","Confirm no inappropriate sensitive-data request on the official page","Confirm closing date and timezone on the official page","Qualifications, shift pattern and pay not captured"] | AP20: Good fit for school leavers and certificate holders if confirmed. | AQ20: =FALSE() | AR20: uganda | AS20: theugandanjobline.com | AT20: open_with_deadline | AU20: unresolved | AV20: 2026-10-12T09:15:53Z
A21: unifi-client-growth-sales-rep-lira-2026-10 | C21: create | D21: Client Growth Sales Representative, Lira | E21: Unifi Uganda | H21: job | I21: individual | J21: Field sales representative role based in Lira for Unifi Uganda. | N21: Lira, Uganda | R21: unknown | U21: 46333 | V21: Closes 7 Nov | W21: unknown | X21: date | Y21: fixed | Z21: Apply as described on the source listing; the official application route is not yet confirmed. | AB21: https://theugandanjobline.com/2026/10/client-growth-sales-representative-lira-jobs-unifi-uganda.html | AC21: [] | AE21: 2026-10-10T12:00:00Z | AF21: scraped | AG21: pending | AH21: =FALSE() | AI21: =FALSE() | AJ21: =FALSE() | AK21: =TRUE() | AL21: =TRUE() | AM21: {"sourceAuthentic":{"urls":["https://theugandanjobline.com/2026/10/client-growth-sales-representative-lira-jobs-unifi-uganda.html"],"rationale":"Seen on The Ugandan Jobline, a third-party or index page. Provider-owned listing not yet located, so authenticity is unconfirmed.","checkedAtUtc":"2026-10-10T12:00:00Z"},"noInappropriateFees":{"urls":["https://theugandanjobline.com/2026/10/client-growth-sales-representative-lira-jobs-unifi-uganda.html"],"rationale":"The summary text retrieved mentions no fee, but the provider page was not reviewed, so this is unconfirmed.","checkedAtUtc":"2026-10-10T12:00:00Z"},"noSensitiveDataAsk":{"urls":["https://theugandanjobline.com/2026/10/client-growth-sales-representative-lira-jobs-unifi-uganda.html"],"rationale":"The retrieved summary asks for no passwords, codes or payments, but full application instructions were not reviewed.","checkedAtUtc":"2026-10-10T12:00:00Z"},"deadlinePlausible":{"urls":["https://theugandanjobline.com/2026/10/client-growth-sales-representative-lira-jobs-unifi-uganda.html"],"rationale":"Source states 'Closes 7 Nov', which falls on or after the delivery date 2026-10-12. Not cross-checked against the provider page.","checkedAtUtc":"2026-10-10T12:00:00Z"},"duplicateChecked":{"urls":[],"rationale":"Title compared with all 115 catalog records and every row in this file using the app's bigram rule (threshold 0.85, 3-day window). Closest catalog title: 'Creative Sales Representative' at 0.704.","checkedAtUtc":"2026-10-10T12:00:00Z"}} | AO21: ["Locate the provider-owned listing and the official application link","Confirm no application, processing or placement fee on the official page","Confirm no inappropriate sensitive-data request on the official page","Confirm closing date and timezone on the official page","Qualifications and pay not captured"] | AP21: Same title pattern as the Iganga posting; different duty stations, so keep as separate listings. Duplicate signals: within_run similarity 0.882 with 'Client Growth Sales Representative, Iganga [unifi-client-growth-sales-rep-iganga-2026-10]'. | AQ21: =FALSE() | AR21: uganda | AS21: theugandanjobline.com | AT21: open_with_deadline | AU21: unresolved | AV21: 2026-10-12T09:15:53Z
A22: unifi-client-growth-sales-rep-iganga-2026-10 | C22: create | D22: Client Growth Sales Representative, Iganga | E22: Unifi Uganda | H22: job | I22: individual | J22: Field sales representative role based in Iganga for Unifi Uganda. | N22: Iganga, Uganda | R22: unknown | U22: 46333 | V22: Closes 7 Nov | W22: unknown | X22: date | Y22: fixed | Z22: Apply as described on the source listing; the official application route is not yet confirmed. | AB22: https://theugandanjobline.com/2026/10/client-growth-sales-representative-iganga-jobs-unifi-uganda.html | AC22: [] | AE22: 2026-10-10T12:00:00Z | AF22: scraped | AG22: pending | AH22: =FALSE() | AI22: =FALSE() | AJ22: =FALSE() | AK22: =TRUE() | AL22: =TRUE() | AM22: {"sourceAuthentic":{"urls":["https://theugandanjobline.com/2026/10/client-growth-sales-representative-iganga-jobs-unifi-uganda.html"],"rationale":"Seen on The Ugandan Jobline, a third-party or index page. Provider-owned listing not yet located, so authenticity is unconfirmed.","checkedAtUtc":"2026-10-10T12:00:00Z"},"noInappropriateFees":{"urls":["https://theugandanjobline.com/2026/10/client-growth-sales-representative-iganga-jobs-unifi-uganda.html"],"rationale":"The summary text retrieved mentions no fee, but the provider page was not reviewed, so this is unconfirmed.","checkedAtUtc":"2026-10-10T12:00:00Z"},"noSensitiveDataAsk":{"urls":["https://theugandanjobline.com/2026/10/client-growth-sales-representative-iganga-jobs-unifi-uganda.html"],"rationale":"The retrieved summary asks for no passwords, codes or payments, but full application instructions were not reviewed.","checkedAtUtc":"2026-10-10T12:00:00Z"},"deadlinePlausible":{"urls":["https://theugandanjobline.com/2026/10/client-growth-sales-representative-iganga-jobs-unifi-uganda.html"],"rationale":"Source states 'Closes 7 Nov', which falls on or after the delivery date 2026-10-12. Not cross-checked against the provider page.","checkedAtUtc":"2026-10-10T12:00:00Z"},"duplicateChecked":{"urls":[],"rationale":"Title compared with all 115 catalog records and every row in this file using the app's bigram rule (threshold 0.85, 3-day window). Closest catalog title: 'Creative Sales Representative' at 0.679.","checkedAtUtc":"2026-10-10T12:00:00Z"}} | AO22: ["Locate the provider-owned listing and the official application link","Confirm no application, processing or placement fee on the official page","Confirm no inappropriate sensitive-data request on the official page","Confirm closing date and timezone on the official page","Qualifications and pay not captured"] | AP22: Same title pattern as the Lira posting; different duty stations, so keep as separate listings. | AQ22: =FALSE() | AR22: uganda | AS22: theugandanjobline.com | AT22: open_with_deadline | AU22: unresolved | AV22: 2026-10-12T09:15:53Z
A23: unifi-special-projects-lead-2026-10 | C23: create | D23: Special Projects Lead | E23: Unifi Uganda | H23: job | I23: individual | J23: Special projects lead role (engineering category on the source site) at Unifi Uganda. | N23: Uganda (town not confirmed) | R23: unknown | U23: 46333 | V23: Closes 7 Nov | W23: unknown | X23: date | Y23: fixed | Z23: Apply as described on the source listing; the official application route is not yet confirmed. | AB23: https://theugandanjobline.com/2026/10/special-projects-lead-jobs-unifi-uganda.html | AC23: [] | AE23: 2026-10-10T12:00:00Z | AF23: scraped | AG23: pending | AH23: =FALSE() | AI23: =FALSE() | AJ23: =FALSE() | AK23: =TRUE() | AL23: =TRUE() | AM23: {"sourceAuthentic":{"urls":["https://theugandanjobline.com/2026/10/special-projects-lead-jobs-unifi-uganda.html"],"rationale":"Seen on The Ugandan Jobline, a third-party or index page. Provider-owned listing not yet located, so authenticity is unconfirmed.","checkedAtUtc":"2026-10-10T12:00:00Z"},"noInappropriateFees":{"urls":["https://theugandanjobline.com/2026/10/special-projects-lead-jobs-unifi-uganda.html"],"rationale":"The summary text retrieved mentions no fee, but the provider page was not reviewed, so this is unconfirmed.","checkedAtUtc":"2026-10-10T12:00:00Z"},"noSensitiveDataAsk":{"urls":["https://theugandanjobline.com/2026/10/special-projects-lead-jobs-unifi-uganda.html"],"rationale":"The retrieved summary asks for no passwords, codes or payments, but full application instructions were not reviewed.","checkedAtUtc":"2026-10-10T12:00:00Z"},"deadlinePlausible":{"urls":["https://theugandanjobline.com/2026/10/special-projects-lead-jobs-unifi-uganda.html"],"rationale":"Source states 'Closes 7 Nov', which falls on or after the delivery date 2026-10-12. Not cross-checked against the provider page.","checkedAtUtc":"2026-10-10T12:00:00Z"},"duplicateChecked":{"urls":[],"rationale":"Title compared with all 115 catalog records and every row in this file using the app's bigram rule (threshold 0.85, 3-day window). Closest catalog title: 'Social Studies Teacher, Upper Primary (PLE)' at 0.357.","checkedAtUtc":"2026-10-10T12:00:00Z"}} | AO23: ["Locate the provider-owned listing and the official application link","Confirm no application, processing or placement fee on the official page","Confirm no inappropriate sensitive-data request on the official page","Confirm closing date and timezone on the official page","Qualifications and pay not captured"] | AQ23: =FALSE() | AR23: uganda | AS23: theugandanjobline.com | AT23: open_with_deadline | AU23: unresolved | AV23: 2026-10-12T09:15:53Z
A24: asilia-africa-hr-coordinator-2026-10 | C24: create | D24: Human Resources Coordinator | E24: Asilia Africa | H24: job | I24: individual | J24: Human resources coordinator role at Asilia Africa, listed under Uganda jobs. | N24: Uganda (town not confirmed) | R24: unknown | U24: 46333 | V24: Closes 7 Nov | W24: unknown | X24: date | Y24: fixed | Z24: Apply as described on the source listing; the official application route is not yet confirmed. | AB24: https://theugandanjobline.com/2026/10/human-resources-coordinator-jobs-asilia-africa.html | AC24: [] | AE24: 2026-10-10T12:00:00Z | AF24: scraped | AG24: pending | AH24: =FALSE() | AI24: =FALSE() | AJ24: =FALSE() | AK24: =TRUE() | AL24: =TRUE() | AM24: {"sourceAuthentic":{"urls":["https://theugandanjobline.com/2026/10/human-resources-coordinator-jobs-asilia-africa.html"],"rationale":"Seen on The Ugandan Jobline, a third-party or index page. Provider-owned listing not yet located, so authenticity is unconfirmed.","checkedAtUtc":"2026-10-10T12:00:00Z"},"noInappropriateFees":{"urls":["https://theugandanjobline.com/2026/10/human-resources-coordinator-jobs-asilia-africa.html"],"rationale":"The summary text retrieved mentions no fee, but the provider page was not reviewed, so this is unconfirmed.","checkedAtUtc":"2026-10-10T12:00:00Z"},"noSensitiveDataAsk":{"urls":["https://theugandanjobline.com/2026/10/human-resources-coordinator-jobs-asilia-africa.html"],"rationale":"The retrieved summary asks for no passwords, codes or payments, but full application instructions were not reviewed.","checkedAtUtc":"2026-10-10T12:00:00Z"},"deadlinePlausible":{"urls":["https://theugandanjobline.com/2026/10/human-resources-coordinator-jobs-asilia-africa.html"],"rationale":"Source states 'Closes 7 Nov', which falls on or after the delivery date 2026-10-12. Not cross-checked against the provider page.","checkedAtUtc":"2026-10-10T12:00:00Z"},"duplicateChecked":{"urls":[],"rationale":"Title compared with all 115 catalog records and every row in this file using the app's bigram rule (threshold 0.85, 3-day window). Closest catalog title: 'Economic Recovery Coordinator' at 0.5.","checkedAtUtc":"2026-10-10T12:00:00Z"}} | AO24: ["Locate the provider-owned listing and the official application link","Confirm no application, processing or placement fee on the official page","Confirm no inappropriate sensitive-data request on the official page","Confirm closing date and timezone on the official page","Duty station (Uganda versus elsewhere) not confirmed"] | AQ24: =FALSE() | AR24: uganda | AS24: theugandanjobline.com | AT24: open_with_deadline | AU24: unresolved | AV24: 2026-10-12T09:15:53Z
A25: esom-front-desk-administrator-2026-10 | C25: create | D25: Front Desk Administrator (2 positions) | E25: ESOM School of Music | H25: job | I25: individual | J25: Two front desk administrator positions at ESOM School of Music. | N25: Uganda (town not confirmed) | R25: unknown | U25: 46333 | V25: Closes 7 Nov | W25: unknown | X25: date | Y25: fixed | Z25: Apply as described on the source listing; the official application route is not yet confirmed. | AB25: https://theugandanjobline.com/2026/10/front-desk-administrator-2-positions-jobs-esom-school-of-music.html | AC25: [] | AE25: 2026-10-10T12:00:00Z | AF25: scraped | AG25: pending | AH25: =FALSE() | AI25: =FALSE() | AJ25: =FALSE() | AK25: =TRUE() | AL25: =TRUE() | AM25: {"sourceAuthentic":{"urls":["https://theugandanjobline.com/2026/10/front-desk-administrator-2-positions-jobs-esom-school-of-music.html"],"rationale":"Seen on The Ugandan Jobline, a third-party or index page. Provider-owned listing not yet located, so authenticity is unconfirmed.","checkedAtUtc":"2026-10-10T12:00:00Z"},"noInappropriateFees":{"urls":["https://theugandanjobline.com/2026/10/front-desk-administrator-2-positions-jobs-esom-school-of-music.html"],"rationale":"The summary text retrieved mentions no fee, but the provider page was not reviewed, so this is unconfirmed.","checkedAtUtc":"2026-10-10T12:00:00Z"},"noSensitiveDataAsk":{"urls":["https://theugandanjobline.com/2026/10/front-desk-administrator-2-positions-jobs-esom-school-of-music.html"],"rationale":"The retrieved summary asks for no passwords, codes or payments, but full application instructions were not reviewed.","checkedAtUtc":"2026-10-10T12:00:00Z"},"deadlinePlausible":{"urls":["https://theugandanjobline.com/2026/10/front-desk-administrator-2-positions-jobs-esom-school-of-music.html"],"rationale":"Source states 'Closes 7 Nov', which falls on or after the delivery date 2026-10-12. Not cross-checked against the provider page.","checkedAtUtc":"2026-10-10T12:00:00Z"},"duplicateChecked":{"urls":[],"rationale":"Title compared with all 115 catalog records and every row in this file using the app's bigram rule (threshold 0.85, 3-day window). Closest catalog title: 'CSO Call for Expressions of Project Intentions' at 0.373.","checkedAtUtc":"2026-10-10T12:00:00Z"}} | AO25: ["Locate the provider-owned listing and the official application link","Confirm no application, processing or placement fee on the official page","Confirm no inappropriate sensitive-data request on the official page","Confirm closing date and timezone on the official page","Qualifications and pay not captured"] | AQ25: =FALSE() | AR25: uganda | AS25: theugandanjobline.com | AT25: open_with_deadline | AU25: unresolved | AV25: 2026-10-12T09:15:53Z
A26: bwinja-agro-sales-manager-2026-10 | C26: create | D26: Sales Manager | E26: Bwinja Agro Farm | H26: job | I26: individual | J26: Sales manager role at Bwinja Agro Farm. | N26: Uganda (town not confirmed) | R26: unknown | U26: 46341 | V26: Closes 15 Nov | W26: unknown | X26: date | Y26: fixed | Z26: Apply as described on the source listing; the official application route is not yet confirmed. | AB26: https://theugandanjobline.com/2026/10/sales-manager-jobs-bwinja-agro-farm.html | AC26: [] | AE26: 2026-10-10T12:00:00Z | AF26: scraped | AG26: pending | AH26: =FALSE() | AI26: =FALSE() | AJ26: =FALSE() | AK26: =TRUE() | AL26: =TRUE() | AM26: {"sourceAuthentic":{"urls":["https://theugandanjobline.com/2026/10/sales-manager-jobs-bwinja-agro-farm.html"],"rationale":"Seen on The Ugandan Jobline, a third-party or index page. Provider-owned listing not yet located, so authenticity is unconfirmed.","checkedAtUtc":"2026-10-10T12:00:00Z"},"noInappropriateFees":{"urls":["https://theugandanjobline.com/2026/10/sales-manager-jobs-bwinja-agro-farm.html"],"rationale":"The summary text retrieved mentions no fee, but the provider page was not reviewed, so this is unconfirmed.","checkedAtUtc":"2026-10-10T12:00:00Z"},"noSensitiveDataAsk":{"urls":["https://theugandanjobline.com/2026/10/sales-manager-jobs-bwinja-agro-farm.html"],"rationale":"The retrieved summary asks for no passwords, codes or payments, but full application instructions were not reviewed.","checkedAtUtc":"2026-10-10T12:00:00Z"},"deadlinePlausible":{"urls":["https://theugandanjobline.com/2026/10/sales-manager-jobs-bwinja-agro-farm.html"],"rationale":"Source states 'Closes 15 Nov', which falls on or after the delivery date 2026-10-12. Not cross-checked against the provider page.","checkedAtUtc":"2026-10-10T12:00:00Z"},"duplicateChecked":{"urls":[],"rationale":"Title compared with all 115 catalog records and every row in this file using the app's bigram rule (threshold 0.85, 3-day window). Closest catalog title: 'Hospital Manager' at 0.593.","checkedAtUtc":"2026-10-10T12:00:00Z"}} | AO26: ["Locate the provider-owned listing and the official application link","Confirm no application, processing or placement fee on the official page","Confirm no inappropriate sensitive-data request on the official page","Confirm closing date and timezone on the official page","Qualifications, location and pay not captured"] | AP26: Small agribusiness employer; verify it exists and check for upfront-fee behaviour. | AQ26: =FALSE() | AR26: uganda | AS26: theugandanjobline.com | AT26: open_with_deadline | AU26: unresolved | AV26: 2026-10-12T09:15:53Z
A27: akes-english-teacher-primary-cambridge-2026-10 | C27: create | D27: English Language Teacher, Primary Cambridge Curriculum | E27: Aga Khan Education Services (AKES) | H27: job | I27: individual | J27: Primary English language teacher on the Cambridge curriculum with Aga Khan Education Services. | N27: Uganda (town not confirmed) | R27: unknown | U27: 46327 | V27: Closes 1 Nov | W27: unknown | X27: date | Y27: fixed | Z27: Apply as described on the source listing; the official application route is not yet confirmed. | AB27: https://theugandanjobline.com/2026/10/english-language-teacher-primary-cambridge-curriculum-jobs-aga-khan-education-services-akes.html | AC27: [] | AE27: 2026-10-10T12:00:00Z | AF27: scraped | AG27: pending | AH27: =FALSE() | AI27: =FALSE() | AJ27: =FALSE() | AK27: =TRUE() | AL27: =TRUE() | AM27: {"sourceAuthentic":{"urls":["https://theugandanjobline.com/2026/10/english-language-teacher-primary-cambridge-curriculum-jobs-aga-khan-education-services-akes.html"],"rationale":"Seen on The Ugandan Jobline, a third-party or index page. Provider-owned listing not yet located, so authenticity is unconfirmed.","checkedAtUtc":"2026-10-10T12:00:00Z"},"noInappropriateFees":{"urls":["https://theugandanjobline.com/2026/10/english-language-teacher-primary-cambridge-curriculum-jobs-aga-khan-education-services-akes.html"],"rationale":"The summary text retrieved mentions no fee, but the provider page was not reviewed, so this is unconfirmed.","checkedAtUtc":"2026-10-10T12:00:00Z"},"noSensitiveDataAsk":{"urls":["https://theugandanjobline.com/2026/10/english-language-teacher-primary-cambridge-curriculum-jobs-aga-khan-education-services-akes.html"],"rationale":"The retrieved summary asks for no passwords, codes or payments, but full application instructions were not reviewed.","checkedAtUtc":"2026-10-10T12:00:00Z"},"deadlinePlausible":{"urls":["https://theugandanjobline.com/2026/10/english-language-teacher-primary-cambridge-curriculum-jobs-aga-khan-education-services-akes.html"],"rationale":"Source states 'Closes 1 Nov', which falls on or after the delivery date 2026-10-12. Not cross-checked against the provider page.","checkedAtUtc":"2026-10-10T12:00:00Z"},"duplicateChecked":{"urls":[],"rationale":"Title compared with all 115 catalog records and every row in this file using the app's bigram rule (threshold 0.85, 3-day window). Closest catalog title: 'Social Studies Teacher, Upper Primary (PLE)' at 0.415.","checkedAtUtc":"2026-10-10T12:00:00Z"}} | AO27: ["Locate the provider-owned listing and the official application link","Confirm no application, processing or placement fee on the official page","Confirm no inappropriate sensitive-data request on the official page","Confirm closing date and timezone on the official page","Duty station, qualifications and pay not captured"] | AQ27: =FALSE() | AR27: uganda | AS27: theugandanjobline.com | AT27: open_with_deadline | AU27: unresolved | AV27: 2026-10-12T09:15:53Z
A28: digital-woman-uganda-accounts-assistant-2026-10 | C28: create | D28: Accounts Assistant | E28: Digital Woman Uganda | H28: job | I28: individual | J28: Accounts assistant role at Digital Woman Uganda. | N28: Uganda (town not confirmed) | R28: unknown | U28: 46321 | V28: Closes 26 Oct | W28: unknown | X28: date | Y28: fixed | Z28: Apply as described on the source listing; the official application route is not yet confirmed. | AB28: https://theugandanjobline.com/2026/10/accounts-assistant-jobs-digital-woman-uganda.html | AC28: [] | AE28: 2026-10-10T12:00:00Z | AF28: scraped | AG28: pending | AH28: =FALSE() | AI28: =FALSE() | AJ28: =FALSE() | AK28: =TRUE() | AL28: =TRUE() | AM28: {"sourceAuthentic":{"urls":["https://theugandanjobline.com/2026/10/accounts-assistant-jobs-digital-woman-uganda.html"],"rationale":"Seen on The Ugandan Jobline, a third-party or index page. Provider-owned listing not yet located, so authenticity is unconfirmed.","checkedAtUtc":"2026-10-10T12:00:00Z"},"noInappropriateFees":{"urls":["https://theugandanjobline.com/2026/10/accounts-assistant-jobs-digital-woman-uganda.html"],"rationale":"The summary text retrieved mentions no fee, but the provider page was not reviewed, so this is unconfirmed.","checkedAtUtc":"2026-10-10T12:00:00Z"},"noSensitiveDataAsk":{"urls":["https://theugandanjobline.com/2026/10/accounts-assistant-jobs-digital-woman-uganda.html"],"rationale":"The retrieved summary asks for no passwords, codes or payments, but full application instructions were not reviewed.","checkedAtUtc":"2026-10-10T12:00:00Z"},"deadlinePlausible":{"urls":["https://theugandanjobline.com/2026/10/accounts-assistant-jobs-digital-woman-uganda.html"],"rationale":"Source states 'Closes 26 Oct', which falls on or after the delivery date 2026-10-12. Not cross-checked against the provider page.","checkedAtUtc":"2026-10-10T12:00:00Z"},"duplicateChecked":{"urls":[],"rationale":"Title compared with all 115 catalog records and every row in this file using the app's bigram rule (threshold 0.85, 3-day window). Closest catalog title: 'Training Assistant, G-6, Entebbe' at 0.429.","checkedAtUtc":"2026-10-10T12:00:00Z"}} | AO28: ["Locate the provider-owned listing and the official application link","Confirm no application, processing or placement fee on the official page","Confirm no inappropriate sensitive-data request on the official page","Confirm closing date and timezone on the official page","Qualifications and pay not captured"] | AQ28: =FALSE() | AR28: uganda | AS28: theugandanjobline.com | AT28: open_with_deadline | AU28: unresolved | AV28: 2026-10-12T09:15:53Z
A29: case-medical-administration-clerk-2026-10 | C29: create | D29: Administration Clerk | E29: Case Medical Services | H29: job | I29: individual | J29: Administration clerk role at Case Medical Services. | N29: Uganda (town not confirmed) | R29: unknown | U29: 46309 | V29: Closes 14 Oct | W29: unknown | X29: date | Y29: fixed | Z29: Apply as described on the source listing; the official application route is not yet confirmed. | AB29: https://theugandanjobline.com/2026/10/administration-clerk-jobs-case-medical-services.html | AC29: [] | AE29: 2026-10-10T12:00:00Z | AF29: scraped | AG29: pending | AH29: =FALSE() | AI29: =FALSE() | AJ29: =FALSE() | AK29: =TRUE() | AL29: =TRUE() | AM29: {"sourceAuthentic":{"urls":["https://theugandanjobline.com/2026/10/administration-clerk-jobs-case-medical-services.html"],"rationale":"Seen on The Ugandan Jobline, a third-party or index page. Provider-owned listing not yet located, so authenticity is unconfirmed.","checkedAtUtc":"2026-10-10T12:00:00Z"},"noInappropriateFees":{"urls":["https://theugandanjobline.com/2026/10/administration-clerk-jobs-case-medical-services.html"],"rationale":"The summary text retrieved mentions no fee, but the provider page was not reviewed, so this is unconfirmed.","checkedAtUtc":"2026-10-10T12:00:00Z"},"noSensitiveDataAsk":{"urls":["https://theugandanjobline.com/2026/10/administration-clerk-jobs-case-medical-services.html"],"rationale":"The retrieved summary asks for no passwords, codes or payments, but full application instructions were not reviewed.","checkedAtUtc":"2026-10-10T12:00:00Z"},"deadlinePlausible":{"urls":["https://theugandanjobline.com/2026/10/administration-clerk-jobs-case-medical-services.html"],"rationale":"Source states 'Closes 14 Oct', which falls on or after the delivery date 2026-10-12. Not cross-checked against the provider page.","checkedAtUtc":"2026-10-10T12:00:00Z"},"duplicateChecked":{"urls":[],"rationale":"Title compared with all 115 catalog records and every row in this file using the app's bigram rule (threshold 0.85, 3-day window). Closest catalog title: 'Head, Credit Origination' at 0.341.","checkedAtUtc":"2026-10-10T12:00:00Z"}} | AO29: ["Locate the provider-owned listing and the official application link","Confirm no application, processing or placement fee on the official page","Confirm no inappropriate sensitive-data request on the official page","Confirm closing date and timezone on the official page","Qualifications and pay not captured"] | AP29: Short window at retrieval. | AQ29: =FALSE() | AR29: uganda | AS29: theugandanjobline.com | AT29: open_with_deadline | AU29: unresolved | AV29: 2026-10-12T09:15:53Z
A30: restless-development-advocacy-officer-2026-09 | C30: create | D30: Advocacy Officer | E30: Restless Development | H30: job | I30: individual | J30: Advocacy officer role at Restless Development. | N30: Uganda (town not confirmed) | R30: unknown | S30: Source title mentions 'Salary 23m'; currency and period not confirmed (likely UGX, possibly annual). | U30: 46308 | V30: Closes 13 Oct | W30: unknown | X30: date | Y30: fixed | Z30: Apply as described on the source listing; the official application route is not yet confirmed. | AB30: https://theugandanjobline.com/2026/09/advocacy-officer-jobs-restless-development.html | AC30: [] | AE30: 2026-10-10T12:00:00Z | AF30: scraped | AG30: pending | AH30: =FALSE() | AI30: =FALSE() | AJ30: =FALSE() | AK30: =TRUE() | AL30: =TRUE() | AM30: {"sourceAuthentic":{"urls":["https://theugandanjobline.com/2026/09/advocacy-officer-jobs-restless-development.html"],"rationale":"Seen on The Ugandan Jobline, a third-party or index page. Provider-owned listing not yet located, so authenticity is unconfirmed.","checkedAtUtc":"2026-10-10T12:00:00Z"},"noInappropriateFees":{"urls":["https://theugandanjobline.com/2026/09/advocacy-officer-jobs-restless-development.html"],"rationale":"The summary text retrieved mentions no fee, but the provider page was not reviewed, so this is unconfirmed.","checkedAtUtc":"2026-10-10T12:00:00Z"},"noSensitiveDataAsk":{"urls":["https://theugandanjobline.com/2026/09/advocacy-officer-jobs-restless-development.html"],"rationale":"The retrieved summary asks for no passwords, codes or payments, but full application instructions were not reviewed.","checkedAtUtc":"2026-10-10T12:00:00Z"},"deadlinePlausible":{"urls":["https://theugandanjobline.com/2026/09/advocacy-officer-jobs-restless-development.html"],"rationale":"Source states 'Closes 13 Oct', which falls on or after the delivery date 2026-10-12. Not cross-checked against the provider page.","checkedAtUtc":"2026-10-10T12:00:00Z"},"duplicateChecked":{"urls":[],"rationale":"Title compared with all 115 catalog records and every row in this file using the app's bigram rule (threshold 0.85, 3-day window). Closest catalog title: 'MEAL Officer' at 0.538.","checkedAtUtc":"2026-10-10T12:00:00Z"}} | AO30: ["Locate the provider-owned listing and the official application link","Confirm no application, processing or placement fee on the official page","Confirm no inappropriate sensitive-data request on the official page","Confirm closing date and timezone on the official page","Salary currency and period not confirmed"] | AP30: Short window at retrieval. Listing page snapshot seen 2026-10-10; some Ugandan Jobline index pages were 1 to 2 weeks old, so reconfirm the deadline on the employer page. | AQ30: =FALSE() | AR30: uganda | AS30: theugandanjobline.com | AT30: open_with_deadline | AU30: unresolved | AV30: 2026-10-12T09:15:53Z
A31: tum-sustainability-coordinator-2026-09 | C31: create | D31: Sustainability Coordinator | E31: Texans and Ugandans on Mission (T&UM) | H31: job | I31: individual | J31: Sustainability coordinator role at Texans and Ugandans on Mission (health category on the source site). | N31: Uganda (town not confirmed) | R31: unknown | U31: 46307 | V31: Closes 12 Oct | W31: unknown | X31: date | Y31: fixed | Z31: Apply as described on the source listing; the official application route is not yet confirmed. | AB31: https://theugandanjobline.com/2026/09/sustainability-coordinator-jobs-texans-and-ugandans-on-mission-tum.html | AC31: [] | AE31: 2026-10-10T12:00:00Z | AF31: scraped | AG31: pending | AH31: =FALSE() | AI31: =FALSE() | AJ31: =FALSE() | AK31: =TRUE() | AL31: =TRUE() | AM31: {"sourceAuthentic":{"urls":["https://theugandanjobline.com/2026/09/sustainability-coordinator-jobs-texans-and-ugandans-on-mission-tum.html"],"rationale":"Seen on The Ugandan Jobline, a third-party or index page. Provider-owned listing not yet located, so authenticity is unconfirmed.","checkedAtUtc":"2026-10-10T12:00:00Z"},"noInappropriateFees":{"urls":["https://theugandanjobline.com/2026/09/sustainability-coordinator-jobs-texans-and-ugandans-on-mission-tum.html"],"rationale":"The summary text retrieved mentions no fee, but the provider page was not reviewed, so this is unconfirmed.","checkedAtUtc":"2026-10-10T12:00:00Z"},"noSensitiveDataAsk":{"urls":["https://theugandanjobline.com/2026/09/sustainability-coordinator-jobs-texans-and-ugandans-on-mission-tum.html"],"rationale":"The retrieved summary asks for no passwords, codes or payments, but full application instructions were not reviewed.","checkedAtUtc":"2026-10-10T12:00:00Z"},"deadlinePlausible":{"urls":["https://theugandanjobline.com/2026/09/sustainability-coordinator-jobs-texans-and-ugandans-on-mission-tum.html"],"rationale":"Source states 'Closes 12 Oct', which falls on or after the delivery date 2026-10-12. Not cross-checked against the provider page.","checkedAtUtc":"2026-10-10T12:00:00Z"},"duplicateChecked":{"urls":[],"rationale":"Title compared with all 115 catalog records and every row in this file using the app's bigram rule (threshold 0.85, 3-day window). Closest catalog title: 'Supply Chain Coordinator' at 0.619.","checkedAtUtc":"2026-10-10T12:00:00Z"}} | AO31: ["Locate the provider-owned listing and the official application link","Confirm no application, processing or placement fee on the official page","Confirm no inappropriate sensitive-data request on the official page","Confirm closing date and timezone on the official page","Qualifications and pay not captured"] | AP31: Closes today (2026-10-12), re-check immediately. Short window at retrieval. Listing page snapshot seen 2026-10-10; some Ugandan Jobline index pages were 1 to 2 weeks old, so reconfirm the deadline on the employer page. | AQ31: =FALSE() | AR31: uganda | AS31: theugandanjobline.com | AT31: open_with_deadline | AU31: unresolved | AV31: 2026-10-12T09:15:53Z
A32: ugafode-ict-security-officer-2026-09 | C32: create | D32: ICT Security Officer | E32: UGAFODE Microfinance | H32: job | I32: individual | J32: ICT security officer role at UGAFODE Microfinance. | N32: Uganda (town not confirmed) | R32: unknown | U32: 46308 | V32: Closes 13 Oct | W32: unknown | X32: date | Y32: fixed | Z32: Apply as described on the source listing; the official application route is not yet confirmed. | AB32: https://theugandanjobline.com/2026/09/ict-security-officer-jobs-ugafode-microfinance-2.html | AC32: [] | AE32: 2026-10-10T12:00:00Z | AF32: scraped | AG32: pending | AH32: =FALSE() | AI32: =FALSE() | AJ32: =FALSE() | AK32: =TRUE() | AL32: =TRUE() | AM32: {"sourceAuthentic":{"urls":["https://theugandanjobline.com/2026/09/ict-security-officer-jobs-ugafode-microfinance-2.html"],"rationale":"Seen on The Ugandan Jobline, a third-party or index page. Provider-owned listing not yet located, so authenticity is unconfirmed.","checkedAtUtc":"2026-10-10T12:00:00Z"},"noInappropriateFees":{"urls":["https://theugandanjobline.com/2026/09/ict-security-officer-jobs-ugafode-microfinance-2.html"],"rationale":"The summary text retrieved mentions no fee, but the provider page was not reviewed, so this is unconfirmed.","checkedAtUtc":"2026-10-10T12:00:00Z"},"noSensitiveDataAsk":{"urls":["https://theugandanjobline.com/2026/09/ict-security-officer-jobs-ugafode-microfinance-2.html"],"rationale":"The retrieved summary asks for no passwords, codes or payments, but full application instructions were not reviewed.","checkedAtUtc":"2026-10-10T12:00:00Z"},"deadlinePlausible":{"urls":["https://theugandanjobline.com/2026/09/ict-security-officer-jobs-ugafode-microfinance-2.html"],"rationale":"Source states 'Closes 13 Oct', which falls on or after the delivery date 2026-10-12. Not cross-checked against the provider page.","checkedAtUtc":"2026-10-10T12:00:00Z"},"duplicateChecked":{"urls":[],"rationale":"Title compared with all 115 catalog records and every row in this file using the app's bigram rule (threshold 0.85, 3-day window). Closest catalog title: 'Security Guard' at 0.516.","checkedAtUtc":"2026-10-10T12:00:00Z"}} | AO32: ["Locate the provider-owned listing and the official application link","Confirm no application, processing or placement fee on the official page","Confirm no inappropriate sensitive-data request on the official page","Confirm closing date and timezone on the official page","Qualifications and pay not captured"] | AP32: Short window at retrieval. Listing page snapshot seen 2026-10-10; some Ugandan Jobline index pages were 1 to 2 weeks old, so reconfirm the deadline on the employer page. | AQ32: =FALSE() | AR32: uganda | AS32: theugandanjobline.com | AT32: open_with_deadline | AU32: unresolved | AV32: 2026-10-12T09:15:53Z
A33: hha-east-africa-director-2026-09 | C33: create | D33: East Africa Director | E33: Hope Health Action (HHA) | H33: job | I33: individual | J33: Contract East Africa Director role at Hope Health Action. | N33: Uganda (town not confirmed) | R33: unknown | U33: 46311 | V33: Closes 16 Oct | W33: unknown | X33: date | Y33: fixed | Z33: Apply as described on the source listing; the official application route is not yet confirmed. | AB33: https://theugandanjobline.com/2026/09/east-africa-director-jobs-hope-health-action.html | AC33: [] | AE33: 2026-10-10T12:00:00Z | AF33: scraped | AG33: pending | AH33: =FALSE() | AI33: =FALSE() | AJ33: =FALSE() | AK33: =TRUE() | AL33: =TRUE() | AM33: {"sourceAuthentic":{"urls":["https://theugandanjobline.com/2026/09/east-africa-director-jobs-hope-health-action.html"],"rationale":"Seen on The Ugandan Jobline, a third-party or index page. Provider-owned listing not yet located, so authenticity is unconfirmed.","checkedAtUtc":"2026-10-10T12:00:00Z"},"noInappropriateFees":{"urls":["https://theugandanjobline.com/2026/09/east-africa-director-jobs-hope-health-action.html"],"rationale":"The summary text retrieved mentions no fee, but the provider page was not reviewed, so this is unconfirmed.","checkedAtUtc":"2026-10-10T12:00:00Z"},"noSensitiveDataAsk":{"urls":["https://theugandanjobline.com/2026/09/east-africa-director-jobs-hope-health-action.html"],"rationale":"The retrieved summary asks for no passwords, codes or payments, but full application instructions were not reviewed.","checkedAtUtc":"2026-10-10T12:00:00Z"},"deadlinePlausible":{"urls":["https://theugandanjobline.com/2026/09/east-africa-director-jobs-hope-health-action.html"],"rationale":"Source states 'Closes 16 Oct', which falls on or after the delivery date 2026-10-12. Not cross-checked against the provider page.","checkedAtUtc":"2026-10-10T12:00:00Z"},"duplicateChecked":{"urls":[],"rationale":"Title compared with all 115 catalog records and every row in this file using the app's bigram rule (threshold 0.85, 3-day window). Closest catalog title: 'Project Director, PlayMatters' at 0.409.","checkedAtUtc":"2026-10-10T12:00:00Z"}} | AO33: ["Locate the provider-owned listing and the official application link","Confirm no application, processing or placement fee on the official page","Confirm no inappropriate sensitive-data request on the official page","Confirm closing date and timezone on the official page","Duty station and contract terms not captured"] | AP33: Senior role. Listing page snapshot seen 2026-10-10; some Ugandan Jobline index pages were 1 to 2 weeks old, so reconfirm the deadline on the employer page. | AQ33: =FALSE() | AR33: uganda | AS33: theugandanjobline.com | AT33: open_with_deadline | AU33: unresolved | AV33: 2026-10-12T09:15:53Z
A34: prime-concepts-sales-executive-assistant-2026-09 | C34: create | D34: Sales Executive Assistant | E34: Prime Concepts Packaging | H34: job | I34: individual | J34: Sales executive assistant role at Prime Concepts Packaging. | N34: Uganda (town not confirmed) | R34: unknown | U34: 46325 | V34: Closes 30 Oct | W34: unknown | X34: date | Y34: fixed | Z34: Apply as described on the source listing; the official application route is not yet confirmed. | AB34: https://theugandanjobline.com/2026/09/sales-executive-assistant-jobs-prime-concepts-packaging.html | AC34: [] | AE34: 2026-10-10T12:00:00Z | AF34: scraped | AG34: pending | AH34: =FALSE() | AI34: =FALSE() | AJ34: =FALSE() | AK34: =TRUE() | AL34: =TRUE() | AM34: {"sourceAuthentic":{"urls":["https://theugandanjobline.com/2026/09/sales-executive-assistant-jobs-prime-concepts-packaging.html"],"rationale":"Seen on The Ugandan Jobline, a third-party or index page. Provider-owned listing not yet located, so authenticity is unconfirmed.","checkedAtUtc":"2026-10-10T12:00:00Z"},"noInappropriateFees":{"urls":["https://theugandanjobline.com/2026/09/sales-executive-assistant-jobs-prime-concepts-packaging.html"],"rationale":"The summary text retrieved mentions no fee, but the provider page was not reviewed, so this is unconfirmed.","checkedAtUtc":"2026-10-10T12:00:00Z"},"noSensitiveDataAsk":{"urls":["https://theugandanjobline.com/2026/09/sales-executive-assistant-jobs-prime-concepts-packaging.html"],"rationale":"The retrieved summary asks for no passwords, codes or payments, but full application instructions were not reviewed.","checkedAtUtc":"2026-10-10T12:00:00Z"},"deadlinePlausible":{"urls":["https://theugandanjobline.com/2026/09/sales-executive-assistant-jobs-prime-concepts-packaging.html"],"rationale":"Source states 'Closes 30 Oct', which falls on or after the delivery date 2026-10-12. Not cross-checked against the provider page.","checkedAtUtc":"2026-10-10T12:00:00Z"},"duplicateChecked":{"urls":[],"rationale":"Title compared with all 115 catalog records and every row in this file using the app's bigram rule (threshold 0.85, 3-day window). Closest catalog title: 'Creative Sales Representative' at 0.489.","checkedAtUtc":"2026-10-10T12:00:00Z"}} | AO34: ["Locate the provider-owned listing and the official application link","Confirm no application, processing or placement fee on the official page","Confirm no inappropriate sensitive-data request on the official page","Confirm closing date and timezone on the official page","Qualifications and pay not captured"] | AQ34: =FALSE() | AR34: uganda | AS34: theugandanjobline.com | AT34: open_with_deadline | AU34: unresolved | AV34: 2026-10-12T09:15:53Z
A35: pinnacle-partners-professional-driver-2026-09 | C35: create | D35: Professional Driver | E35: Pinnacle Partners | H35: job | I35: individual | J35: Professional driver role at Pinnacle Partners. | N35: Uganda (town not confirmed) | R35: unknown | U35: 46323 | V35: Closes 28 Oct | W35: unknown | X35: date | Y35: fixed | Z35: Apply as described on the source listing; the official application route is not yet confirmed. | AB35: https://theugandanjobline.com/2026/09/professional-driver-jobs-pinnacle-partners.html | AC35: [] | AE35: 2026-10-10T12:00:00Z | AF35: scraped | AG35: pending | AH35: =FALSE() | AI35: =FALSE() | AJ35: =FALSE() | AK35: =TRUE() | AL35: =TRUE() | AM35: {"sourceAuthentic":{"urls":["https://theugandanjobline.com/2026/09/professional-driver-jobs-pinnacle-partners.html"],"rationale":"Seen on The Ugandan Jobline, a third-party or index page. Provider-owned listing not yet located, so authenticity is unconfirmed.","checkedAtUtc":"2026-10-10T12:00:00Z"},"noInappropriateFees":{"urls":["https://theugandanjobline.com/2026/09/professional-driver-jobs-pinnacle-partners.html"],"rationale":"The summary text retrieved mentions no fee, but the provider page was not reviewed, so this is unconfirmed.","checkedAtUtc":"2026-10-10T12:00:00Z"},"noSensitiveDataAsk":{"urls":["https://theugandanjobline.com/2026/09/professional-driver-jobs-pinnacle-partners.html"],"rationale":"The retrieved summary asks for no passwords, codes or payments, but full application instructions were not reviewed.","checkedAtUtc":"2026-10-10T12:00:00Z"},"deadlinePlausible":{"urls":["https://theugandanjobline.com/2026/09/professional-driver-jobs-pinnacle-partners.html"],"rationale":"Source states 'Closes 28 Oct', which falls on or after the delivery date 2026-10-12. Not cross-checked against the provider page.","checkedAtUtc":"2026-10-10T12:00:00Z"},"duplicateChecked":{"urls":[],"rationale":"Title compared with all 115 catalog records and every row in this file using the app's bigram rule (threshold 0.85, 3-day window). Closest catalog title: 'World Bank Group Young Professionals Program 2027' at 0.367.","checkedAtUtc":"2026-10-10T12:00:00Z"}} | AO35: ["Locate the provider-owned listing and the official application link","Confirm no application, processing or placement fee on the official page","Confirm no inappropriate sensitive-data request on the official page","Confirm closing date and timezone on the official page","Licence class, location and pay not captured"] | AP35: Vocational option without a degree requirement if confirmed. | AQ35: =FALSE() | AR35: uganda | AS35: theugandanjobline.com | AT35: open_with_deadline | AU35: unresolved | AV35: 2026-10-12T09:15:53Z
A36: nft-consult-deputy-service-head-2026-09 | C36: create | D36: Deputy Service Head | E36: NFT Consult | H36: job | I36: individual | J36: Deputy service head role (engineering category) at NFT Consult. | N36: Uganda (town not confirmed) | R36: unknown | U36: 46320 | V36: Closes 25 Oct | W36: unknown | X36: date | Y36: fixed | Z36: Apply as described on the source listing; the official application route is not yet confirmed. | AB36: https://theugandanjobline.com/2026/09/deputy-service-head-jobs-nft-consult.html | AC36: [] | AE36: 2026-10-10T12:00:00Z | AF36: scraped | AG36: pending | AH36: =FALSE() | AI36: =FALSE() | AJ36: =FALSE() | AK36: =TRUE() | AL36: =TRUE() | AM36: {"sourceAuthentic":{"urls":["https://theugandanjobline.com/2026/09/deputy-service-head-jobs-nft-consult.html"],"rationale":"Seen on The Ugandan Jobline, a third-party or index page. Provider-owned listing not yet located, so authenticity is unconfirmed.","checkedAtUtc":"2026-10-10T12:00:00Z"},"noInappropriateFees":{"urls":["https://theugandanjobline.com/2026/09/deputy-service-head-jobs-nft-consult.html"],"rationale":"The summary text retrieved mentions no fee, but the provider page was not reviewed, so this is unconfirmed.","checkedAtUtc":"2026-10-10T12:00:00Z"},"noSensitiveDataAsk":{"urls":["https://theugandanjobline.com/2026/09/deputy-service-head-jobs-nft-consult.html"],"rationale":"The retrieved summary asks for no passwords, codes or payments, but full application instructions were not reviewed.","checkedAtUtc":"2026-10-10T12:00:00Z"},"deadlinePlausible":{"urls":["https://theugandanjobline.com/2026/09/deputy-service-head-jobs-nft-consult.html"],"rationale":"Source states 'Closes 25 Oct', which falls on or after the delivery date 2026-10-12. Not cross-checked against the provider page.","checkedAtUtc":"2026-10-10T12:00:00Z"},"duplicateChecked":{"urls":[],"rationale":"Title compared with all 115 catalog records and every row in this file using the app's bigram rule (threshold 0.85, 3-day window). Closest catalog title: 'Customer Service Representative' at 0.4.","checkedAtUtc":"2026-10-10T12:00:00Z"}} | AO36: ["Locate the provider-owned listing and the official application link","Confirm no application, processing or placement fee on the official page","Confirm no inappropriate sensitive-data request on the official page","Confirm closing date and timezone on the official page","Client employer, qualifications and pay not captured"] | AP36: NFT Consult appears to be a recruiter; confirm the real employer. | AQ36: =FALSE() | AR36: uganda | AS36: theugandanjobline.com | AT36: open_with_deadline | AU36: unresolved | AV36: 2026-10-12T09:15:53Z
A37: nft-consult-deputy-assistant-sales-head-2026-09 | C37: create | D37: Deputy or Assistant Sales Head | E37: NFT Consult | H37: job | I37: individual | J37: Deputy or assistant sales head role at NFT Consult. | N37: Uganda (town not confirmed) | R37: unknown | U37: 46320 | V37: Closes 25 Oct | W37: unknown | X37: date | Y37: fixed | Z37: Apply as described on the source listing; the official application route is not yet confirmed. | AB37: https://theugandanjobline.com/2026/09/deputy-assistant-sales-head-jobs-nft-consult.html | AC37: [] | AE37: 2026-10-10T12:00:00Z | AF37: scraped | AG37: pending | AH37: =FALSE() | AI37: =FALSE() | AJ37: =FALSE() | AK37: =TRUE() | AL37: =TRUE() | AM37: {"sourceAuthentic":{"urls":["https://theugandanjobline.com/2026/09/deputy-assistant-sales-head-jobs-nft-consult.html"],"rationale":"Seen on The Ugandan Jobline, a third-party or index page. Provider-owned listing not yet located, so authenticity is unconfirmed.","checkedAtUtc":"2026-10-10T12:00:00Z"},"noInappropriateFees":{"urls":["https://theugandanjobline.com/2026/09/deputy-assistant-sales-head-jobs-nft-consult.html"],"rationale":"The summary text retrieved mentions no fee, but the provider page was not reviewed, so this is unconfirmed.","checkedAtUtc":"2026-10-10T12:00:00Z"},"noSensitiveDataAsk":{"urls":["https://theugandanjobline.com/2026/09/deputy-assistant-sales-head-jobs-nft-consult.html"],"rationale":"The retrieved summary asks for no passwords, codes or payments, but full application instructions were not reviewed.","checkedAtUtc":"2026-10-10T12:00:00Z"},"deadlinePlausible":{"urls":["https://theugandanjobline.com/2026/09/deputy-assistant-sales-head-jobs-nft-consult.html"],"rationale":"Source states 'Closes 25 Oct', which falls on or after the delivery date 2026-10-12. Not cross-checked against the provider page.","checkedAtUtc":"2026-10-10T12:00:00Z"},"duplicateChecked":{"urls":[],"rationale":"Title compared with all 115 catalog records and every row in this file using the app's bigram rule (threshold 0.85, 3-day window). Closest catalog title: 'Creative Sales Representative' at 0.4.","checkedAtUtc":"2026-10-10T12:00:00Z"}} | AO37: ["Locate the provider-owned listing and the official application link","Confirm no application, processing or placement fee on the official page","Confirm no inappropriate sensitive-data request on the official page","Confirm closing date and timezone on the official page","Client employer, qualifications and pay not captured"] | AP37: NFT Consult appears to be a recruiter; confirm the real employer. | AQ37: =FALSE() | AR37: uganda | AS37: theugandanjobline.com | AT37: open_with_deadline | AU37: unresolved | AV37: 2026-10-12T09:15:53Z
A38: stanbic-manager-business-development-west-2026-09 | C38: create | D38: Manager, Business Development, West and Far West | E38: Stanbic Bank Uganda | F38: https://www.stanbicbank.co.ug/ | H38: job | I38: individual | J38: Business development manager role covering the West and Far West regions at Stanbic Bank. | N38: Western Uganda | R38: unknown | U38: 46320 | V38: Closes 25 Oct | W38: unknown | X38: date | Y38: fixed | Z38: Apply as described on the source listing; the official application route is not yet confirmed. | AB38: https://theugandanjobline.com/2026/09/manager-business-development-west-far-west-jobs-stanbic-bank.html | AC38: [] | AE38: 2026-10-10T12:00:00Z | AF38: scraped | AG38: pending | AH38: =FALSE() | AI38: =FALSE() | AJ38: =FALSE() | AK38: =TRUE() | AL38: =TRUE() | AM38: {"sourceAuthentic":{"urls":["https://theugandanjobline.com/2026/09/manager-business-development-west-far-west-jobs-stanbic-bank.html"],"rationale":"Seen on The Ugandan Jobline, a third-party or index page. Provider-owned listing not yet located, so authenticity is unconfirmed.","checkedAtUtc":"2026-10-10T12:00:00Z"},"noInappropriateFees":{"urls":["https://theugandanjobline.com/2026/09/manager-business-development-west-far-west-jobs-stanbic-bank.html"],"rationale":"The summary text retrieved mentions no fee, but the provider page was not reviewed, so this is unconfirmed.","checkedAtUtc":"2026-10-10T12:00:00Z"},"noSensitiveDataAsk":{"urls":["https://theugandanjobline.com/2026/09/manager-business-development-west-far-west-jobs-stanbic-bank.html"],"rationale":"The retrieved summary asks for no passwords, codes or payments, but full application instructions were not reviewed.","checkedAtUtc":"2026-10-10T12:00:00Z"},"deadlinePlausible":{"urls":["https://theugandanjobline.com/2026/09/manager-business-development-west-far-west-jobs-stanbic-bank.html"],"rationale":"Source states 'Closes 25 Oct', which falls on or after the delivery date 2026-10-12. Not cross-checked against the provider page.","checkedAtUtc":"2026-10-10T12:00:00Z"},"duplicateChecked":{"urls":[],"rationale":"Title compared with all 115 catalog records and every row in this file using the app's bigram rule (threshold 0.85, 3-day window). Closest catalog title: 'Business Development and Green Finance Readiness Support Consultant' at 0.578.","checkedAtUtc":"2026-10-10T12:00:00Z"}} | AO38: ["Locate the provider-owned listing and the official application link","Confirm no application, processing or placement fee on the official page","Confirm no inappropriate sensitive-data request on the official page","Confirm closing date and timezone on the official page","Exact duty station and qualifications not captured"] | AP38: Verify on the Stanbic careers portal. | AQ38: =FALSE() | AR38: uganda | AS38: theugandanjobline.com | AT38: open_with_deadline | AU38: unresolved | AV38: 2026-10-12T09:15:53Z
A39: cic-insurance-agent-2026-09 | C39: create | D39: Insurance Agent (several positions) | E39: CIC Insurance Uganda | H39: job | I39: individual | J39: Several agent positions, tagged no experience required, at CIC Insurance Uganda. | N39: Uganda (town not confirmed) | R39: unknown | U39: 46319 | V39: Closes 24 Oct | W39: unknown | X39: date | Y39: fixed | Z39: Apply as described on the source listing; the official application route is not yet confirmed. | AB39: https://theugandanjobline.com/2026/09/agent-several-no-experience-jobs-jobs-cic-insurance-uganda.html | AC39: [] | AE39: 2026-10-10T12:00:00Z | AF39: scraped | AG39: pending | AH39: =FALSE() | AI39: =FALSE() | AJ39: =FALSE() | AK39: =TRUE() | AL39: =TRUE() | AM39: {"sourceAuthentic":{"urls":["https://theugandanjobline.com/2026/09/agent-several-no-experience-jobs-jobs-cic-insurance-uganda.html"],"rationale":"Seen on The Ugandan Jobline, a third-party or index page. Provider-owned listing not yet located, so authenticity is unconfirmed.","checkedAtUtc":"2026-10-10T12:00:00Z"},"noInappropriateFees":{"urls":["https://theugandanjobline.com/2026/09/agent-several-no-experience-jobs-jobs-cic-insurance-uganda.html"],"rationale":"The summary text retrieved mentions no fee, but the provider page was not reviewed, so this is unconfirmed.","checkedAtUtc":"2026-10-10T12:00:00Z"},"noSensitiveDataAsk":{"urls":["https://theugandanjobline.com/2026/09/agent-several-no-experience-jobs-jobs-cic-insurance-uganda.html"],"rationale":"The retrieved summary asks for no passwords, codes or payments, but full application instructions were not reviewed.","checkedAtUtc":"2026-10-10T12:00:00Z"},"deadlinePlausible":{"urls":["https://theugandanjobline.com/2026/09/agent-several-no-experience-jobs-jobs-cic-insurance-uganda.html"],"rationale":"Source states 'Closes 24 Oct', which falls on or after the delivery date 2026-10-12. Not cross-checked against the provider page.","checkedAtUtc":"2026-10-10T12:00:00Z"},"duplicateChecked":{"urls":[],"rationale":"Title compared with all 115 catalog records and every row in this file using the app's bigram rule (threshold 0.85, 3-day window). Closest catalog title: 'Digital Services Specialist / Client Operations Manager' at 0.507.","checkedAtUtc":"2026-10-10T12:00:00Z"}} | AO39: ["Locate the provider-owned listing and the official application link","Confirm no application, processing or placement fee on the official page","Confirm no inappropriate sensitive-data request on the official page","Confirm closing date and timezone on the official page","Commission versus salary not captured"] | AP39: Agent roles are often commission-based. Confirm pay structure. | AQ39: =FALSE() | AR39: uganda | AS39: theugandanjobline.com | AT39: open_with_deadline | AU39: unresolved | AV39: 2026-10-12T09:15:53Z
A40: xclusive-uganda-management-hr-consultancy-rfp-2026-10 | C40: create | D40: Request for Proposals: Management and Human Resource Consultancy | E40: Xclusive Uganda | H40: consultancy | I40: organization | J40: Request for proposals for a management and human resource consultancy issued by Xclusive Uganda. | N40: Uganda (town not confirmed) | R40: unknown | U40: 46311 | V40: Closes 16 Oct | W40: unknown | X40: date | Y40: fixed | Z40: Apply as described on the source listing; the official application route is not yet confirmed. | AB40: https://theugandanjobline.com/2026/10/request-for-proposals-rfp-management-human-resource-consultancy-xclusive-uganda.html | AC40: [] | AE40: 2026-10-10T12:00:00Z | AF40: scraped | AG40: pending | AH40: =FALSE() | AI40: =FALSE() | AJ40: =FALSE() | AK40: =TRUE() | AL40: =TRUE() | AM40: {"sourceAuthentic":{"urls":["https://theugandanjobline.com/2026/10/request-for-proposals-rfp-management-human-resource-consultancy-xclusive-uganda.html"],"rationale":"Seen on The Ugandan Jobline, a third-party or index page. Provider-owned listing not yet located, so authenticity is unconfirmed.","checkedAtUtc":"2026-10-10T12:00:00Z"},"noInappropriateFees":{"urls":["https://theugandanjobline.com/2026/10/request-for-proposals-rfp-management-human-resource-consultancy-xclusive-uganda.html"],"rationale":"The summary text retrieved mentions no fee, but the provider page was not reviewed, so this is unconfirmed.","checkedAtUtc":"2026-10-10T12:00:00Z"},"noSensitiveDataAsk":{"urls":["https://theugandanjobline.com/2026/10/request-for-proposals-rfp-management-human-resource-consultancy-xclusive-uganda.html"],"rationale":"The retrieved summary asks for no passwords, codes or payments, but full application instructions were not reviewed.","checkedAtUtc":"2026-10-10T12:00:00Z"},"deadlinePlausible":{"urls":["https://theugandanjobline.com/2026/10/request-for-proposals-rfp-management-human-resource-consultancy-xclusive-uganda.html"],"rationale":"Source states 'Closes 16 Oct', which falls on or after the delivery date 2026-10-12. Not cross-checked against the provider page.","checkedAtUtc":"2026-10-10T12:00:00Z"},"duplicateChecked":{"urls":[],"rationale":"Title compared with all 115 catalog records and every row in this file using the app's bigram rule (threshold 0.85, 3-day window). Closest catalog title: 'Business Development and Green Finance Readiness Support Consultant' at 0.537.","checkedAtUtc":"2026-10-10T12:00:00Z"}} | AO40: ["Locate the provider-owned listing and the official application link","Confirm no application, processing or placement fee on the official page","Confirm no inappropriate sensitive-data request on the official page","Confirm closing date and timezone on the official page","Scope, budget and bidder eligibility not captured"] | AP40: Likely suits firms rather than individuals. | AQ40: =FALSE() | AR40: uganda | AS40: theugandanjobline.com | AT40: open_with_deadline | AU40: unresolved | AV40: 2026-10-12T09:15:53Z
A41: xclusive-uganda-compound-designer-gardener-2026-10 | C41: create | D41: Compound Designer or Gardener | E41: Xclusive Uganda | H41: job | I41: individual | J41: Compound designer or gardener position at Xclusive Uganda. | N41: Uganda (town not confirmed) | R41: unknown | U41: 46311 | V41: Closes 16 Oct | W41: unknown | X41: date | Y41: fixed | Z41: Apply as described on the source listing; the official application route is not yet confirmed. | AB41: https://theugandanjobline.com/2026/10/compound-designer-gardener-jobs-xclusive-uganda.html | AC41: [] | AE41: 2026-10-10T12:00:00Z | AF41: scraped | AG41: pending | AH41: =FALSE() | AI41: =FALSE() | AJ41: =FALSE() | AK41: =TRUE() | AL41: =TRUE() | AM41: {"sourceAuthentic":{"urls":["https://theugandanjobline.com/2026/10/compound-designer-gardener-jobs-xclusive-uganda.html"],"rationale":"Seen on The Ugandan Jobline, a third-party or index page. Provider-owned listing not yet located, so authenticity is unconfirmed.","checkedAtUtc":"2026-10-10T12:00:00Z"},"noInappropriateFees":{"urls":["https://theugandanjobline.com/2026/10/compound-designer-gardener-jobs-xclusive-uganda.html"],"rationale":"The summary text retrieved mentions no fee, but the provider page was not reviewed, so this is unconfirmed.","checkedAtUtc":"2026-10-10T12:00:00Z"},"noSensitiveDataAsk":{"urls":["https://theugandanjobline.com/2026/10/compound-designer-gardener-jobs-xclusive-uganda.html"],"rationale":"The retrieved summary asks for no passwords, codes or payments, but full application instructions were not reviewed.","checkedAtUtc":"2026-10-10T12:00:00Z"},"deadlinePlausible":{"urls":["https://theugandanjobline.com/2026/10/compound-designer-gardener-jobs-xclusive-uganda.html"],"rationale":"Source states 'Closes 16 Oct', which falls on or after the delivery date 2026-10-12. Not cross-checked against the provider page.","checkedAtUtc":"2026-10-10T12:00:00Z"},"duplicateChecked":{"urls":[],"rationale":"Title compared with all 115 catalog records and every row in this file using the app's bigram rule (threshold 0.85, 3-day window). Closest catalog title: 'Experience Designer' at 0.439.","checkedAtUtc":"2026-10-10T12:00:00Z"}} | AO41: ["Locate the provider-owned listing and the official application link","Confirm no application, processing or placement fee on the official page","Confirm no inappropriate sensitive-data request on the official page","Confirm closing date and timezone on the official page","Location and pay not captured"] | AP41: Vocational option without a degree requirement if confirmed. | AQ41: =FALSE() | AR41: uganda | AS41: theugandanjobline.com | AT41: open_with_deadline | AU41: unresolved | AV41: 2026-10-12T09:15:53Z
A42: agro-processing-plant-composting-manager-2026-10 | C42: exclude | D42: Composting Site By-Product Operations Manager | E42: Agro Processing Plant | H42: job | I42: individual | J42: Composting site by-product operations manager at an agro processing plant (employer name shown generically on the source). | N42: Uganda (town not confirmed) | R42: unknown | U42: 46306 | V42: Closes 11 Oct | W42: unknown | X42: date | Y42: fixed | Z42: Apply as described on the source listing; the official application route is not yet confirmed. | AB42: https://theugandanjobline.com/2026/10/composting-site-by-product-operations-manager-jobs-agro-processing-plant.html | AC42: [] | AE42: 2026-10-10T12:00:00Z | AF42: scraped | AG42: flagged | AH42: =FALSE() | AI42: =FALSE() | AJ42: =FALSE() | AK42: =FALSE() | AL42: =TRUE() | AM42: {"sourceAuthentic":{"urls":["https://theugandanjobline.com/2026/10/composting-site-by-product-operations-manager-jobs-agro-processing-plant.html"],"rationale":"Seen on The Ugandan Jobline, a third-party or index page. Provider-owned listing not yet located, so authenticity is unconfirmed.","checkedAtUtc":"2026-10-10T12:00:00Z"},"noInappropriateFees":{"urls":["https://theugandanjobline.com/2026/10/composting-site-by-product-operations-manager-jobs-agro-processing-plant.html"],"rationale":"The summary text retrieved mentions no fee, but the provider page was not reviewed, so this is unconfirmed.","checkedAtUtc":"2026-10-10T12:00:00Z"},"noSensitiveDataAsk":{"urls":["https://theugandanjobline.com/2026/10/composting-site-by-product-operations-manager-jobs-agro-processing-plant.html"],"rationale":"The retrieved summary asks for no passwords, codes or payments, but full application instructions were not reviewed.","checkedAtUtc":"2026-10-10T12:00:00Z"},"deadlinePlausible":{"urls":["https://theugandanjobline.com/2026/10/composting-site-by-product-operations-manager-jobs-agro-processing-plant.html"],"rationale":"Source states 'Closes 11 Oct'. Not cross-checked against the provider page.","checkedAtUtc":"2026-10-10T12:00:00Z"},"duplicateChecked":{"urls":[],"rationale":"Title compared with all 115 catalog records and every row in this file using the app's bigram rule (threshold 0.85, 3-day window). Closest catalog title: 'Digital Services Specialist / Client Operations Manager' at 0.488.","checkedAtUtc":"2026-10-10T12:00:00Z"}} | AO42: ["Real employer identity not shown"] | AP42: Closing date 2026-10-11 passed before delivery on 2026-10-12. Closed on 11 Oct, before delivery. Employer is anonymous on the source, so authenticity is hard to confirm. | AQ42: =FALSE() | AR42: uganda | AS42: theugandanjobline.com | AT42: expired_or_excluded | AU42: expired | AV42: 2026-10-12T09:15:53Z
A43: path-supply-chain-specialist-cold-chain-uganda | C43: create | D43: Supply Chain Specialist, Evolving Cold Chain Equipment Project | E43: PATH | H43: job | I43: individual | J43: Supply chain specialist role on PATH's evolving cold chain equipment project, listed for Kampala. | N43: Kampala, Uganda | R43: unknown | Y43: fixed | Z43: Apply as described on the source listing; the official application route is not yet confirmed. | AB43: https://www.unjobnet.org/jobs/detail/path-supply-chain-specialist-evolving-cold-chain-equipment-project-89199677 | AC43: [] | AE43: 2026-10-10T12:00:00Z | AF43: scraped | AG43: pending | AH43: =FALSE() | AI43: =FALSE() | AJ43: =FALSE() | AK43: =FALSE() | AL43: =TRUE() | AM43: {"sourceAuthentic":{"urls":["https://www.unjobnet.org/jobs/detail/path-supply-chain-specialist-evolving-cold-chain-equipment-project-89199677"],"rationale":"Seen on UNjobnet, a third-party or index page. Provider-owned listing not yet located, so authenticity is unconfirmed.","checkedAtUtc":"2026-10-10T12:00:00Z"},"noInappropriateFees":{"urls":["https://www.unjobnet.org/jobs/detail/path-supply-chain-specialist-evolving-cold-chain-equipment-project-89199677"],"rationale":"The summary text retrieved mentions no fee, but the provider page was not reviewed, so this is unconfirmed.","checkedAtUtc":"2026-10-10T12:00:00Z"},"noSensitiveDataAsk":{"urls":["https://www.unjobnet.org/jobs/detail/path-supply-chain-specialist-evolving-cold-chain-equipment-project-89199677"],"rationale":"The retrieved summary asks for no passwords, codes or payments, but full application instructions were not reviewed.","checkedAtUtc":"2026-10-10T12:00:00Z"},"deadlinePlausible":{"urls":["https://www.unjobnet.org/jobs/detail/path-supply-chain-specialist-evolving-cold-chain-equipment-project-89199677"],"rationale":"No closing date seen on the source. Not cross-checked against the provider page.","checkedAtUtc":"2026-10-10T12:00:00Z"},"duplicateChecked":{"urls":[],"rationale":"Title compared with all 115 catalog records and every row in this file using the app's bigram rule (threshold 0.85, 3-day window). Closest catalog title: 'Procurement Officer, P-4 - UN Office of Supply Chain Management' at 0.426.","checkedAtUtc":"2026-10-10T12:00:00Z"}} | AO43: ["Locate the provider-owned listing and the official application link","Confirm no application, processing or placement fee on the official page","Confirm no inappropriate sensitive-data request on the official page","Confirm closing date and timezone on the official page","Closing date not captured, open the listing and confirm the role is still open"] | AP43: Listing showed 'posted 2 weeks ago' on 2026-10-10. | AQ43: =FALSE() | AR43: uganda | AS43: unjobnet.org | AT43: lead_no_deadline | AU43: unresolved | AV43: 2026-10-12T09:15:53Z
A44: chai-senior-associate-srmnh-uganda | C44: create | D44: Senior Associate, Sexual, Reproductive, Maternal and Newborn Health | E44: Clinton Health Access Initiative (CHAI) | H44: job | I44: individual | J44: Senior associate role in sexual, reproductive, maternal and newborn health within CHAI Uganda country programs. | N44: Uganda (town not confirmed) | R44: unknown | Y44: fixed | Z44: Apply as described on the source listing; the official application route is not yet confirmed. | AB44: https://www.unjobnet.org/jobs/detail/chai-senior-associate-sexual-reproductive-maternal-and-newborn-health-88814714 | AC44: [] | AE44: 2026-10-10T12:00:00Z | AF44: scraped | AG44: pending | AH44: =FALSE() | AI44: =FALSE() | AJ44: =FALSE() | AK44: =FALSE() | AL44: =TRUE() | AM44: {"sourceAuthentic":{"urls":["https://www.unjobnet.org/jobs/detail/chai-senior-associate-sexual-reproductive-maternal-and-newborn-health-88814714"],"rationale":"Seen on UNjobnet, a third-party or index page. Provider-owned listing not yet located, so authenticity is unconfirmed.","checkedAtUtc":"2026-10-10T12:00:00Z"},"noInappropriateFees":{"urls":["https://www.unjobnet.org/jobs/detail/chai-senior-associate-sexual-reproductive-maternal-and-newborn-health-88814714"],"rationale":"The summary text retrieved mentions no fee, but the provider page was not reviewed, so this is unconfirmed.","checkedAtUtc":"2026-10-10T12:00:00Z"},"noSensitiveDataAsk":{"urls":["https://www.unjobnet.org/jobs/detail/chai-senior-associate-sexual-reproductive-maternal-and-newborn-health-88814714"],"rationale":"The retrieved summary asks for no passwords, codes or payments, but full application instructions were not reviewed.","checkedAtUtc":"2026-10-10T12:00:00Z"},"deadlinePlausible":{"urls":["https://www.unjobnet.org/jobs/detail/chai-senior-associate-sexual-reproductive-maternal-and-newborn-health-88814714"],"rationale":"No closing date seen on the source. Not cross-checked against the provider page.","checkedAtUtc":"2026-10-10T12:00:00Z"},"duplicateChecked":{"urls":[],"rationale":"Title compared with all 115 catalog records and every row in this file using the app's bigram rule (threshold 0.85, 3-day window). Closest catalog title: 'Grants Finance Senior Associate/Manager' at 0.506.","checkedAtUtc":"2026-10-10T12:00:00Z"}} | AO44: ["Locate the provider-owned listing and the official application link","Confirm no application, processing or placement fee on the official page","Confirm no inappropriate sensitive-data request on the official page","Confirm closing date and timezone on the official page","Closing date not captured, open the listing and confirm the role is still open"] | AP44: Listing showed 'posted 4 weeks ago'; may have closed. Duplicate signals: within_run similarity 0.961 with 'Associate, Sexual, Reproductive, Maternal and Newborn Health [chai-associate-srmnh-uganda]'. | AQ44: =FALSE() | AR44: uganda | AS44: unjobnet.org | AT44: lead_no_deadline | AU44: unresolved | AV44: 2026-10-12T09:15:53Z
A45: chai-program-manager-srmnh-uganda | C45: create | D45: Program Manager, Sexual, Reproductive, Maternal and Newborn Health | E45: Clinton Health Access Initiative (CHAI) | H45: job | I45: individual | J45: Program manager role in sexual, reproductive, maternal and newborn health within CHAI Uganda country programs. | N45: Uganda (town not confirmed) | R45: unknown | Y45: fixed | Z45: Apply as described on the source listing; the official application route is not yet confirmed. | AB45: https://www.unjobnet.org/jobs/detail/chai-program-manager-sexual-reproductive-maternal-and-newborn-health-88814713 | AC45: [] | AE45: 2026-10-10T12:00:00Z | AF45: scraped | AG45: pending | AH45: =FALSE() | AI45: =FALSE() | AJ45: =FALSE() | AK45: =FALSE() | AL45: =TRUE() | AM45: {"sourceAuthentic":{"urls":["https://www.unjobnet.org/jobs/detail/chai-program-manager-sexual-reproductive-maternal-and-newborn-health-88814713"],"rationale":"Seen on UNjobnet, a third-party or index page. Provider-owned listing not yet located, so authenticity is unconfirmed.","checkedAtUtc":"2026-10-10T12:00:00Z"},"noInappropriateFees":{"urls":["https://www.unjobnet.org/jobs/detail/chai-program-manager-sexual-reproductive-maternal-and-newborn-health-88814713"],"rationale":"The summary text retrieved mentions no fee, but the provider page was not reviewed, so this is unconfirmed.","checkedAtUtc":"2026-10-10T12:00:00Z"},"noSensitiveDataAsk":{"urls":["https://www.unjobnet.org/jobs/detail/chai-program-manager-sexual-reproductive-maternal-and-newborn-health-88814713"],"rationale":"The retrieved summary asks for no passwords, codes or payments, but full application instructions were not reviewed.","checkedAtUtc":"2026-10-10T12:00:00Z"},"deadlinePlausible":{"urls":["https://www.unjobnet.org/jobs/detail/chai-program-manager-sexual-reproductive-maternal-and-newborn-health-88814713"],"rationale":"No closing date seen on the source. Not cross-checked against the provider page.","checkedAtUtc":"2026-10-10T12:00:00Z"},"duplicateChecked":{"urls":[],"rationale":"Title compared with all 115 catalog records and every row in this file using the app's bigram rule (threshold 0.85, 3-day window). Closest catalog title: 'Senior Portfolio Manager, Inclusive Health' at 0.432.","checkedAtUtc":"2026-10-10T12:00:00Z"}} | AO45: ["Locate the provider-owned listing and the official application link","Confirm no application, processing or placement fee on the official page","Confirm no inappropriate sensitive-data request on the official page","Confirm closing date and timezone on the official page","Closing date not captured, open the listing and confirm the role is still open"] | AP45: Listing showed 'posted 4 weeks ago'; may have closed. Duplicate signals: within_run similarity 0.86 with 'Associate, Sexual, Reproductive, Maternal and Newborn Health [chai-associate-srmnh-uganda]'. | AQ45: =FALSE() | AR45: uganda | AS45: unjobnet.org | AT45: lead_no_deadline | AU45: unresolved | AV45: 2026-10-12T09:15:53Z
A46: chai-associate-srmnh-uganda | C46: create | D46: Associate, Sexual, Reproductive, Maternal and Newborn Health | E46: Clinton Health Access Initiative (CHAI) | H46: job | I46: individual | J46: Associate role in sexual, reproductive, maternal and newborn health within CHAI Uganda country programs. | N46: Uganda (town not confirmed) | R46: unknown | Y46: fixed | Z46: Apply as described on the source listing; the official application route is not yet confirmed. | AB46: https://www.unjobnet.org/jobs/detail/chai-associate-sexual-reproductive-maternal-and-newborn-health-88814712 | AC46: [] | AE46: 2026-10-10T12:00:00Z | AF46: scraped | AG46: pending | AH46: =FALSE() | AI46: =FALSE() | AJ46: =FALSE() | AK46: =FALSE() | AL46: =TRUE() | AM46: {"sourceAuthentic":{"urls":["https://www.unjobnet.org/jobs/detail/chai-associate-sexual-reproductive-maternal-and-newborn-health-88814712"],"rationale":"Seen on UNjobnet, a third-party or index page. Provider-owned listing not yet located, so authenticity is unconfirmed.","checkedAtUtc":"2026-10-10T12:00:00Z"},"noInappropriateFees":{"urls":["https://www.unjobnet.org/jobs/detail/chai-associate-sexual-reproductive-maternal-and-newborn-health-88814712"],"rationale":"The summary text retrieved mentions no fee, but the provider page was not reviewed, so this is unconfirmed.","checkedAtUtc":"2026-10-10T12:00:00Z"},"noSensitiveDataAsk":{"urls":["https://www.unjobnet.org/jobs/detail/chai-associate-sexual-reproductive-maternal-and-newborn-health-88814712"],"rationale":"The retrieved summary asks for no passwords, codes or payments, but full application instructions were not reviewed.","checkedAtUtc":"2026-10-10T12:00:00Z"},"deadlinePlausible":{"urls":["https://www.unjobnet.org/jobs/detail/chai-associate-sexual-reproductive-maternal-and-newborn-health-88814712"],"rationale":"No closing date seen on the source. Not cross-checked against the provider page.","checkedAtUtc":"2026-10-10T12:00:00Z"},"duplicateChecked":{"urls":[],"rationale":"Title compared with all 115 catalog records and every row in this file using the app's bigram rule (threshold 0.85, 3-day window). Closest catalog title: 'Grants Finance Senior Associate/Manager' at 0.434.","checkedAtUtc":"2026-10-10T12:00:00Z"}} | AO46: ["Locate the provider-owned listing and the official application link","Confirm no application, processing or placement fee on the official page","Confirm no inappropriate sensitive-data request on the official page","Confirm closing date and timezone on the official page","Closing date not captured, open the listing and confirm the role is still open"] | AP46: Listing showed 'posted 4 weeks ago'; may have closed. Entry-to-mid level compared with the other two CHAI rows. | AQ46: =FALSE() | AR46: uganda | AS46: unjobnet.org | AT46: lead_no_deadline | AU46: unresolved | AV46: 2026-10-12T09:15:53Z
A47: acf-uganda-fsl-extension-worker | C47: create | D47: Food Security and Livelihoods (FSL) Extension Worker | E47: Action contre la Faim (ACF) Uganda | H47: job | I47: individual | J47: ACF Uganda programme role listed on UNjobnet as part of a batch of Uganda postings (agriculture, nutrition and food security programming). | N47: Uganda (town not confirmed) | R47: unknown | Y47: fixed | Z47: Apply as described on the source listing; the official application route is not yet confirmed. | AB47: https://www.unjobnet.org/jobs/detail/action-contre-la-faim-programs-food-security-livelihoods-fsl-extension-worker-ug-88807673 | AC47: [] | AE47: 2026-10-10T12:00:00Z | AF47: scraped | AG47: pending | AH47: =FALSE() | AI47: =FALSE() | AJ47: =FALSE() | AK47: =FALSE() | AL47: =TRUE() | AM47: {"sourceAuthentic":{"urls":["https://www.unjobnet.org/jobs/detail/action-contre-la-faim-programs-food-security-livelihoods-fsl-extension-worker-ug-88807673"],"rationale":"Seen on UNjobnet, a third-party or index page. Provider-owned listing not yet located, so authenticity is unconfirmed.","checkedAtUtc":"2026-10-10T12:00:00Z"},"noInappropriateFees":{"urls":["https://www.unjobnet.org/jobs/detail/action-contre-la-faim-programs-food-security-livelihoods-fsl-extension-worker-ug-88807673"],"rationale":"The summary text retrieved mentions no fee, but the provider page was not reviewed, so this is unconfirmed.","checkedAtUtc":"2026-10-10T12:00:00Z"},"noSensitiveDataAsk":{"urls":["https://www.unjobnet.org/jobs/detail/action-contre-la-faim-programs-food-security-livelihoods-fsl-extension-worker-ug-88807673"],"rationale":"The retrieved summary asks for no passwords, codes or payments, but full application instructions were not reviewed.","checkedAtUtc":"2026-10-10T12:00:00Z"},"deadlinePlausible":{"urls":["https://www.unjobnet.org/jobs/detail/action-contre-la-faim-programs-food-security-livelihoods-fsl-extension-worker-ug-88807673"],"rationale":"No closing date seen on the source. Not cross-checked against the provider page.","checkedAtUtc":"2026-10-10T12:00:00Z"},"duplicateChecked":{"urls":[],"rationale":"Title compared with all 115 catalog records and every row in this file using the app's bigram rule (threshold 0.85, 3-day window). Closest catalog title: 'Whitley Award for Wildlife and Biodiversity Conservation' at 0.452.","checkedAtUtc":"2026-10-10T12:00:00Z"}} | AO47: ["Locate the provider-owned listing and the official application link","Confirm no application, processing or placement fee on the official page","Confirm no inappropriate sensitive-data request on the official page","Confirm closing date and timezone on the official page","Closing date not captured, open the listing and confirm the role is still open"] | AP47: Batch of ACF Uganda roles all 'posted 4 weeks ago' on 2026-10-10; the ACF careers site is the authority for status. | AQ47: =FALSE() | AR47: uganda | AS47: unjobnet.org | AT47: lead_no_deadline | AU47: unresolved | AV47: 2026-10-12T09:15:53Z
A48: acf-uganda-project-manager-team-leader | C48: create | D48: Project Manager or Team Leader | E48: Action contre la Faim (ACF) Uganda | H48: job | I48: individual | J48: ACF Uganda programme role listed on UNjobnet as part of a batch of Uganda postings (agriculture, nutrition and food security programming). | N48: Uganda (town not confirmed) | R48: unknown | Y48: fixed | Z48: Apply as described on the source listing; the official application route is not yet confirmed. | AB48: https://www.unjobnet.org/jobs/detail/action-contre-la-faim-uga-project-managerteam-leader-88807665 | AC48: [] | AE48: 2026-10-10T12:00:00Z | AF48: scraped | AG48: pending | AH48: =FALSE() | AI48: =FALSE() | AJ48: =FALSE() | AK48: =FALSE() | AL48: =TRUE() | AM48: {"sourceAuthentic":{"urls":["https://www.unjobnet.org/jobs/detail/action-contre-la-faim-uga-project-managerteam-leader-88807665"],"rationale":"Seen on UNjobnet, a third-party or index page. Provider-owned listing not yet located, so authenticity is unconfirmed.","checkedAtUtc":"2026-10-10T12:00:00Z"},"noInappropriateFees":{"urls":["https://www.unjobnet.org/jobs/detail/action-contre-la-faim-uga-project-managerteam-leader-88807665"],"rationale":"The summary text retrieved mentions no fee, but the provider page was not reviewed, so this is unconfirmed.","checkedAtUtc":"2026-10-10T12:00:00Z"},"noSensitiveDataAsk":{"urls":["https://www.unjobnet.org/jobs/detail/action-contre-la-faim-uga-project-managerteam-leader-88807665"],"rationale":"The retrieved summary asks for no passwords, codes or payments, but full application instructions were not reviewed.","checkedAtUtc":"2026-10-10T12:00:00Z"},"deadlinePlausible":{"urls":["https://www.unjobnet.org/jobs/detail/action-contre-la-faim-uga-project-managerteam-leader-88807665"],"rationale":"No closing date seen on the source. Not cross-checked against the provider page.","checkedAtUtc":"2026-10-10T12:00:00Z"},"duplicateChecked":{"urls":[],"rationale":"Title compared with all 115 catalog records and every row in this file using the app's bigram rule (threshold 0.85, 3-day window). Closest catalog title: 'Project Director, PlayMatters' at 0.471.","checkedAtUtc":"2026-10-10T12:00:00Z"}} | AO48: ["Locate the provider-owned listing and the official application link","Confirm no application, processing or placement fee on the official page","Confirm no inappropriate sensitive-data request on the official page","Confirm closing date and timezone on the official page","Closing date not captured, open the listing and confirm the role is still open"] | AP48: Batch of ACF Uganda roles all 'posted 4 weeks ago' on 2026-10-10; the ACF careers site is the authority for status. | AQ48: =FALSE() | AR48: uganda | AS48: unjobnet.org | AT48: lead_no_deadline | AU48: unresolved | AV48: 2026-10-12T09:15:53Z
A49: acf-uganda-entomologist | C49: create | D49: Entomologist | E49: Action contre la Faim (ACF) Uganda | H49: job | I49: individual | J49: ACF Uganda programme role listed on UNjobnet as part of a batch of Uganda postings (agriculture, nutrition and food security programming). | N49: Uganda (town not confirmed) | R49: unknown | Y49: fixed | Z49: Apply as described on the source listing; the official application route is not yet confirmed. | AB49: https://www.unjobnet.org/jobs/detail/action-contre-la-faim-uga-entomologist-88807664 | AC49: [] | AE49: 2026-10-10T12:00:00Z | AF49: scraped | AG49: pending | AH49: =FALSE() | AI49: =FALSE() | AJ49: =FALSE() | AK49: =FALSE() | AL49: =TRUE() | AM49: {"sourceAuthentic":{"urls":["https://www.unjobnet.org/jobs/detail/action-contre-la-faim-uga-entomologist-88807664"],"rationale":"Seen on UNjobnet, a third-party or index page. Provider-owned listing not yet located, so authenticity is unconfirmed.","checkedAtUtc":"2026-10-10T12:00:00Z"},"noInappropriateFees":{"urls":["https://www.unjobnet.org/jobs/detail/action-contre-la-faim-uga-entomologist-88807664"],"rationale":"The summary text retrieved mentions no fee, but the provider page was not reviewed, so this is unconfirmed.","checkedAtUtc":"2026-10-10T12:00:00Z"},"noSensitiveDataAsk":{"urls":["https://www.unjobnet.org/jobs/detail/action-contre-la-faim-uga-entomologist-88807664"],"rationale":"The retrieved summary asks for no passwords, codes or payments, but full application instructions were not reviewed.","checkedAtUtc":"2026-10-10T12:00:00Z"},"deadlinePlausible":{"urls":["https://www.unjobnet.org/jobs/detail/action-contre-la-faim-uga-entomologist-88807664"],"rationale":"No closing date seen on the source. Not cross-checked against the provider page.","checkedAtUtc":"2026-10-10T12:00:00Z"},"duplicateChecked":{"urls":[],"rationale":"Title compared with all 115 catalog records and every row in this file using the app's bigram rule (threshold 0.85, 3-day window). Closest catalog title: 'Chemistry and Biology Teacher' at 0.278.","checkedAtUtc":"2026-10-10T12:00:00Z"}} | AO49: ["Locate the provider-owned listing and the official application link","Confirm no application, processing or placement fee on the official page","Confirm no inappropriate sensitive-data request on the official page","Confirm closing date and timezone on the official page","Closing date not captured, open the listing and confirm the role is still open"] | AP49: Batch of ACF Uganda roles all 'posted 4 weeks ago' on 2026-10-10; the ACF careers site is the authority for status. | AQ49: =FALSE() | AR49: uganda | AS49: unjobnet.org | AT49: lead_no_deadline | AU49: unresolved | AV49: 2026-10-12T09:15:53Z
A50: acf-uganda-sustainable-land-management-officer | C50: create | D50: Sustainable Land Management Officer | E50: Action contre la Faim (ACF) Uganda | H50: job | I50: individual | J50: ACF Uganda programme role listed on UNjobnet as part of a batch of Uganda postings (agriculture, nutrition and food security programming). | N50: Uganda (town not confirmed) | R50: unknown | Y50: fixed | Z50: Apply as described on the source listing; the official application route is not yet confirmed. | AB50: https://www.unjobnet.org/jobs/detail/action-contre-la-faim-uga-sustainable-land-management-officer-88807663 | AC50: [] | AE50: 2026-10-10T12:00:00Z | AF50: scraped | AG50: pending | AH50: =FALSE() | AI50: =FALSE() | AJ50: =FALSE() | AK50: =FALSE() | AL50: =TRUE() | AM50: {"sourceAuthentic":{"urls":["https://www.unjobnet.org/jobs/detail/action-contre-la-faim-uga-sustainable-land-management-officer-88807663"],"rationale":"Seen on UNjobnet, a third-party or index page. Provider-owned listing not yet located, so authenticity is unconfirmed.","checkedAtUtc":"2026-10-10T12:00:00Z"},"noInappropriateFees":{"urls":["https://www.unjobnet.org/jobs/detail/action-contre-la-faim-uga-sustainable-land-management-officer-88807663"],"rationale":"The summary text retrieved mentions no fee, but the provider page was not reviewed, so this is unconfirmed.","checkedAtUtc":"2026-10-10T12:00:00Z"},"noSensitiveDataAsk":{"urls":["https://www.unjobnet.org/jobs/detail/action-contre-la-faim-uga-sustainable-land-management-officer-88807663"],"rationale":"The retrieved summary asks for no passwords, codes or payments, but full application instructions were not reviewed.","checkedAtUtc":"2026-10-10T12:00:00Z"},"deadlinePlausible":{"urls":["https://www.unjobnet.org/jobs/detail/action-contre-la-faim-uga-sustainable-land-management-officer-88807663"],"rationale":"No closing date seen on the source. Not cross-checked against the provider page.","checkedAtUtc":"2026-10-10T12:00:00Z"},"duplicateChecked":{"urls":[],"rationale":"Title compared with all 115 catalog records and every row in this file using the app's bigram rule (threshold 0.85, 3-day window). Closest catalog title: 'Procurement Officer, P-4 - UN Office of Supply Chain Management' at 0.564.","checkedAtUtc":"2026-10-10T12:00:00Z"}} | AO50: ["Locate the provider-owned listing and the official application link","Confirm no application, processing or placement fee on the official page","Confirm no inappropriate sensitive-data request on the official page","Confirm closing date and timezone on the official page","Closing date not captured, open the listing and confirm the role is still open"] | AP50: Batch of ACF Uganda roles all 'posted 4 weeks ago' on 2026-10-10; the ACF careers site is the authority for status. | AQ50: =FALSE() | AR50: uganda | AS50: unjobnet.org | AT50: lead_no_deadline | AU50: unresolved | AV50: 2026-10-12T09:15:53Z
A51: acf-uganda-agribusiness-market-systems-officer | C51: create | D51: Agribusiness and Market Systems Officer | E51: Action contre la Faim (ACF) Uganda | H51: job | I51: individual | J51: ACF Uganda programme role listed on UNjobnet as part of a batch of Uganda postings (agriculture, nutrition and food security programming). | N51: Uganda (town not confirmed) | R51: unknown | Y51: fixed | Z51: Apply as described on the source listing; the official application route is not yet confirmed. | AB51: https://www.unjobnet.org/jobs/detail/action-contre-la-faim-uga-agribusinessmarket-systems-officer-88807662 | AC51: [] | AE51: 2026-10-10T12:00:00Z | AF51: scraped | AG51: pending | AH51: =FALSE() | AI51: =FALSE() | AJ51: =FALSE() | AK51: =FALSE() | AL51: =TRUE() | AM51: {"sourceAuthentic":{"urls":["https://www.unjobnet.org/jobs/detail/action-contre-la-faim-uga-agribusinessmarket-systems-officer-88807662"],"rationale":"Seen on UNjobnet, a third-party or index page. Provider-owned listing not yet located, so authenticity is unconfirmed.","checkedAtUtc":"2026-10-10T12:00:00Z"},"noInappropriateFees":{"urls":["https://www.unjobnet.org/jobs/detail/action-contre-la-faim-uga-agribusinessmarket-systems-officer-88807662"],"rationale":"The summary text retrieved mentions no fee, but the provider page was not reviewed, so this is unconfirmed.","checkedAtUtc":"2026-10-10T12:00:00Z"},"noSensitiveDataAsk":{"urls":["https://www.unjobnet.org/jobs/detail/action-contre-la-faim-uga-agribusinessmarket-systems-officer-88807662"],"rationale":"The retrieved summary asks for no passwords, codes or payments, but full application instructions were not reviewed.","checkedAtUtc":"2026-10-10T12:00:00Z"},"deadlinePlausible":{"urls":["https://www.unjobnet.org/jobs/detail/action-contre-la-faim-uga-agribusinessmarket-systems-officer-88807662"],"rationale":"No closing date seen on the source. Not cross-checked against the provider page.","checkedAtUtc":"2026-10-10T12:00:00Z"},"duplicateChecked":{"urls":[],"rationale":"Title compared with all 115 catalog records and every row in this file using the app's bigram rule (threshold 0.85, 3-day window). Closest catalog title: 'Physics and Mathematics Teacher' at 0.426.","checkedAtUtc":"2026-10-10T12:00:00Z"}} | AO51: ["Locate the provider-owned listing and the official application link","Confirm no application, processing or placement fee on the official page","Confirm no inappropriate sensitive-data request on the official page","Confirm closing date and timezone on the official page","Closing date not captured, open the listing and confirm the role is still open"] | AP51: Batch of ACF Uganda roles all 'posted 4 weeks ago' on 2026-10-10; the ACF careers site is the authority for status. | AQ51: =FALSE() | AR51: uganda | AS51: unjobnet.org | AT51: lead_no_deadline | AU51: unresolved | AV51: 2026-10-12T09:15:53Z
A52: acf-uganda-livestock-officer | C52: create | D52: Livestock Officer | E52: Action contre la Faim (ACF) Uganda | H52: job | I52: individual | J52: ACF Uganda programme role listed on UNjobnet as part of a batch of Uganda postings (agriculture, nutrition and food security programming). | N52: Uganda (town not confirmed) | R52: unknown | Y52: fixed | Z52: Apply as described on the source listing; the official application route is not yet confirmed. | AB52: https://www.unjobnet.org/jobs/detail/action-contre-la-faim-uga-livestock-officer-88807661 | AC52: [] | AE52: 2026-10-10T12:00:00Z | AF52: scraped | AG52: pending | AH52: =FALSE() | AI52: =FALSE() | AJ52: =FALSE() | AK52: =FALSE() | AL52: =TRUE() | AM52: {"sourceAuthentic":{"urls":["https://www.unjobnet.org/jobs/detail/action-contre-la-faim-uga-livestock-officer-88807661"],"rationale":"Seen on UNjobnet, a third-party or index page. Provider-owned listing not yet located, so authenticity is unconfirmed.","checkedAtUtc":"2026-10-10T12:00:00Z"},"noInappropriateFees":{"urls":["https://www.unjobnet.org/jobs/detail/action-contre-la-faim-uga-livestock-officer-88807661"],"rationale":"The summary text retrieved mentions no fee, but the provider page was not reviewed, so this is unconfirmed.","checkedAtUtc":"2026-10-10T12:00:00Z"},"noSensitiveDataAsk":{"urls":["https://www.unjobnet.org/jobs/detail/action-contre-la-faim-uga-livestock-officer-88807661"],"rationale":"The retrieved summary asks for no passwords, codes or payments, but full application instructions were not reviewed.","checkedAtUtc":"2026-10-10T12:00:00Z"},"deadlinePlausible":{"urls":["https://www.unjobnet.org/jobs/detail/action-contre-la-faim-uga-livestock-officer-88807661"],"rationale":"No closing date seen on the source. Not cross-checked against the provider page.","checkedAtUtc":"2026-10-10T12:00:00Z"},"duplicateChecked":{"urls":[],"rationale":"Title compared with all 115 catalog records and every row in this file using the app's bigram rule (threshold 0.85, 3-day window). Closest catalog title: 'MEAL Officer' at 0.519.","checkedAtUtc":"2026-10-10T12:00:00Z"}} | AO52: ["Locate the provider-owned listing and the official application link","Confirm no application, processing or placement fee on the official page","Confirm no inappropriate sensitive-data request on the official page","Confirm closing date and timezone on the official page","Closing date not captured, open the listing and confirm the role is still open"] | AP52: Batch of ACF Uganda roles all 'posted 4 weeks ago' on 2026-10-10; the ACF careers site is the authority for status. | AQ52: =FALSE() | AR52: uganda | AS52: unjobnet.org | AT52: lead_no_deadline | AU52: unresolved | AV52: 2026-10-12T09:15:53Z
A53: acf-uganda-accountant | C53: create | D53: Accountant | E53: Action contre la Faim (ACF) Uganda | H53: job | I53: individual | J53: ACF Uganda programme role listed on UNjobnet as part of a batch of Uganda postings (agriculture, nutrition and food security programming). | N53: Uganda (town not confirmed) | R53: unknown | Y53: fixed | Z53: Apply as described on the source listing; the official application route is not yet confirmed. | AB53: https://www.unjobnet.org/jobs/detail/action-contre-la-faim-uga-accountant-88807659 | AC53: [] | AE53: 2026-10-10T12:00:00Z | AF53: scraped | AG53: pending | AH53: =FALSE() | AI53: =FALSE() | AJ53: =FALSE() | AK53: =FALSE() | AL53: =TRUE() | AM53: {"sourceAuthentic":{"urls":["https://www.unjobnet.org/jobs/detail/action-contre-la-faim-uga-accountant-88807659"],"rationale":"Seen on UNjobnet, a third-party or index page. Provider-owned listing not yet located, so authenticity is unconfirmed.","checkedAtUtc":"2026-10-10T12:00:00Z"},"noInappropriateFees":{"urls":["https://www.unjobnet.org/jobs/detail/action-contre-la-faim-uga-accountant-88807659"],"rationale":"The summary text retrieved mentions no fee, but the provider page was not reviewed, so this is unconfirmed.","checkedAtUtc":"2026-10-10T12:00:00Z"},"noSensitiveDataAsk":{"urls":["https://www.unjobnet.org/jobs/detail/action-contre-la-faim-uga-accountant-88807659"],"rationale":"The retrieved summary asks for no passwords, codes or payments, but full application instructions were not reviewed.","checkedAtUtc":"2026-10-10T12:00:00Z"},"deadlinePlausible":{"urls":["https://www.unjobnet.org/jobs/detail/action-contre-la-faim-uga-accountant-88807659"],"rationale":"No closing date seen on the source. Not cross-checked against the provider page.","checkedAtUtc":"2026-10-10T12:00:00Z"},"duplicateChecked":{"urls":[],"rationale":"Title compared with all 115 catalog records and every row in this file using the app's bigram rule (threshold 0.85, 3-day window). Closest catalog title: 'UN Coordination and Normative Consultant' at 0.256.","checkedAtUtc":"2026-10-10T12:00:00Z"}} | AO53: ["Locate the provider-owned listing and the official application link","Confirm no application, processing or placement fee on the official page","Confirm no inappropriate sensitive-data request on the official page","Confirm closing date and timezone on the official page","Closing date not captured, open the listing and confirm the role is still open"] | AP53: Batch of ACF Uganda roles all 'posted 4 weeks ago' on 2026-10-10; the ACF careers site is the authority for status. | AQ53: =FALSE() | AR53: uganda | AS53: unjobnet.org | AT53: lead_no_deadline | AU53: unresolved | AV53: 2026-10-12T09:15:53Z
A54: acf-uganda-merl-digital-data-quality-officer | C54: create | D54: MERL and Digital Data Quality Officer | E54: Action contre la Faim (ACF) Uganda | H54: job | I54: individual | J54: ACF Uganda programme role listed on UNjobnet as part of a batch of Uganda postings (agriculture, nutrition and food security programming). | N54: Uganda (town not confirmed) | R54: unknown | Y54: fixed | Z54: Apply as described on the source listing; the official application route is not yet confirmed. | AB54: https://www.unjobnet.org/jobs/detail/action-contre-la-faim-uga-merl-digital-data-quality-officer-88807658 | AC54: [] | AE54: 2026-10-10T12:00:00Z | AF54: scraped | AG54: pending | AH54: =FALSE() | AI54: =FALSE() | AJ54: =FALSE() | AK54: =FALSE() | AL54: =TRUE() | AM54: {"sourceAuthentic":{"urls":["https://www.unjobnet.org/jobs/detail/action-contre-la-faim-uga-merl-digital-data-quality-officer-88807658"],"rationale":"Seen on UNjobnet, a third-party or index page. Provider-owned listing not yet located, so authenticity is unconfirmed.","checkedAtUtc":"2026-10-10T12:00:00Z"},"noInappropriateFees":{"urls":["https://www.unjobnet.org/jobs/detail/action-contre-la-faim-uga-merl-digital-data-quality-officer-88807658"],"rationale":"The summary text retrieved mentions no fee, but the provider page was not reviewed, so this is unconfirmed.","checkedAtUtc":"2026-10-10T12:00:00Z"},"noSensitiveDataAsk":{"urls":["https://www.unjobnet.org/jobs/detail/action-contre-la-faim-uga-merl-digital-data-quality-officer-88807658"],"rationale":"The retrieved summary asks for no passwords, codes or payments, but full application instructions were not reviewed.","checkedAtUtc":"2026-10-10T12:00:00Z"},"deadlinePlausible":{"urls":["https://www.unjobnet.org/jobs/detail/action-contre-la-faim-uga-merl-digital-data-quality-officer-88807658"],"rationale":"No closing date seen on the source. Not cross-checked against the provider page.","checkedAtUtc":"2026-10-10T12:00:00Z"},"duplicateChecked":{"urls":[],"rationale":"Title compared with all 115 catalog records and every row in this file using the app's bigram rule (threshold 0.85, 3-day window). Closest catalog title: 'MEAL Officer' at 0.488.","checkedAtUtc":"2026-10-10T12:00:00Z"}} | AO54: ["Locate the provider-owned listing and the official application link","Confirm no application, processing or placement fee on the official page","Confirm no inappropriate sensitive-data request on the official page","Confirm closing date and timezone on the official page","Closing date not captured, open the listing and confirm the role is still open"] | AP54: Batch of ACF Uganda roles all 'posted 4 weeks ago' on 2026-10-10; the ACF careers site is the authority for status. | AQ54: =FALSE() | AR54: uganda | AS54: unjobnet.org | AT54: lead_no_deadline | AU54: unresolved | AV54: 2026-10-12T09:15:53Z
... A56: acf-uganda-nutrition-expert-officer | C56: create | D56: Nutrition Expert or Officer | E56: Action contre la Faim (ACF) Uganda | H56: job | I56: individual | J56: ACF Uganda nutrition role. UNjobnet shows two near-identical nutrition postings (88807660 and 88807657). | N56: Uganda (town not confirmed) | R56: unknown | Y56: fixed | Z56: Apply as described on the source listing; the official application route is not yet confirmed. | AB56: https://www.unjobnet.org/jobs/detail/action-contre-la-faim-uga-nutrition-expertofficer-88807660 | AC56: ["https://www.unjobnet.org/jobs/detail/action-contre-la-faim-uga-nutrition-expert-officer-88807657"] | AE56: 2026-10-10T12:00:00Z | AF56: scraped | AG56: pending | AH56: =FALSE() | AI56: =FALSE() | AJ56: =FALSE() | AK56: =FALSE() | AL56: =TRUE() | AM56: {"sourceAuthentic":{"urls":["https://www.unjobnet.org/jobs/detail/action-contre-la-faim-uga-nutrition-expertofficer-88807660","https://www.unjobnet.org/jobs/detail/action-contre-la-faim-uga-nutrition-expert-officer-88807657"],"rationale":"Seen on UNjobnet, a third-party or index page. Provider-owned listing not yet located, so authenticity is unconfirmed.","checkedAtUtc":"2026-10-10T12:00:00Z"},"noInappropriateFees":{"urls":["https://www.unjobnet.org/jobs/detail/action-contre-la-faim-uga-nutrition-expertofficer-88807660"],"rationale":"The summary text retrieved mentions no fee, but the provider page was not reviewed, so this is unconfirmed.","checkedAtUtc":"2026-10-10T12:00:00Z"},"noSensitiveDataAsk":{"urls":["https://www.unjobnet.org/jobs/detail/action-contre-la-faim-uga-nutrition-expertofficer-88807660"],"rationale":"The retrieved summary asks for no passwords, codes or payments, but full application instructions were not reviewed.","checkedAtUtc":"2026-10-10T12:00:00Z"},"deadlinePlausible":{"urls":["https://www.unjobnet.org/jobs/detail/action-contre-la-faim-uga-nutrition-expertofficer-88807660"],"rationale":"No closing date seen on the source. Not cross-checked against the provider page.","checkedAtUtc":"2026-10-10T12:00:00Z"},"duplicateChecked":{"urls":[],"rationale":"Title compared with all 115 catalog records and every row in this file using the app's bigram rule (threshold 0.85, 3-day window). Closest catalog title: 'Chief Operations Officer' at 0.489.","checkedAtUtc":"2026-10-10T12:00:00Z"}} | AO56: ["Locate the provider-owned listing and the official application link","Confirm no application, processing or placement fee on the official page","Confirm no inappropriate sensitive-data request on the official page","Confirm closing date and timezone on the official page","Closing date not captured, open the listing and confirm the role is still open"] | AP56: Two near-duplicate postings; the second is the Chief and Senior Professional level. Agent should split or merge after reading both. | AQ56: =FALSE() | AR56: uganda | AS56: unjobnet.org | AT56: lead_no_deadline | AU56: unresolved | AV56: 2026-10-12T09:15:53Z
A57: totalenergies-ep-uganda-graduate-trainees | C57: create | D57: TotalEnergies EP Uganda Graduate Trainee Programme (multiple tracks) | E57: TotalEnergies EP Uganda | H57: job | I57: individual | J57: Graduate trainee openings across tracks such as field operations, biodiversity, field engineering, smart room, contracts and procurement, and geoscience and reservoir. Seen on third-party boards only. | K57: {"additionalRequirements":["Bachelor's degree in a relevant field (stated for some tracks)","Less than 2 years since graduation (stated for the contracts and procurement track)"]} | N57: Uganda (town not confirmed) | R57: unknown | Y57: fixed | Z57: Apply as described on the source listing; the official application route is not yet confirmed. | AB57: https://www.progigfinder.com/graduate-trainee-jobs-uganda | AC57: ["https://www.iagora.com/work/de/jobs/auf-englisch/uganda"] | AE57: 2026-10-10T12:00:00Z | AF57: scraped | AG57: pending | AH57: =FALSE() | AI57: =FALSE() | AJ57: =FALSE() | AK57: =FALSE() | AL57: =TRUE() | AM57: {"sourceAuthentic":{"urls":["https://www.progigfinder.com/graduate-trainee-jobs-uganda","https://www.iagora.com/work/de/jobs/auf-englisch/uganda"],"rationale":"Seen on ProGigFinder, a third-party or index page. Provider-owned listing not yet located, so authenticity is unconfirmed.","checkedAtUtc":"2026-10-10T12:00:00Z"},"noInappropriateFees":{"urls":["https://www.progigfinder.com/graduate-trainee-jobs-uganda"],"rationale":"The summary text retrieved mentions no fee, but the provider page was not reviewed, so this is unconfirmed.","checkedAtUtc":"2026-10-10T12:00:00Z"},"noSensitiveDataAsk":{"urls":["https://www.progigfinder.com/graduate-trainee-jobs-uganda"],"rationale":"The retrieved summary asks for no passwords, codes or payments, but full application instructions were not reviewed.","checkedAtUtc":"2026-10-10T12:00:00Z"},"deadlinePlausible":{"urls":["https://www.progigfinder.com/graduate-trainee-jobs-uganda"],"rationale":"No closing date seen on the source. Not cross-checked against the provider page.","checkedAtUtc":"2026-10-10T12:00:00Z"},"duplicateChecked":{"urls":[],"rationale":"Title compared with all 115 catalog records and every row in this file using the app's bigram rule (threshold 0.85, 3-day window). Closest catalog title: 'Senior Programme Officer - Trade for Jobs Uganda' at 0.468.","checkedAtUtc":"2026-10-10T12:00:00Z"}} | AO57: ["Locate the provider-owned listing and the official application link","Confirm no application, processing or placement fee on the official page","Confirm no inappropriate sensitive-data request on the official page","Confirm closing date and timezone on the official page","Closing date not captured, open the listing and confirm the role is still open"] | AP57: Split into one row per track once the official TotalEnergies careers listing is located. The ProGigFinder page was an old snapshot. | AQ57: =FALSE() | AR57: uganda | AS57: progigfinder.com | AT57: lead_no_deadline | AU57: unresolved | AV57: 2026-10-12T09:15:53Z
A58: totalenergies-marketing-uganda-young-graduate-2026 | C58: create | D58: TotalEnergies Marketing Uganda Young Graduate Program 2026 | E58: TotalEnergies Marketing Uganda Limited | H58: job | I58: individual | J58: Young Graduate Program for fresh graduates, aimed at applicants who graduated in 2025 and 2026, with mentoring and coaching. | K58: {"additionalRequirements":["Must have graduated in 2025 or 2026"]} | N58: Uganda (town not confirmed) | R58: unknown | Y58: fixed | Z58: Apply as described on the source listing; the official application route is not yet confirmed. | AB58: https://www.fuzu.com/uganda/job/nansana?page=13 | AC58: [] | AE58: 2026-10-10T12:00:00Z | AF58: scraped | AG58: pending | AH58: =FALSE() | AI58: =FALSE() | AJ58: =FALSE() | AK58: =FALSE() | AL58: =TRUE() | AM58: {"sourceAuthentic":{"urls":["https://www.fuzu.com/uganda/job/nansana?page=13"],"rationale":"Seen on Fuzu, a third-party or index page. Provider-owned listing not yet located, so authenticity is unconfirmed.","checkedAtUtc":"2026-10-10T12:00:00Z"},"noInappropriateFees":{"urls":["https://www.fuzu.com/uganda/job/nansana?page=13"],"rationale":"The summary text retrieved mentions no fee, but the provider page was not reviewed, so this is unconfirmed.","checkedAtUtc":"2026-10-10T12:00:00Z"},"noSensitiveDataAsk":{"urls":["https://www.fuzu.com/uganda/job/nansana?page=13"],"rationale":"The retrieved summary asks for no passwords, codes or payments, but full application instructions were not reviewed.","checkedAtUtc":"2026-10-10T12:00:00Z"},"deadlinePlausible":{"urls":["https://www.fuzu.com/uganda/job/nansana?page=13"],"rationale":"No closing date seen on the source. Not cross-checked against the provider page.","checkedAtUtc":"2026-10-10T12:00:00Z"},"duplicateChecked":{"urls":[],"rationale":"Title compared with all 115 catalog records and every row in this file using the app's bigram rule (threshold 0.85, 3-day window). Closest catalog title: 'World Bank Group Young Professionals Program 2027' at 0.463.","checkedAtUtc":"2026-10-10T12:00:00Z"}} | AO58: ["Locate the provider-owned listing and the official application link","Confirm no application, processing or placement fee on the official page","Confirm no inappropriate sensitive-data request on the official page","Confirm closing date and timezone on the official page","Closing date not captured, open the listing and confirm the role is still open"] | AP58: Fuzu page showed the listing, but its status may be closed. | AQ58: =FALSE() | AR58: uganda | AS58: fuzu.com | AT58: lead_no_deadline | AU58: unresolved | AV58: 2026-10-12T09:15:53Z
A59: seatini-uganda-graduate-trainee-5th-cohort | C59: create | D59: SEATINI Uganda Graduate Trainee Programme (5th cohort) | E59: Southern and Eastern Africa Trade Information and Negotiations Institute (SEATINI) Uganda | H59: job | I59: individual | J59: Fifth cohort of SEATINI Uganda's graduate trainee programme in Kampala. | N59: Kampala, Uganda | R59: unknown | S59: An older SEATINI trainee posting (Jan 2024) described unpaid positions with lunch and transport allowances; the 5th cohort terms are unconfirmed. | Y59: fixed | Z59: Apply as described on the source listing; the official application route is not yet confirmed. | AB59: https://www.fuzu.com/uganda/job/business-strategic-management/mukono?page=2 | AC59: [] | AE59: 2026-10-10T12:00:00Z | AF59: scraped | AG59: pending | AH59: =FALSE() | AI59: =FALSE() | AJ59: =FALSE() | AK59: =FALSE() | AL59: =TRUE() | AM59: {"sourceAuthentic":{"urls":["https://www.fuzu.com/uganda/job/business-strategic-management/mukono?page=2"],"rationale":"Seen on Fuzu, a third-party or index page. Provider-owned listing not yet located, so authenticity is unconfirmed.","checkedAtUtc":"2026-10-10T12:00:00Z"},"noInappropriateFees":{"urls":["https://www.fuzu.com/uganda/job/business-strategic-management/mukono?page=2"],"rationale":"The summary text retrieved mentions no fee, but the provider page was not reviewed, so this is unconfirmed.","checkedAtUtc":"2026-10-10T12:00:00Z"},"noSensitiveDataAsk":{"urls":["https://www.fuzu.com/uganda/job/business-strategic-management/mukono?page=2"],"rationale":"The retrieved summary asks for no passwords, codes or payments, but full application instructions were not reviewed.","checkedAtUtc":"2026-10-10T12:00:00Z"},"deadlinePlausible":{"urls":["https://www.fuzu.com/uganda/job/business-strategic-management/mukono?page=2"],"rationale":"No closing date seen on the source. Not cross-checked against the provider page.","checkedAtUtc":"2026-10-10T12:00:00Z"},"duplicateChecked":{"urls":[],"rationale":"Title compared with all 115 catalog records and every row in this file using the app's bigram rule (threshold 0.85, 3-day window). Closest catalog title: 'Senior Programme Officer - Trade for Jobs Uganda' at 0.518.","checkedAtUtc":"2026-10-10T12:00:00Z"}} | AO59: ["Locate the provider-owned listing and the official application link","Confirm no application, processing or placement fee on the official page","Confirm no inappropriate sensitive-data request on the official page","Confirm closing date and timezone on the official page","Compensation for this cohort","Closing date not captured, open the listing and confirm the role is still open"] | AP59: Possible unpaid placement, so confirm compensation before labelling it a job. | AQ59: =FALSE() | AR59: uganda | AS59: fuzu.com | AT59: lead_no_deadline | AU59: unresolved | AV59: 2026-10-12T09:15:53Z
A60: muljibhai-madhvani-foundation-university-scholarship | C60: create | D60: Muljibhai Madhvani Foundation University Scholarship | E60: Muljibhai Madhvani Foundation | H60: scholarship | I60: individual | J60: Scholarship for Ugandan nationals studying at Ugandan universities in listed fields, covering undergraduate year two onward and some postgraduate study. | K60: {"additionalRequirements":["Ugandan national studying at a Ugandan university in a listed field","Undergraduate year two onward","CGPA of at least 3.0","No prior-year retakes","No other sponsor","Two to three reference letters"]} | N60: Uganda | O60: ["Uganda"] | R60: funded | Y60: fixed | Z60: Apply as described on the source listing; the official application route is not yet confirmed. | AB60: https://scholarshipsforafricans.com/scholarships/muljibhai-madhvani-foundation-university-scholarship | AC60: ["https://madhvanifoundation.com/wp-content/uploads/2026/05/Application-Form-Sample.pdf"] | AE60: 2026-10-10T12:00:00Z | AF60: scraped | AG60: pending | AH60: =FALSE() | AI60: =FALSE() | AJ60: =FALSE() | AK60: =FALSE() | AL60: =TRUE() | AM60: {"sourceAuthentic":{"urls":["https://scholarshipsforafricans.com/scholarships/muljibhai-madhvani-foundation-university-scholarship","https://madhvanifoundation.com/wp-content/uploads/2026/05/Application-Form-Sample.pdf"],"rationale":"Seen on Scholarships for Africans, a third-party or index page. Provider-owned listing not yet located, so authenticity is unconfirmed.","checkedAtUtc":"2026-10-10T12:00:00Z"},"noInappropriateFees":{"urls":["https://scholarshipsforafricans.com/scholarships/muljibhai-madhvani-foundation-university-scholarship"],"rationale":"The summary text retrieved mentions no fee, but the provider page was not reviewed, so this is unconfirmed.","checkedAtUtc":"2026-10-10T12:00:00Z"},"noSensitiveDataAsk":{"urls":["https://scholarshipsforafricans.com/scholarships/muljibhai-madhvani-foundation-university-scholarship"],"rationale":"The retrieved summary asks for no passwords, codes or payments, but full application instructions were not reviewed.","checkedAtUtc":"2026-10-10T12:00:00Z"},"deadlinePlausible":{"urls":["https://scholarshipsforafricans.com/scholarships/muljibhai-madhvani-foundation-university-scholarship"],"rationale":"No closing date seen on the source. Not cross-checked against the provider page.","checkedAtUtc":"2026-10-10T12:00:00Z"},"duplicateChecked":{"urls":[],"rationale":"Title compared with all 115 catalog records and every row in this file using the app's bigram rule (threshold 0.85, 3-day window). Closest catalog title: 'ASU Mastercard Foundation Innovation and Technology Scholarship 2027/2028' at 0.544.","checkedAtUtc":"2026-10-10T12:00:00Z"}} | AO60: ["Locate the provider-owned listing and the official application link","Confirm no application, processing or placement fee on the official page","Confirm no inappropriate sensitive-data request on the official page","Confirm closing date and timezone on the official page","Next application window","Funding amount and coverage"] | AP60: Aggregator says a 2026 sample form and award list exist but the next submission window is unconfirmed. Treat as watch-list until the foundation announces a window. | AQ60: =FALSE() | AR60: uganda | AS60: scholarshipsforafricans.com | AT60: lead_no_deadline | AU60: unresolved | AV60: 2026-10-12T09:15:53Z
A61: van-doorn-foundation-east-africa-grants | C61: create | D61: Van Doorn Foundation grants for East African organisations | E61: Van Doorn Foundation | H61: grant | I61: organization | J61: Grants to local organisations in Kenya, Tanzania, Uganda and Zambia; applications are reportedly accepted each October. | N61: Kenya, Tanzania, Uganda, Zambia | O61: ["Kenya","Tanzania","Uganda","Zambia"] | R61: unknown | V61: Applications are accepted in October, annually | Z61: Apply as described on the source listing; the official application route is not yet confirmed. | AB61: https://grantstation.com/find-grants/uganda | AC61: [] | AE61: 2026-10-10T12:00:00Z | AF61: scraped | AG61: pending | AH61: =FALSE() | AI61: =FALSE() | AJ61: =FALSE() | AK61: =FALSE() | AL61: =TRUE() | AM61: {"sourceAuthentic":{"urls":["https://grantstation.com/find-grants/uganda"],"rationale":"Seen on GrantStation, a third-party or index page. Provider-owned listing not yet located, so authenticity is unconfirmed.","checkedAtUtc":"2026-10-10T12:00:00Z"},"noInappropriateFees":{"urls":["https://grantstation.com/find-grants/uganda"],"rationale":"The summary text retrieved mentions no fee, but the provider page was not reviewed, so this is unconfirmed.","checkedAtUtc":"2026-10-10T12:00:00Z"},"noSensitiveDataAsk":{"urls":["https://grantstation.com/find-grants/uganda"],"rationale":"The retrieved summary asks for no passwords, codes or payments, but full application instructions were not reviewed.","checkedAtUtc":"2026-10-10T12:00:00Z"},"deadlinePlausible":{"urls":["https://grantstation.com/find-grants/uganda"],"rationale":"Source states 'Applications are accepted in October, annually'. Not cross-checked against the provider page.","checkedAtUtc":"2026-10-10T12:00:00Z"},"duplicateChecked":{"urls":[],"rationale":"Title compared with all 115 catalog records and every row in this file using the app's bigram rule (threshold 0.85, 3-day window). Closest catalog title: 'Hinrich Foundation Trade Research Grants' at 0.506.","checkedAtUtc":"2026-10-10T12:00:00Z"}} | AO61: ["Locate the provider-owned listing and the official application link","Confirm no application, processing or placement fee on the official page","Confirm no inappropriate sensitive-data request on the official page","Confirm closing date and timezone on the official page","Whether the programme is still active","Current window dates","Grant size"] | AP61: Source page is old (about 563 days). Confirm the foundation still operates this programme and the current October window. | AQ61: =FALSE() | AR61: east_africa | AS61: grantstation.com | AT61: lead_no_deadline | AU61: unresolved | AV61: 2026-10-12T09:15:53Z
A62: agnes-bayer-science-foundation-research-grant-2026 | C62: create | D62: AGNES-BAYER Science Foundation Research Grant 2026 | E62: African-German Network of Excellence in Science (AGNES) with Bayer Science Foundation | H62: grant | I62: individual | J62: Research grant focused on biodiversity conservation and sustainable agriculture in sub-Saharan Africa. | N62: Sub-Saharan Africa | O62: ["Sub-Saharan Africa"] | R62: unknown | Y62: fixed | Z62: Apply as described on the source listing; the official application route is not yet confirmed. | AB62: https://www2.fundsforngos.org/tag/uganda/ | AC62: [] | AE62: 2026-10-10T12:00:00Z | AF62: scraped | AG62: pending | AH62: =FALSE() | AI62: =FALSE() | AJ62: =FALSE() | AK62: =FALSE() | AL62: =TRUE() | AM62: {"sourceAuthentic":{"urls":["https://www2.fundsforngos.org/tag/uganda/"],"rationale":"Seen on fundsforNGOs, a third-party or index page. Provider-owned listing not yet located, so authenticity is unconfirmed.","checkedAtUtc":"2026-10-10T12:00:00Z"},"noInappropriateFees":{"urls":["https://www2.fundsforngos.org/tag/uganda/"],"rationale":"The summary text retrieved mentions no fee, but the provider page was not reviewed, so this is unconfirmed.","checkedAtUtc":"2026-10-10T12:00:00Z"},"noSensitiveDataAsk":{"urls":["https://www2.fundsforngos.org/tag/uganda/"],"rationale":"The retrieved summary asks for no passwords, codes or payments, but full application instructions were not reviewed.","checkedAtUtc":"2026-10-10T12:00:00Z"},"deadlinePlausible":{"urls":["https://www2.fundsforngos.org/tag/uganda/"],"rationale":"No closing date seen on the source. Not cross-checked against the provider page.","checkedAtUtc":"2026-10-10T12:00:00Z"},"duplicateChecked":{"urls":[],"rationale":"Title compared with all 115 catalog records and every row in this file using the app's bigram rule (threshold 0.85, 3-day window). Closest catalog title: 'Hinrich Foundation Trade Research Grants' at 0.619.","checkedAtUtc":"2026-10-10T12:00:00Z"}} | AO62: ["Locate the provider-owned listing and the official application link","Confirm no application, processing or placement fee on the official page","Confirm no inappropriate sensitive-data request on the official page","Confirm closing date and timezone on the official page","Deadline","Eligibility","Award size"] | AP62: Seen as a headline only. Deadline not captured. | AQ62: =FALSE() | AR62: africa | AS62: fundsforngos.org | AT62: lead_no_deadline | AU62: unresolved | AV62: 2026-10-12T09:15:53Z
A63: gates-cambridge-scholarship-2027-28 | C63: create | D63: Gates Cambridge Scholarship 2027/28 | E63: Gates Cambridge Trust, University of Cambridge | F63: https://www.gatescambridge.org/ | H63: scholarship | I63: individual | J63: Full-cost postgraduate scholarships at the University of Cambridge for about 70 to 80 outstanding applicants from outside the UK, roughly two thirds to PhD students. Applicants apply through the Cambridge postgraduate portal. | K63: {"additionalRequirements":["Citizen of a country outside the United Kingdom","Applying to an eligible postgraduate course at the University of Cambridge","Assessed on intellectual ability, reasons for choice of course, commitment to improving the lives of others and leadership potential"]} | N63: Cambridge, United Kingdom | O63: ["Any country outside the United Kingdom"] | R63: funded | S63: Described as full-cost funding. | U63: 46364 | V63: Either Tuesday 8th December 2026 or Wednesday 6th January 2027 depending on course; full application by 11:59pm UK time | W63: UK time (GMT in December) | X63: date | Y63: fixed | Z63: Submit one application for admission and funding through the University of Cambridge Graduate Application Portal. | AB63: https://www.opportunitiesforafricans.com/?p=102638 | AC63: ["https://propakistani.pk/edunation/?p=6764","https://globalscholarsguide.com/gates-cambridge-scholarship-2027/"] | AD63: 2026-09 | AE63: 2026-10-10T12:00:00Z | AF63: scraped | AG63: pending | AH63: =FALSE() | AI63: =FALSE() | AJ63: =FALSE() | AK63: =TRUE() | AL63: =TRUE() | AM63: {"sourceAuthentic":{"urls":["https://www.opportunitiesforafricans.com/?p=102638","https://propakistani.pk/edunation/?p=6764","https://globalscholarsguide.com/gates-cambridge-scholarship-2027/"],"rationale":"Seen on Opportunities for Africans (copy of official text), a third-party or index page. Provider-owned listing not yet located, so authenticity is unconfirmed.","checkedAtUtc":"2026-10-10T12:00:00Z"},"noInappropriateFees":{"urls":["https://www.opportunitiesforafricans.com/?p=102638"],"rationale":"The summary text retrieved mentions no fee, but the provider page was not reviewed, so this is unconfirmed.","checkedAtUtc":"2026-10-10T12:00:00Z"},"noSensitiveDataAsk":{"urls":["https://www.opportunitiesforafricans.com/?p=102638"],"rationale":"The retrieved summary asks for no passwords, codes or payments, but full application instructions were not reviewed.","checkedAtUtc":"2026-10-10T12:00:00Z"},"deadlinePlausible":{"urls":["https://www.opportunitiesforafricans.com/?p=102638"],"rationale":"Source states 'Either Tuesday 8th December 2026 or Wednesday 6th January 2027 depending on course; full application by 11:59pm UK time', which falls on or after the delivery date 2026-10-12. Not cross-checked against the provider page.","checkedAtUtc":"2026-10-10T12:00:00Z"},"duplicateChecked":{"urls":[],"rationale":"Title compared with all 115 catalog records and every row in this file using the app's bigram rule (threshold 0.85, 3-day window). Closest catalog title: '2027 Rhodes Scholarship for East Africa' at 0.571.","checkedAtUtc":"2026-10-10T12:00:00Z"}} | AN63: Cambridge may charge an application fee to the graduate portal; check and disclose. | AO63: ["Locate the provider-owned listing and the official application link","Confirm no application, processing or placement fee on the official page","Confirm no inappropriate sensitive-data request on the official page","Confirm closing date and timezone on the official page","Which deadline applies to a given course","Official page confirmation"] | AP63: Deadline is course-dependent (8 Dec 2026 or 6 Jan 2027). deadline_date holds the earlier date. US citizens resident in the US have a separate 14 Oct 2026 round. Cambridge may close courses early. | AQ63: =FALSE() | AR63: global | AS63: opportunitiesforafricans.com | AT63: open_with_deadline | AU63: unresolved | AV63: 2026-10-12T09:15:53Z
A64: daad-in-country-in-region-masters-2027 | C64: create | D64: DAAD In-Country/In-Region Master's Scholarship Programme 2027 intake | E64: German Academic Exchange Service (DAAD) | F64: https://www.daad.de/ | H64: scholarship | I64: individual | J64: DAAD scholarships for development-related Master's study at selected host institutions in Sub-Saharan Africa (including Uganda, Kenya, Tanzania, Rwanda, Ethiopia, Ghana, Malawi, Burkina Faso and others), for people planning teaching or research careers in higher education. | K64: {"additionalRequirements":["Graduate or postgraduate from Sub-Saharan Africa with a first academic degree","Intends a teaching or research career at a higher education institution in Sub-Saharan Africa","Women and candidates from less privileged regions are encouraged"]} | N64: Selected universities in Sub-Saharan Africa, including Uganda | O64: ["Sub-Saharan Africa"] | R64: funded | S64: Fact sheet lists monthly scholarship payments, tuition fees, annual research allowances and a possible research stay abroad (subject to funding). | U64: 46338 | V64: Application Deadline 12 Nov 2026 (aggregator); DAAD host institutions set their own dates | W64: unknown | X64: date | Y64: fixed | Z64: Apply as described on the source listing; the official application route is not yet confirmed. | AB64: https://www.scholarshipset.com/scholarships/daad-in-country-in-region-programme-scholarship-in-sub-saharan-africa-2027 | AC64: ["https://cooperation.ucad.sn/sites/default/files/ICIR_Fact%20Sheet_2027_1_compressed.pdf","https://www.opportunitiesforafricans.com/daad-in-country-in-region-masters-scholarship-programme-2026-2027/"] | AE64: 2026-10-10T12:00:00Z | AF64: scraped | AG64: pending | AH64: =FALSE() | AI64: =FALSE() | AJ64: =FALSE() | AK64: =TRUE() | AL64: =TRUE() | AM64: {"sourceAuthentic":{"urls":["https://www.scholarshipset.com/scholarships/daad-in-country-in-region-programme-scholarship-in-sub-saharan-africa-2027","https://cooperation.ucad.sn/sites/default/files/ICIR_Fact%20Sheet_2027_1_compressed.pdf","https://www.opportunitiesforafricans.com/daad-in-country-in-region-masters-scholarship-programme-2026-2027/"],"rationale":"Seen on ScholarshipSet, a third-party or index page. Provider-owned listing not yet located, so authenticity is unconfirmed.","checkedAtUtc":"2026-10-10T12:00:00Z"},"noInappropriateFees":{"urls":["https://www.scholarshipset.com/scholarships/daad-in-country-in-region-programme-scholarship-in-sub-saharan-africa-2027"],"rationale":"The summary text retrieved mentions no fee, but the provider page was not reviewed, so this is unconfirmed.","checkedAtUtc":"2026-10-10T12:00:00Z"},"noSensitiveDataAsk":{"urls":["https://www.scholarshipset.com/scholarships/daad-in-country-in-region-programme-scholarship-in-sub-saharan-africa-2027"],"rationale":"The retrieved summary asks for no passwords, codes or payments, but full application instructions were not reviewed.","checkedAtUtc":"2026-10-10T12:00:00Z"},"deadlinePlausible":{"urls":["https://www.scholarshipset.com/scholarships/daad-in-country-in-region-programme-scholarship-in-sub-saharan-africa-2027"],"rationale":"Source states 'Application Deadline 12 Nov 2026 (aggregator); DAAD host institutions set their own dates', which falls on or after the delivery date 2026-10-12. Not cross-checked against the provider page.","checkedAtUtc":"2026-10-10T12:00:00Z"},"duplicateChecked":{"urls":[],"rationale":"Title compared with all 115 catalog records and every row in this file using the app's bigram rule (threshold 0.85, 3-day window). Closest catalog title: 'ASU Mastercard Foundation Innovation and Technology Scholarship 2027/2028' at 0.591.","checkedAtUtc":"2026-10-10T12:00:00Z"}} | AO64: ["Locate the provider-owned listing and the official application link","Confirm no application, processing or placement fee on the official page","Confirm no inappropriate sensitive-data request on the official page","Confirm closing date and timezone on the official page","Per-host-institution deadlines","Official DAAD page confirmation","Which Ugandan host programmes participate"] | AP64: Conflict: another aggregator gives 29 April 2026 as the deadline for the 2026/27 intake. The 12 Nov 2026 date is for the 2027 intake per ScholarshipSet and Scholarship Tab. Confirm per host institution on DAAD and the host university pages. | AQ64: =FALSE() | AR64: east_africa | AS64: scholarshipset.com | AT64: open_with_deadline | AU64: unresolved | AV64: 2026-10-12T09:15:53Z
A65: princeton-in-africa-fellowship-2027-28 | B65: 77777777-7777-4777-8777-000000000016 | C65: update_existing | D65: Princeton in Africa Fellowship 2027/28 (Nexus applicants) | E65: Princeton in Africa | H65: fellowship | I65: individual | J65: Year-long fellowship placing young professionals with organisations across Africa with stipend funding. Nexus applicants come from African universities. | K65: {"additionalRequirements":["Young professionals or current undergraduates graduating by June of the application year (previous cycle wording)","Passport valid through the end of the fellowship year (previous cycle wording)"]} | N65: Various host countries in Africa | O65: ["African countries"] | R65: funded | S65: Stipend funding stated. | T65: 2026-10-27T03:59:00Z | U65: 46321 | V65: Monday 26 October 2026, 11:59 PM Eastern Daylight Time | W65: America/New_York (EDT, UTC-4) | X65: datetime | Y65: fixed | Z65: Apply as described on the source listing; the official application route is not yet confirmed. | AB65: https://scholarshipsforafricans.com/scholarships/princeton-in-africa-fellowship-2027-28 | AC65: ["https://www.opportunitiesforafricans.com/princeton-in-africa-fellowships-2026-2027/"] | AE65: 2026-10-10T12:00:00Z | AF65: scraped | AG65: pending | AH65: =FALSE() | AI65: =FALSE() | AJ65: =FALSE() | AK65: =TRUE() | AL65: =TRUE() | AM65: {"sourceAuthentic":{"urls":["https://scholarshipsforafricans.com/scholarships/princeton-in-africa-fellowship-2027-28","https://www.opportunitiesforafricans.com/princeton-in-africa-fellowships-2026-2027/"],"rationale":"Seen on Scholarships for Africans, a third-party or index page. Provider-owned listing not yet located, so authenticity is unconfirmed.","checkedAtUtc":"2026-10-10T12:00:00Z"},"noInappropriateFees":{"urls":["https://scholarshipsforafricans.com/scholarships/princeton-in-africa-fellowship-2027-28"],"rationale":"The summary text retrieved mentions no fee, but the provider page was not reviewed, so this is unconfirmed.","checkedAtUtc":"2026-10-10T12:00:00Z"},"noSensitiveDataAsk":{"urls":["https://scholarshipsforafricans.com/scholarships/princeton-in-africa-fellowship-2027-28"],"rationale":"The retrieved summary asks for no passwords, codes or payments, but full application instructions were not reviewed.","checkedAtUtc":"2026-10-10T12:00:00Z"},"deadlinePlausible":{"urls":["https://scholarshipsforafricans.com/scholarships/princeton-in-africa-fellowship-2027-28"],"rationale":"Source states 'Monday 26 October 2026, 11:59 PM Eastern Daylight Time', which falls on or after the delivery date 2026-10-12. Not cross-checked against the provider page.","checkedAtUtc":"2026-10-10T12:00:00Z"},"duplicateChecked":{"urls":[],"rationale":"Title compared with all 115 catalog records and every row in this file using the app's bigram rule (threshold 0.85, 3-day window). Closest catalog title: 'Princeton in Africa Nexus Fellowships' at 0.8.","checkedAtUtc":"2026-10-10T12:00:00Z"}} | AO65: ["Locate the provider-owned listing and the official application link","Confirm no application, processing or placement fee on the official page","Confirm no inappropriate sensitive-data request on the official page","Confirm closing date and timezone on the official page","Official page confirmation","Which date is correct (18 Oct in catalog, 26 Oct here)"] | AP65: Updates catalog record 'Princeton in Africa Nexus Fellowships' (catalog deadline 2026-10-18). The aggregator page is dated 28 Sep 2026 and gives 26 Oct (one graphic shows 27 Oct). Confirm on princetoninafrica.org. | AQ65: =FALSE() | AR65: africa | AS65: scholarshipsforafricans.com | AT65: open_with_deadline | AU65: unresolved | AV65: 2026-10-12T09:15:53Z
A66: giz-rwanda-young-economist-program-2026-10 | C66: create | D66: Young Economist Program | E66: GIZ Rwanda | F66: https://www.giz.de/ | H66: training | I66: individual | J66: Young economist programme advertised by GIZ Rwanda in Kigali. | N66: Kigali, Rwanda | R66: unknown | U66: 46318 | V66: Deadline 23-10-2026 | W66: unknown | X66: date | Y66: fixed | Z66: Apply as described on the source listing; the official application route is not yet confirmed. | AB66: https://www.jobinrwanda.com/ | AC66: [] | AD66: 2026-10-09 | AE66: 2026-10-10T12:00:00Z | AF66: scraped | AG66: pending | AH66: =FALSE() | AI66: =FALSE() | AJ66: =FALSE() | AK66: =TRUE() | AL66: =TRUE() | AM66: {"sourceAuthentic":{"urls":["https://www.jobinrwanda.com/"],"rationale":"Seen on Job in Rwanda (homepage; listing-specific URL needed), a third-party or index page. Provider-owned listing not yet located, so authenticity is unconfirmed.","checkedAtUtc":"2026-10-10T12:00:00Z"},"noInappropriateFees":{"urls":["https://www.jobinrwanda.com/"],"rationale":"The summary text retrieved mentions no fee, but the provider page was not reviewed, so this is unconfirmed.","checkedAtUtc":"2026-10-10T12:00:00Z"},"noSensitiveDataAsk":{"urls":["https://www.jobinrwanda.com/"],"rationale":"The retrieved summary asks for no passwords, codes or payments, but full application instructions were not reviewed.","checkedAtUtc":"2026-10-10T12:00:00Z"},"deadlinePlausible":{"urls":["https://www.jobinrwanda.com/"],"rationale":"Source states 'Deadline 23-10-2026', which falls on or after the delivery date 2026-10-12. Not cross-checked against the provider page.","checkedAtUtc":"2026-10-10T12:00:00Z"},"duplicateChecked":{"urls":[],"rationale":"Title compared with all 115 catalog records and every row in this file using the app's bigram rule (threshold 0.85, 3-day window). Closest catalog title: 'Programme Assistant - UNESCO Eastern Africa' at 0.407.","checkedAtUtc":"2026-10-10T12:00:00Z"}} | AO66: ["Locate the provider-owned listing and the official application link","Confirm no application, processing or placement fee on the official page","Confirm no inappropriate sensitive-data request on the official page","Confirm closing date and timezone on the official page","Listing-specific URL","Paid or unpaid","Eligibility"] | AP66: Source URL is the homepage only. Agent must find the listing-specific URL. | AQ66: =FALSE() | AR66: east_africa | AS66: jobinrwanda.com | AT66: open_with_deadline | AU66: unresolved | AV66: 2026-10-12T09:15:53Z
A67: hc-solutions-ai-workflow-automation-programme-2026-10 | C67: create | D67: AI Workflow Automation Programme | E67: HC Solutions Ltd | H67: training | I67: individual | J67: AI workflow automation training programme in Kigali. | N67: Kigali, Rwanda | R67: unknown | U67: 46320 | V67: Deadline 25-10-2026 | W67: unknown | X67: date | Y67: fixed | Z67: Apply as described on the source listing; the official application route is not yet confirmed. | AB67: https://www.jobinrwanda.com/ | AC67: [] | AD67: 2026-10-07 | AE67: 2026-10-10T12:00:00Z | AF67: scraped | AG67: pending | AH67: =FALSE() | AI67: =FALSE() | AJ67: =FALSE() | AK67: =TRUE() | AL67: =TRUE() | AM67: {"sourceAuthentic":{"urls":["https://www.jobinrwanda.com/"],"rationale":"Seen on Job in Rwanda (homepage; listing-specific URL needed), a third-party or index page. Provider-owned listing not yet located, so authenticity is unconfirmed.","checkedAtUtc":"2026-10-10T12:00:00Z"},"noInappropriateFees":{"urls":["https://www.jobinrwanda.com/"],"rationale":"The summary text retrieved mentions no fee, but the provider page was not reviewed, so this is unconfirmed.","checkedAtUtc":"2026-10-10T12:00:00Z"},"noSensitiveDataAsk":{"urls":["https://www.jobinrwanda.com/"],"rationale":"The retrieved summary asks for no passwords, codes or payments, but full application instructions were not reviewed.","checkedAtUtc":"2026-10-10T12:00:00Z"},"deadlinePlausible":{"urls":["https://www.jobinrwanda.com/"],"rationale":"Source states 'Deadline 25-10-2026', which falls on or after the delivery date 2026-10-12. Not cross-checked against the provider page.","checkedAtUtc":"2026-10-10T12:00:00Z"},"duplicateChecked":{"urls":[],"rationale":"Title compared with all 115 catalog records and every row in this file using the app's bigram rule (threshold 0.85, 3-day window). Closest catalog title: 'Smithsonian Institution Fellowship Program' at 0.412.","checkedAtUtc":"2026-10-10T12:00:00Z"}} | AN67: Possible tuition fee, not stated. | AO67: ["Locate the provider-owned listing and the official application link","Confirm no application, processing or placement fee on the official page","Confirm no inappropriate sensitive-data request on the official page","Confirm closing date and timezone on the official page","Listing-specific URL","Fees","Eligibility"] | AP67: Check whether the programme charges tuition (many 'programmes' are paid courses). | AQ67: =FALSE() | AR67: east_africa | AS67: jobinrwanda.com | AT67: open_with_deadline | AU67: unresolved | AV67: 2026-10-12T09:15:53Z
A68: rwanda-sous-chef-and-butler-2026-10 | C68: create | D68: Sous Chef and Butler | E68: Employer not named on source | H68: job | I68: individual | J68: Hospitality role (sous chef and butler) in Kigali, entry level with 1 to 3 years of experience. | K68: {"minimumExperienceMonths":12} | N68: Kigali, Rwanda | R68: unknown | U68: 46325 | V68: Deadline 30-10-2026 | W68: unknown | X68: date | Y68: fixed | Z68: Apply as described on the source listing; the official application route is not yet confirmed. | AB68: https://www.jobinrwanda.com/ | AC68: [] | AD68: 2026-09-29 | AE68: 2026-10-10T12:00:00Z | AF68: scraped | AG68: pending | AH68: =FALSE() | AI68: =FALSE() | AJ68: =FALSE() | AK68: =TRUE() | AL68: =TRUE() | AM68: {"sourceAuthentic":{"urls":["https://www.jobinrwanda.com/"],"rationale":"Seen on Job in Rwanda (homepage; listing-specific URL needed), a third-party or index page. Provider-owned listing not yet located, so authenticity is unconfirmed.","checkedAtUtc":"2026-10-10T12:00:00Z"},"noInappropriateFees":{"urls":["https://www.jobinrwanda.com/"],"rationale":"The summary text retrieved mentions no fee, but the provider page was not reviewed, so this is unconfirmed.","checkedAtUtc":"2026-10-10T12:00:00Z"},"noSensitiveDataAsk":{"urls":["https://www.jobinrwanda.com/"],"rationale":"The retrieved summary asks for no passwords, codes or payments, but full application instructions were not reviewed.","checkedAtUtc":"2026-10-10T12:00:00Z"},"deadlinePlausible":{"urls":["https://www.jobinrwanda.com/"],"rationale":"Source states 'Deadline 30-10-2026', which falls on or after the delivery date 2026-10-12. Not cross-checked against the provider page.","checkedAtUtc":"2026-10-10T12:00:00Z"},"duplicateChecked":{"urls":[],"rationale":"Title compared with all 115 catalog records and every row in this file using the app's bigram rule (threshold 0.85, 3-day window). Closest catalog title: 'Physics and Mathematics Teacher' at 0.372.","checkedAtUtc":"2026-10-10T12:00:00Z"}} | AO68: ["Locate the provider-owned listing and the official application link","Confirm no application, processing or placement fee on the official page","Confirm no inappropriate sensitive-data request on the official page","Confirm closing date and timezone on the official page","Employer identity","Listing-specific URL","Pay"] | AP68: minimumExperienceMonths set to 12 from the stated 1 to 3 years band (lower bound). | AQ68: =FALSE() | AR68: east_africa | AS68: jobinrwanda.com | AT68: open_with_deadline | AU68: unresolved | AV68: 2026-10-12T09:15:53Z
